Workbook

Sheet Summary
A1: Accrued Commissions - Unclaimed Property Exposure by Entity
A2: Source: United_Cash_Requirements.xlsx, each entity tab, 'Previous Month's Accrued Commissions' block (deposited checks not yet booked in Sage) plus the current-month 'Deposited checks' block. Extracted 10/6/2026; every entity total ties to the tab's 'outstanding amount' cell. Legend: blue = input, black = formula, green = link to another sheet, yellow fill = confirm or fill in.
A3: As-of date | B3: 46301
A4: Fee check amounts - all entities (inputs) | C4: 644 | D4: 1044 | E4: 69 | F4: 595 | G4: 995 | H4: 49 | I4: 110
A5: Additional fee amounts - Philly only (inputs) | C5: 495 | D5: 295
A6: Additional fee amounts - TUR only (inputs) | C6: 150 | D6: 250 | E6: 350 | F6: 450 | G6: 60 | H6: 179
A7: Small-amount threshold | B7: 250
A9: Entity | B9: State (confirm) | C9: Prior-month accrued (unbooked deposits) | D9: Current-month accrued (Sept/Oct 2026 deposits) | E9: Total accrued per workbook | F9: Items (count) | G9: 0-1 yrs | H9: 1-2 yrs | I9: 2-3 yrs | J9: 3-5 yrs | K9: 5+ yrs | L9: $ at fee amounts (presumed company revenue) | M9: $ small amounts (likely fee, review) | N9: $ memo-flagged (not ours / unknown / hold) | O9: $ larger amounts (likely includes agent commission) | P9: Short period (yrs) | Q9: Long period (yrs) | R9: Dormant today - SHORT test - ALL items | S9: Dormant today - LONG test - ALL items | T9: Dormant today - SHORT test - likely-commission + memo-flagged only | U9: Dormant today - LONG test - likely-commission + memo-flagged only | V9: Dormant at next report cutoff - SHORT - likely-commission + memo-flagged | W9: Dormant at next report cutoff - LONG - likely-commission + memo-flagged | X9: Likely test given independent-contractor agents | Y9: Dormant today - LIKELY test - likely-commission + memo-flagged | Z9: Dormant at next report cutoff - LIKELY test - likely-commission + memo-flagged | AA9: Oldest item | AB9: Entity-state note
A10: Dallas | B10: TX | C10: =SUMIFS(Detail!$H:$H,Detail!$A:$A,$A10) -> 59991.62 | D10: =SUMIFS('Current Month'!$F:$F,'Current Month'!$A:$A,$A10) -> 15586.87 | E10: =C10+D10 -> 75578.49 | F10: =COUNTIFS(Detail!$A:$A,$A10,Detail!$H:$H,"<>") -> 50 | G10: =SUMIFS(Detail!$H:$H,Detail!$A:$A,$A10,Detail!$L:$L,"0-1 yrs") -> 39767.62 | H10: =SUMIFS(Detail!$H:$H,Detail!$A:$A,$A10,Detail!$L:$L,"1-2 yrs") -> 6244.96 | I10: =SUMIFS(Detail!$H:$H,Detail!$A:$A,$A10,Detail!$L:$L,"2-3 yrs") -> 7179.74 | J10: =SUMIFS(Detail!$H:$H,Detail!$A:$A,$A10,Detail!$L:$L,"3-5 yrs") -> 6799.3 | K10: =SUMIFS(Detail!$H:$H,Detail!$A:$A,$A10,Detail!$L:$L,"5+ yrs") -> 0 | L10: =SUMIFS(Detail!$H:$H,Detail!$A:$A,$A10,Detail!$N:$N,"Fee amount*") -> 2401 | M10: =SUMIFS(Detail!$H:$H,Detail!$A:$A,$A10,Detail!$N:$N,"Small amount*") -> 622.08 | N10: =SUMIFS(Detail!$H:$H,Detail!$A:$A,$A10,Detail!$N:$N,"Memo flag*") -> 27321.63 | O10: =SUMIFS(Detail!$H:$H,Detail!$A:$A,$A10,Detail!$N:$N,"Larger amount*") -> 29646.91 | P10: =IFERROR(INDEX('State Rules'!$C$5:$C$11,MATCH($B10,'State Rules'!$A$5:$A$11,0)),"") -> 1 | Q10: =IFERROR(INDEX('State Rules'!$E$5:$E$11,MATCH($B10,'State Rules'!$A$5:$A$11,0)),"") -> 3 | R10: =SUMIFS(Detail!$H:$H,Detail!$A:$A,$A10,Detail!$P:$P,"<="&$B$3) -> 20224 | S10: =SUMIFS(Detail!$H:$H,Detail!$A:$A,$A10,Detail!$Q:$Q,"<="&$B$3) -> 6799.3 | T10: =SUMIFS(Detail!$AA:$AA,Detail!$A:$A,$A10,Detail!$P:$P,"<="&$B$3) -> 17639.54 | U10: =SUMIFS(Detail!$AA:$AA,Detail!$A:$A,$A10,Detail!$Q:$Q,"<="&$B$3) -> 6707.8 | V10: =SUMIFS(Detail!$AA:$AA,Detail!$A:$A,$A10,Detail!$R:$R,"Yes") -> 21952.66 | W10: =SUMIFS(Detail!$AA:$AA,Detail!$A:$A,$A10,Detail!$S:$S,"Yes") -> 8042.3 | X10: =IFERROR(INDEX('State Rules'!$M$5:$M$11,MATCH($B10,'State Rules'!$A$5:$A$11,0)),"") -> LONG | Y10: =IF(X10="SHORT",T10,IF(X10="LONG",U10,0)) -> 6707.8 | Z10: =IF(X10="SHORT",V10,IF(X10="LONG",W10,0)) -> 8042.3 | AA10: =IF(F10=0,"",_xlfn.MINIFS(Detail!$E$7:$E$400,Detail!$A$7:$A$400,$A10)) -> 44988 | AB10: Confirmed by user 10/6/2026: Texas. ICA names 'URE Dallas LLC dba United Real Estate'. State of formation not yet provided.
A11: Houston | B11: TX | C11: =SUMIFS(Detail!$H:$H,Detail!$A:$A,$A11) -> 76889.5 | D11: =SUMIFS('Current Month'!$F:$F,'Current Month'!$A:$A,$A11) -> 10071.93 | E11: =C11+D11 -> 86961.43 | F11: =COUNTIFS(Detail!$A:$A,$A11,Detail!$H:$H,"<>") -> 40 | G11: =SUMIFS(Detail!$H:$H,Detail!$A:$A,$A11,Detail!$L:$L,"0-1 yrs") -> 26416.5 | H11: =SUMIFS(Detail!$H:$H,Detail!$A:$A,$A11,Detail!$L:$L,"1-2 yrs") -> 35650.9 | I11: =SUMIFS(Detail!$H:$H,Detail!$A:$A,$A11,Detail!$L:$L,"2-3 yrs") -> 9185.5 | J11: =SUMIFS(Detail!$H:$H,Detail!$A:$A,$A11,Detail!$L:$L,"3-5 yrs") -> 5636.6 | K11: =SUMIFS(Detail!$H:$H,Detail!$A:$A,$A11,Detail!$L:$L,"5+ yrs") -> 0 | L11: =SUMIFS(Detail!$H:$H,Detail!$A:$A,$A11,Detail!$N:$N,"Fee amount*") -> 3669 | M11: =SUMIFS(Detail!$H:$H,Detail!$A:$A,$A11,Detail!$N:$N,"Small amount*") -> 450 | N11: =SUMIFS(Detail!$H:$H,Detail!$A:$A,$A11,Detail!$N:$N,"Memo flag*") -> 1875 | O11: =SUMIFS(Detail!$H:$H,Detail!$A:$A,$A11,Detail!$N:$N,"Larger amount*") -> 70895.5 | P11: =IFERROR(INDEX('State Rules'!$C$5:$C$11,MATCH($B11,'State Rules'!$A$5:$A$11,0)),"") -> 1 | Q11: =IFERROR(INDEX('State Rules'!$E$5:$E$11,MATCH($B11,'State Rules'!$A$5:$A$11,0)),"") -> 3 | R11: =SUMIFS(Detail!$H:$H,Detail!$A:$A,$A11,Detail!$P:$P,"<="&$B$3) -> 50473 | S11: =SUMIFS(Detail!$H:$H,Detail!$A:$A,$A11,Detail!$Q:$Q,"<="&$B$3) -> 5636.6 | T11: =SUMIFS(Detail!$AA:$AA,Detail!$A:$A,$A11,Detail!$P:$P,"<="&$B$3) -> 48286 | U11: =SUMIFS(Detail!$AA:$AA,Detail!$A:$A,$A11,Detail!$Q:$Q,"<="&$B$3) -> 5636.6 | V11: =SUMIFS(Detail!$AA:$AA,Detail!$A:$A,$A11,Detail!$R:$R,"Yes") -> 49136 | W11: =SUMIFS(Detail!$AA:$AA,Detail!$A:$A,$A11,Detail!$S:$S,"Yes") -> 6011.6 | X11: =IFERROR(INDEX('State Rules'!$M$5:$M$11,MATCH($B11,'State Rules'!$A$5:$A$11,0)),"") -> LONG | Y11: =IF(X11="SHORT",T11,IF(X11="LONG",U11,0)) -> 5636.6 | Z11: =IF(X11="SHORT",V11,IF(X11="LONG",W11,0)) -> 6011.6 | AA11: =IF(F11=0,"",_xlfn.MINIFS(Detail!$E$7:$E$400,Detail!$A$7:$A$400,$A11)) -> 44592 | AB11: Confirmed by user 10/6/2026: Texas. ICA names 'URE Houston LLC d/b/a United Real Estate'. State of formation not yet provided.
A12: TUR | B12: TX | C12: =SUMIFS(Detail!$H:$H,Detail!$A:$A,$A12) -> 55528.45 | D12: =SUMIFS('Current Month'!$F:$F,'Current Month'!$A:$A,$A12) -> 20054.2 | E12: =C12+D12 -> 75582.65 | F12: =COUNTIFS(Detail!$A:$A,$A12,Detail!$H:$H,"<>") -> 50 | G12: =SUMIFS(Detail!$H:$H,Detail!$A:$A,$A12,Detail!$L:$L,"0-1 yrs") -> 34473 | H12: =SUMIFS(Detail!$H:$H,Detail!$A:$A,$A12,Detail!$L:$L,"1-2 yrs") -> 5539.51 | I12: =SUMIFS(Detail!$H:$H,Detail!$A:$A,$A12,Detail!$L:$L,"2-3 yrs") -> 13657.94 | J12: =SUMIFS(Detail!$H:$H,Detail!$A:$A,$A12,Detail!$L:$L,"3-5 yrs") -> 1858 | K12: =SUMIFS(Detail!$H:$H,Detail!$A:$A,$A12,Detail!$L:$L,"5+ yrs") -> 0 | L12: =SUMIFS(Detail!$H:$H,Detail!$A:$A,$A12,Detail!$N:$N,"Fee amount*") -> 5684 | M12: =SUMIFS(Detail!$H:$H,Detail!$A:$A,$A12,Detail!$N:$N,"Small amount*") -> 1034.25 | N12: =SUMIFS(Detail!$H:$H,Detail!$A:$A,$A12,Detail!$N:$N,"Memo flag*") -> 1444 | O12: =SUMIFS(Detail!$H:$H,Detail!$A:$A,$A12,Detail!$N:$N,"Larger amount*") -> 47366.2 | P12: =IFERROR(INDEX('State Rules'!$C$5:$C$11,MATCH($B12,'State Rules'!$A$5:$A$11,0)),"") -> 1 | Q12: =IFERROR(INDEX('State Rules'!$E$5:$E$11,MATCH($B12,'State Rules'!$A$5:$A$11,0)),"") -> 3 | R12: =SUMIFS(Detail!$H:$H,Detail!$A:$A,$A12,Detail!$P:$P,"<="&$B$3) -> 21055.45 | S12: =SUMIFS(Detail!$H:$H,Detail!$A:$A,$A12,Detail!$Q:$Q,"<="&$B$3) -> 1858 | T12: =SUMIFS(Detail!$AA:$AA,Detail!$A:$A,$A12,Detail!$P:$P,"<="&$B$3) -> 14486.2 | U12: =SUMIFS(Detail!$AA:$AA,Detail!$A:$A,$A12,Detail!$Q:$Q,"<="&$B$3) -> 1188 | V12: =SUMIFS(Detail!$AA:$AA,Detail!$A:$A,$A12,Detail!$R:$R,"Yes") -> 15883.7 | W12: =SUMIFS(Detail!$AA:$AA,Detail!$A:$A,$A12,Detail!$S:$S,"Yes") -> 2917.5 | X12: =IFERROR(INDEX('State Rules'!$M$5:$M$11,MATCH($B12,'State Rules'!$A$5:$A$11,0)),"") -> LONG | Y12: =IF(X12="SHORT",T12,IF(X12="LONG",U12,0)) -> 1188 | Z12: =IF(X12="SHORT",V12,IF(X12="LONG",W12,0)) -> 2917.5 | AA12: =IF(F12=0,"",_xlfn.MINIFS(Detail!$E$7:$E$400,Detail!$A$7:$A$400,$A12)) -> 44951 | AB12: Confirmed by user 10/6/2026: Texas. Sign-up docs name 'Quick-Close Properties, LLC dba Texas United Realty' (TREC 599460). State of formation not yet provided.
A13: Chicago | B13: IL | C13: =SUMIFS(Detail!$H:$H,Detail!$A:$A,$A13) -> 0 | D13: =SUMIFS('Current Month'!$F:$F,'Current Month'!$A:$A,$A13) -> 18345 | E13: =C13+D13 -> 18345 | F13: =COUNTIFS(Detail!$A:$A,$A13,Detail!$H:$H,"<>") -> 0 | G13: =SUMIFS(Detail!$H:$H,Detail!$A:$A,$A13,Detail!$L:$L,"0-1 yrs") -> 0 | H13: =SUMIFS(Detail!$H:$H,Detail!$A:$A,$A13,Detail!$L:$L,"1-2 yrs") -> 0 | I13: =SUMIFS(Detail!$H:$H,Detail!$A:$A,$A13,Detail!$L:$L,"2-3 yrs") -> 0 | J13: =SUMIFS(Detail!$H:$H,Detail!$A:$A,$A13,Detail!$L:$L,"3-5 yrs") -> 0 | K13: =SUMIFS(Detail!$H:$H,Detail!$A:$A,$A13,Detail!$L:$L,"5+ yrs") -> 0 | L13: =SUMIFS(Detail!$H:$H,Detail!$A:$A,$A13,Detail!$N:$N,"Fee amount*") -> 0 | M13: =SUMIFS(Detail!$H:$H,Detail!$A:$A,$A13,Detail!$N:$N,"Small amount*") -> 0 | N13: =SUMIFS(Detail!$H:$H,Detail!$A:$A,$A13,Detail!$N:$N,"Memo flag*") -> 0 | O13: =SUMIFS(Detail!$H:$H,Detail!$A:$A,$A13,Detail!$N:$N,"Larger amount*") -> 0 | P13: =IFERROR(INDEX('State Rules'!$C$5:$C$11,MATCH($B13,'State Rules'!$A$5:$A$11,0)),"") -> 1 | Q13: =IFERROR(INDEX('State Rules'!$E$5:$E$11,MATCH($B13,'State Rules'!$A$5:$A$11,0)),"") -> 3 | R13: =SUMIFS(Detail!$H:$H,Detail!$A:$A,$A13,Detail!$P:$P,"<="&$B$3) -> 0 | S13: =SUMIFS(Detail!$H:$H,Detail!$A:$A,$A13,Detail!$Q:$Q,"<="&$B$3) -> 0 | T13: =SUMIFS(Detail!$AA:$AA,Detail!$A:$A,$A13,Detail!$P:$P,"<="&$B$3) -> 0 | U13: =SUMIFS(Detail!$AA:$AA,Detail!$A:$A,$A13,Detail!$Q:$Q,"<="&$B$3) -> 0 | V13: =SUMIFS(Detail!$AA:$AA,Detail!$A:$A,$A13,Detail!$R:$R,"Yes") -> 0 | W13: =SUMIFS(Detail!$AA:$AA,Detail!$A:$A,$A13,Detail!$S:$S,"Yes") -> 0 | X13: =IFERROR(INDEX('State Rules'!$M$5:$M$11,MATCH($B13,'State Rules'!$A$5:$A$11,0)),"") -> SHORT | Y13: =IF(X13="SHORT",T13,IF(X13="LONG",U13,0)) -> 0 | Z13: =IF(X13="SHORT",V13,IF(X13="LONG",W13,0)) -> 0 | AA13: =IF(F13=0,"",_xlfn.MINIFS(Detail!$E$7:$E$400,Detail!$A$7:$A$400,$A13)) | AB13: Confirmed by user 10/6/2026: Illinois. ICA names 'URE Chicago LLC dba United Real Estate - Chicago'. State of formation not yet provided.
A14: Philly | B14: PA | C14: =SUMIFS(Detail!$H:$H,Detail!$A:$A,$A14) -> 29708.78 | D14: =SUMIFS('Current Month'!$F:$F,'Current Month'!$A:$A,$A14) -> 49091.5 | E14: =C14+D14 -> 78800.28 | F14: =COUNTIFS(Detail!$A:$A,$A14,Detail!$H:$H,"<>") -> 34 | G14: =SUMIFS(Detail!$H:$H,Detail!$A:$A,$A14,Detail!$L:$L,"0-1 yrs") -> 8931.12 | H14: =SUMIFS(Detail!$H:$H,Detail!$A:$A,$A14,Detail!$L:$L,"1-2 yrs") -> 10077.25 | I14: =SUMIFS(Detail!$H:$H,Detail!$A:$A,$A14,Detail!$L:$L,"2-3 yrs") -> 10281.06 | J14: =SUMIFS(Detail!$H:$H,Detail!$A:$A,$A14,Detail!$L:$L,"3-5 yrs") -> 419.35 | K14: =SUMIFS(Detail!$H:$H,Detail!$A:$A,$A14,Detail!$L:$L,"5+ yrs") -> 0 | L14: =SUMIFS(Detail!$H:$H,Detail!$A:$A,$A14,Detail!$N:$N,"Fee amount*") -> 6592 | M14: =SUMIFS(Detail!$H:$H,Detail!$A:$A,$A14,Detail!$N:$N,"Small amount*") -> 252 | N14: =SUMIFS(Detail!$H:$H,Detail!$A:$A,$A14,Detail!$N:$N,"Memo flag*") -> 0 | O14: =SUMIFS(Detail!$H:$H,Detail!$A:$A,$A14,Detail!$N:$N,"Larger amount*") -> 22864.78 | P14: =IFERROR(INDEX('State Rules'!$C$5:$C$11,MATCH($B14,'State Rules'!$A$5:$A$11,0)),"") -> 2 | Q14: =IFERROR(INDEX('State Rules'!$E$5:$E$11,MATCH($B14,'State Rules'!$A$5:$A$11,0)),"") -> 3 | R14: =SUMIFS(Detail!$H:$H,Detail!$A:$A,$A14,Detail!$P:$P,"<="&$B$3) -> 10700.41 | S14: =SUMIFS(Detail!$H:$H,Detail!$A:$A,$A14,Detail!$Q:$Q,"<="&$B$3) -> 419.35 | T14: =SUMIFS(Detail!$AA:$AA,Detail!$A:$A,$A14,Detail!$P:$P,"<="&$B$3) -> 8566.41 | U14: =SUMIFS(Detail!$AA:$AA,Detail!$A:$A,$A14,Detail!$Q:$Q,"<="&$B$3) -> 419.35 | V14: =SUMIFS(Detail!$AA:$AA,Detail!$A:$A,$A14,Detail!$R:$R,"Yes") -> 12172.66 | W14: =SUMIFS(Detail!$AA:$AA,Detail!$A:$A,$A14,Detail!$S:$S,"Yes") -> 419.35 | X14: =IFERROR(INDEX('State Rules'!$M$5:$M$11,MATCH($B14,'State Rules'!$A$5:$A$11,0)),"") -> SHORT | Y14: =IF(X14="SHORT",T14,IF(X14="LONG",U14,0)) -> 8566.41 | Z14: =IF(X14="SHORT",V14,IF(X14="LONG",W14,0)) -> 12172.66 | AA14: =IF(F14=0,"",_xlfn.MINIFS(Detail!$E$7:$E$400,Detail!$A$7:$A$400,$A14)) -> 45175 | AB14: Confirmed by user 10/6/2026: Pennsylvania. PA ICA names only 'United Real Estate'; legal entity and state of formation not yet provided.
A15: Gallery | B15: FL | C15: =SUMIFS(Detail!$H:$H,Detail!$A:$A,$A15) -> 4001.11 | D15: =SUMIFS('Current Month'!$F:$F,'Current Month'!$A:$A,$A15) -> 0 | E15: =C15+D15 -> 4001.11 | F15: =COUNTIFS(Detail!$A:$A,$A15,Detail!$H:$H,"<>") -> 4 | G15: =SUMIFS(Detail!$H:$H,Detail!$A:$A,$A15,Detail!$L:$L,"0-1 yrs") -> 4001.11 | H15: =SUMIFS(Detail!$H:$H,Detail!$A:$A,$A15,Detail!$L:$L,"1-2 yrs") -> 0 | I15: =SUMIFS(Detail!$H:$H,Detail!$A:$A,$A15,Detail!$L:$L,"2-3 yrs") -> 0 | J15: =SUMIFS(Detail!$H:$H,Detail!$A:$A,$A15,Detail!$L:$L,"3-5 yrs") -> 0 | K15: =SUMIFS(Detail!$H:$H,Detail!$A:$A,$A15,Detail!$L:$L,"5+ yrs") -> 0 | L15: =SUMIFS(Detail!$H:$H,Detail!$A:$A,$A15,Detail!$N:$N,"Fee amount*") -> 0 | M15: =SUMIFS(Detail!$H:$H,Detail!$A:$A,$A15,Detail!$N:$N,"Small amount*") -> 0 | N15: =SUMIFS(Detail!$H:$H,Detail!$A:$A,$A15,Detail!$N:$N,"Memo flag*") -> 0 | O15: =SUMIFS(Detail!$H:$H,Detail!$A:$A,$A15,Detail!$N:$N,"Larger amount*") -> 4001.11 | P15: =IFERROR(INDEX('State Rules'!$C$5:$C$11,MATCH($B15,'State Rules'!$A$5:$A$11,0)),"") -> 1 | Q15: =IFERROR(INDEX('State Rules'!$E$5:$E$11,MATCH($B15,'State Rules'!$A$5:$A$11,0)),"") -> 5 | R15: =SUMIFS(Detail!$H:$H,Detail!$A:$A,$A15,Detail!$P:$P,"<="&$B$3) -> 0 | S15: =SUMIFS(Detail!$H:$H,Detail!$A:$A,$A15,Detail!$Q:$Q,"<="&$B$3) -> 0 | T15: =SUMIFS(Detail!$AA:$AA,Detail!$A:$A,$A15,Detail!$P:$P,"<="&$B$3) -> 0 | U15: =SUMIFS(Detail!$AA:$AA,Detail!$A:$A,$A15,Detail!$Q:$Q,"<="&$B$3) -> 0 | V15: =SUMIFS(Detail!$AA:$AA,Detail!$A:$A,$A15,Detail!$R:$R,"Yes") -> 0 | W15: =SUMIFS(Detail!$AA:$AA,Detail!$A:$A,$A15,Detail!$S:$S,"Yes") -> 0 | X15: =IFERROR(INDEX('State Rules'!$M$5:$M$11,MATCH($B15,'State Rules'!$A$5:$A$11,0)),"") -> LONG | Y15: =IF(X15="SHORT",T15,IF(X15="LONG",U15,0)) -> 0 | Z15: =IF(X15="SHORT",V15,IF(X15="LONG",W15,0)) -> 0 | AA15: =IF(F15=0,"",_xlfn.MINIFS(Detail!$E$7:$E$400,Detail!$A$7:$A$400,$A15)) -> 46156 | AB15: Confirmed by user 10/6/2026: Florida. LLC; state of formation not yet provided.
A16: Leading Edge | B16: AL | C16: =SUMIFS(Detail!$H:$H,Detail!$A:$A,$A16) -> 645 | D16: =SUMIFS('Current Month'!$F:$F,'Current Month'!$A:$A,$A16) -> 31392.5 | E16: =C16+D16 -> 32037.5 | F16: =COUNTIFS(Detail!$A:$A,$A16,Detail!$H:$H,"<>") -> 3 | G16: =SUMIFS(Detail!$H:$H,Detail!$A:$A,$A16,Detail!$L:$L,"0-1 yrs") -> 645 | H16: =SUMIFS(Detail!$H:$H,Detail!$A:$A,$A16,Detail!$L:$L,"1-2 yrs") -> 0 | I16: =SUMIFS(Detail!$H:$H,Detail!$A:$A,$A16,Detail!$L:$L,"2-3 yrs") -> 0 | J16: =SUMIFS(Detail!$H:$H,Detail!$A:$A,$A16,Detail!$L:$L,"3-5 yrs") -> 0 | K16: =SUMIFS(Detail!$H:$H,Detail!$A:$A,$A16,Detail!$L:$L,"5+ yrs") -> 0 | L16: =SUMIFS(Detail!$H:$H,Detail!$A:$A,$A16,Detail!$N:$N,"Fee amount*") -> 0 | M16: =SUMIFS(Detail!$H:$H,Detail!$A:$A,$A16,Detail!$N:$N,"Small amount*") -> 250 | N16: =SUMIFS(Detail!$H:$H,Detail!$A:$A,$A16,Detail!$N:$N,"Memo flag*") -> 0 | O16: =SUMIFS(Detail!$H:$H,Detail!$A:$A,$A16,Detail!$N:$N,"Larger amount*") -> 395 | P16: =IFERROR(INDEX('State Rules'!$C$5:$C$11,MATCH($B16,'State Rules'!$A$5:$A$11,0)),"") -> 1 | Q16: =IFERROR(INDEX('State Rules'!$E$5:$E$11,MATCH($B16,'State Rules'!$A$5:$A$11,0)),"") -> 3 | R16: =SUMIFS(Detail!$H:$H,Detail!$A:$A,$A16,Detail!$P:$P,"<="&$B$3) -> 0 | S16: =SUMIFS(Detail!$H:$H,Detail!$A:$A,$A16,Detail!$Q:$Q,"<="&$B$3) -> 0 | T16: =SUMIFS(Detail!$AA:$AA,Detail!$A:$A,$A16,Detail!$P:$P,"<="&$B$3) -> 0 | U16: =SUMIFS(Detail!$AA:$AA,Detail!$A:$A,$A16,Detail!$Q:$Q,"<="&$B$3) -> 0 | V16: =SUMIFS(Detail!$AA:$AA,Detail!$A:$A,$A16,Detail!$R:$R,"Yes") -> 395 | W16: =SUMIFS(Detail!$AA:$AA,Detail!$A:$A,$A16,Detail!$S:$S,"Yes") -> 0 | X16: =IFERROR(INDEX('State Rules'!$M$5:$M$11,MATCH($B16,'State Rules'!$A$5:$A$11,0)),"") -> SHORT | Y16: =IF(X16="SHORT",T16,IF(X16="LONG",U16,0)) -> 0 | Z16: =IF(X16="SHORT",V16,IF(X16="LONG",W16,0)) -> 395 | AA16: =IF(F16=0,"",_xlfn.MINIFS(Detail!$E$7:$E$400,Detail!$A$7:$A$400,$A16)) -> 46113 | AB16: Confirmed by user 10/6/2026: Alabama. LLC; state of formation not yet provided.
A17: DC | B17: DC | C17: =SUMIFS(Detail!$H:$H,Detail!$A:$A,$A17) -> 0 | D17: =SUMIFS('Current Month'!$F:$F,'Current Month'!$A:$A,$A17) -> 0 | E17: =C17+D17 -> 0 | F17: =COUNTIFS(Detail!$A:$A,$A17,Detail!$H:$H,"<>") -> 0 | G17: =SUMIFS(Detail!$H:$H,Detail!$A:$A,$A17,Detail!$L:$L,"0-1 yrs") -> 0 | H17: =SUMIFS(Detail!$H:$H,Detail!$A:$A,$A17,Detail!$L:$L,"1-2 yrs") -> 0 | I17: =SUMIFS(Detail!$H:$H,Detail!$A:$A,$A17,Detail!$L:$L,"2-3 yrs") -> 0 | J17: =SUMIFS(Detail!$H:$H,Detail!$A:$A,$A17,Detail!$L:$L,"3-5 yrs") -> 0 | K17: =SUMIFS(Detail!$H:$H,Detail!$A:$A,$A17,Detail!$L:$L,"5+ yrs") -> 0 | L17: =SUMIFS(Detail!$H:$H,Detail!$A:$A,$A17,Detail!$N:$N,"Fee amount*") -> 0 | M17: =SUMIFS(Detail!$H:$H,Detail!$A:$A,$A17,Detail!$N:$N,"Small amount*") -> 0 | N17: =SUMIFS(Detail!$H:$H,Detail!$A:$A,$A17,Detail!$N:$N,"Memo flag*") -> 0 | O17: =SUMIFS(Detail!$H:$H,Detail!$A:$A,$A17,Detail!$N:$N,"Larger amount*") -> 0 | P17: =IFERROR(INDEX('State Rules'!$C$5:$C$11,MATCH($B17,'State Rules'!$A$5:$A$11,0)),"") -> 0 | Q17: =IFERROR(INDEX('State Rules'!$E$5:$E$11,MATCH($B17,'State Rules'!$A$5:$A$11,0)),"") -> 0 | R17: =SUMIFS(Detail!$H:$H,Detail!$A:$A,$A17,Detail!$P:$P,"<="&$B$3) -> 0 | S17: =SUMIFS(Detail!$H:$H,Detail!$A:$A,$A17,Detail!$Q:$Q,"<="&$B$3) -> 0 | T17: =SUMIFS(Detail!$AA:$AA,Detail!$A:$A,$A17,Detail!$P:$P,"<="&$B$3) -> 0 | U17: =SUMIFS(Detail!$AA:$AA,Detail!$A:$A,$A17,Detail!$Q:$Q,"<="&$B$3) -> 0 | V17: =SUMIFS(Detail!$AA:$AA,Detail!$A:$A,$A17,Detail!$R:$R,"Yes") -> 0 | W17: =SUMIFS(Detail!$AA:$AA,Detail!$A:$A,$A17,Detail!$S:$S,"Yes") -> 0 | X17: =IFERROR(INDEX('State Rules'!$M$5:$M$11,MATCH($B17,'State Rules'!$A$5:$A$11,0)),"") -> 0 | Y17: =IF(X17="SHORT",T17,IF(X17="LONG",U17,0)) -> 0 | Z17: =IF(X17="SHORT",V17,IF(X17="LONG",W17,0)) -> 0 | AA17: =IF(F17=0,"",_xlfn.MINIFS(Detail!$E$7:$E$400,Detail!$A$7:$A$400,$A17)) | AB17: Tab exists in workbook with $0 accrued balance; user did not list DC. No DC rules researched.
A18: TOTAL | C18: =SUM(C10:C17) -> 226764.46 | D18: =SUM(D10:D17) -> 144542 | E18: =SUM(E10:E17) -> 371306.46 | F18: =SUM(F10:F17) -> 181 | G18: =SUM(G10:G17) -> 114234.35 | H18: =SUM(H10:H17) -> 57512.62 | I18: =SUM(I10:I17) -> 40304.24 | J18: =SUM(J10:J17) -> 14713.25 | ... O18: =SUM(O10:O17) -> 175169.5 | R18: =SUM(R10:R17) -> 102452.86 | S18: =SUM(S10:S17) -> 14713.25 | T18: =SUM(T10:T17) -> 88978.15 | U18: =SUM(U10:U17) -> 13951.75 | V18: =SUM(V10:V17) -> 99540.02 | W18: =SUM(W10:W17) -> 17390.75 | Y18: =SUM(Y10:Y17) -> 22098.81 | Z18: =SUM(Z10:Z17) -> 29539.06
A20: How to read this
A21: Classification (Detail col N) uses the fee amounts in rows 4-6 and the threshold in B7: an exact fee amount = presumed company revenue (keep; book to revenue, not unclaimed property). At or under the threshold = likely fee, review. Memo-flagged = memo says not ours / unknown agent / duplicate / legal hold (owed back to the payer or needs resolution). Everything else = larger amount that likely includes an agent's commission split - this is the unclaimed-property population.
A22: Columns R-S apply the dormancy tests to ALL unbooked items (upper bound). Columns T-W apply them only to the likely-commission and memo-flagged items. Even the T-W figures are upper bounds: within a larger check, only the agent's share (typically the check less the company's fee / split) is reportable; the company's share is revenue.
A23: SHORT test = the state's period for wages / compensation for personal services. LONG test = the general catch-all period. Column X picks the likely test per state now that agents are confirmed to be independent contractors (Texas and Florida: LONG; Illinois, Pennsylvania, Alabama: SHORT), and columns Y-Z apply it. See State Rules cols M-N for the reasoning; it is a legal judgment for counsel to confirm.
A24: Unknown agent = second priority rule. The user confirmed that many older checks cannot be tied to an agent. Those items do not become the company's; they are reportable to the state where the holding LLC was formed (still to be provided). If an LLC is formed in its office state, nothing changes; if formed elsewhere (e.g. Missouri or Delaware), that state's rules and report cycle apply to the unknown-owner items.
A25: Current-month accrued (column D) is all September/October 2026 deposits in normal matching workflow. It is included so the total ties to the cash-requirements Summary, but none of it is near any dormancy period.
A26: Nothing here is legal advice. Dormancy periods, report dates and due-diligence rules on the State Rules tab were sourced from statute summaries and state guidance found by web search; the statute pages themselves could not be opened from this session. Have counsel or your unclaimed-property advisor confirm before filing.

Sheet Detail
A1: Unbooked deposited checks - item detail (prior-month accrued commissions block of each entity tab)
A2: Columns A-J are copied from the source workbook. K-S and Z-AA are formulas. T-Y (yellow) are for you to fill in from Paperless Pipeline / Sage: once the agent share is entered, column Z shows the dollar amount that is both dormant (long test) and owed to someone else. Column AA is the heuristic stand-in until then.
A3: Classification (col N) is driven by Summary rows 4-6 (fee amounts, with Philly-only and TUR-only lists) and Summary B7 (small-amount threshold). Col M flags memos that say not ours / unknown agent / duplicate / legal hold / '?'. Classifications are hints, not conclusions.
A4: As-of date (linked) | B4: =Summary!$B$3 -> 46301
A6: Entity | B6: State | C6: Bank / block | D6: Source row | E6: Deposit date | F6: Check # | G6: Payer / check writer | H6: Amount | I6: Memo (source) | J6: Booked in Sage? | K6: Age (yrs) | L6: Age bucket | M6: Memo flag? | N6: Classification | O6: Short period (yrs) | P6: Dormant date - SHORT | Q6: Dormant date - LONG | R6: Dormant at next cutoff - SHORT? | S6: Dormant at next cutoff - LONG? | T6: Agent / owner name (fill in) | U6: Owner last-known state (fill in) | V6: Brokerage fee / E&O share $ (fill in) | W6: Agent share $ (fill in) | X6: Refund to payer $ (fill in) | Y6: Resolution / status (fill in) | Z6: Reportable if dormant (LONG test) = agent + refund share (from fill-in) | AA6: Heuristic reportable population $ (larger-amount + memo-flagged items)
A7: Dallas | B7: =IFERROR(INDEX(Summary!$B$10:$B$17,MATCH($A7,Summary!$A$10:$A$17,0)),"") -> TX | C7: Dallas | D7: 21 | E7: 44988 | F7: 1839 | G7: Jogip Management | H7: 1097.5 | I7: Vera Garza2538 Emmett St-agent hasn’t uploaded docs, emailed again | J7: No | K7: =IF(E7="","",($B$4-E7)/365.25) -> 3.5947981 | L7: =IF(K7="","no date",IF(K7<1,"0-1 yrs",IF(K7<2,"1-2 yrs",IF(K7<3,"2-3 yrs",IF(K7<5,"3-5 yrs","5+ yrs"))))) -> 3-5 yrs | M7: No | N7: =IF(M7="Yes","Memo flag - not ours / unknown / hold: resolve",IF(OR(COUNTIF(Summary!$C$4:$L$4,H7)>0,AND(A7="Philly",COUNTIF(Summary!$C$5:$L$5,H7)>0),AND(A7="TUR",COUNTIF(Summary!$C$6:$L$6,H7)>0)),"Fee amount - presumed company revenue",IF(H7<=Summary!$B$7,"Small amount - likely fee, review","Larger amount - likely includes agent commission"))) -> Larger amount - likely includes agent commission | O7: =IFERROR(INDEX('State Rules'!$C$5:$C$11,MATCH($B7,'State Rules'!$A$5:$A$11,0)),"") -> 1 | P7: =IF(OR(O7="",E7=""),"",EDATE(E7,12*O7)) -> 45354 | Q7: =IF(E7="","",IFERROR(EDATE(E7,12*INDEX('State Rules'!$E$5:$E$11,MATCH($B7,'State Rules'!$A$5:$A$11,0))),"")) -> 46084 | R7: =IF(P7="","",IFERROR(IF(P7<=INDEX('State Rules'!$I$5:$I$11,MATCH($B7,'State Rules'!$A$5:$A$11,0)),"Yes","No"),"")) -> Yes | S7: =IF(Q7="","",IFERROR(IF(Q7<=INDEX('State Rules'!$I$5:$I$11,MATCH($B7,'State Rules'!$A$5:$A$11,0)),"Yes","No"),"")) -> Yes | Z7: =IF(Q7="","",IF(Q7<=$B$4,N(W7)+N(X7),0)) -> 0 | AA7: =IF(OR(LEFT(N7,6)="Larger",LEFT(N7,4)="Memo"),H7,0) -> 1097.5
A8: Dallas | B8: =IFERROR(INDEX(Summary!$B$10:$B$17,MATCH($A8,Summary!$A$10:$A$17,0)),"") -> TX | C8: Dallas | D8: 22 | E8: 45035 | F8: 167928 | G8: Freedom Title | H8: 444 | I8: File 23067608FM-CC | J8: No | K8: =IF(E8="","",($B$4-E8)/365.25) -> 3.4661191 | L8: =IF(K8="","no date",IF(K8<1,"0-1 yrs",IF(K8<2,"1-2 yrs",IF(K8<3,"2-3 yrs",IF(K8<5,"3-5 yrs","5+ yrs"))))) -> 3-5 yrs | M8: No | N8: =IF(M8="Yes","Memo flag - not ours / unknown / hold: resolve",IF(OR(COUNTIF(Summary!$C$4:$L$4,H8)>0,AND(A8="Philly",COUNTIF(Summary!$C$5:$L$5,H8)>0),AND(A8="TUR",COUNTIF(Summary!$C$6:$L$6,H8)>0)),"Fee amount - presumed company revenue",IF(H8<=Summary!$B$7,"Small amount - likely fee, review","Larger amount - likely includes agent commission"))) -> Larger amount - likely includes agent commission | O8: =IFERROR(INDEX('State Rules'!$C$5:$C$11,MATCH($B8,'State Rules'!$A$5:$A$11,0)),"") -> 1 | P8: =IF(OR(O8="",E8=""),"",EDATE(E8,12*O8)) -> 45401 | Q8: =IF(E8="","",IFERROR(EDATE(E8,12*INDEX('State Rules'!$E$5:$E$11,MATCH($B8,'State Rules'!$A$5:$A$11,0))),"")) -> 46131 | R8: =IF(P8="","",IFERROR(IF(P8<=INDEX('State Rules'!$I$5:$I$11,MATCH($B8,'State Rules'!$A$5:$A$11,0)),"Yes","No"),"")) -> Yes | S8: =IF(Q8="","",IFERROR(IF(Q8<=INDEX('State Rules'!$I$5:$I$11,MATCH($B8,'State Rules'!$A$5:$A$11,0)),"Yes","No"),"")) -> Yes | Z8: =IF(Q8="","",IF(Q8<=$B$4,N(W8)+N(X8),0)) -> 0 | AA8: =IF(OR(LEFT(N8,6)="Larger",LEFT(N8,4)="Memo"),H8,0) -> 444
A9: Dallas | B9: =IFERROR(INDEX(Summary!$B$10:$B$17,MATCH($A9,Summary!$A$10:$A$17,0)),"") -> TX | C9: Dallas | D9: 23 | E9: 45051 | F9: 593095968 | G9: Chicago Title of Texas | H9: 2147.5 | J9: No | K9: =IF(E9="","",($B$4-E9)/365.25) -> 3.4223135 | L9: =IF(K9="","no date",IF(K9<1,"0-1 yrs",IF(K9<2,"1-2 yrs",IF(K9<3,"2-3 yrs",IF(K9<5,"3-5 yrs","5+ yrs"))))) -> 3-5 yrs | M9: No | N9: =IF(M9="Yes","Memo flag - not ours / unknown / hold: resolve",IF(OR(COUNTIF(Summary!$C$4:$L$4,H9)>0,AND(A9="Philly",COUNTIF(Summary!$C$5:$L$5,H9)>0),AND(A9="TUR",COUNTIF(Summary!$C$6:$L$6,H9)>0)),"Fee amount - presumed company revenue",IF(H9<=Summary!$B$7,"Small amount - likely fee, review","Larger amount - likely includes agent commission"))) -> Larger amount - likely includes agent commission | O9: =IFERROR(INDEX('State Rules'!$C$5:$C$11,MATCH($B9,'State Rules'!$A$5:$A$11,0)),"") -> 1 | P9: =IF(OR(O9="",E9=""),"",EDATE(E9,12*O9)) -> 45417 | Q9: =IF(E9="","",IFERROR(EDATE(E9,12*INDEX('State Rules'!$E$5:$E$11,MATCH($B9,'State Rules'!$A$5:$A$11,0))),"")) -> 46147 | R9: =IF(P9="","",IFERROR(IF(P9<=INDEX('State Rules'!$I$5:$I$11,MATCH($B9,'State Rules'!$A$5:$A$11,0)),"Yes","No"),"")) -> Yes | S9: =IF(Q9="","",IFERROR(IF(Q9<=INDEX('State Rules'!$I$5:$I$11,MATCH($B9,'State Rules'!$A$5:$A$11,0)),"Yes","No"),"")) -> Yes | Z9: =IF(Q9="","",IF(Q9<=$B$4,N(W9)+N(X9),0)) -> 0 | AA9: =IF(OR(LEFT(N9,6)="Larger",LEFT(N9,4)="Memo"),H9,0) -> 2147.5
A10: Dallas | B10: =IFERROR(INDEX(Summary!$B$10:$B$17,MATCH($A10,Summary!$A$10:$A$17,0)),"") -> TX | C10: Dallas | D10: 24 | E10: 45071 | F10: 15215 | G10: JARA INVESTMENTS INC | H10: 694.68 | J10: No | K10: =IF(E10="","",($B$4-E10)/365.25) -> 3.3675565 | L10: =IF(K10="","no date",IF(K10<1,"0-1 yrs",IF(K10<2,"1-2 yrs",IF(K10<3,"2-3 yrs",IF(K10<5,"3-5 yrs","5+ yrs"))))) -> 3-5 yrs | M10: No | N10: =IF(M10="Yes","Memo flag - not ours / unknown / hold: resolve",IF(OR(COUNTIF(Summary!$C$4:$L$4,H10)>0,AND(A10="Philly",COUNTIF(Summary!$C$5:$L$5,H10)>0),AND(A10="TUR",COUNTIF(Summary!$C$6:$L$6,H10)>0)),"Fee amount - presumed company revenue",IF(H10<=Summary!$B$7,"Small amount - likely fee, review","Larger amount - likely includes agent commission"))) -> Larger amount - likely includes agent commission | O10: =IFERROR(INDEX('State Rules'!$C$5:$C$11,MATCH($B10,'State Rules'!$A$5:$A$11,0)),"") -> 1 | P10: =IF(OR(O10="",E10=""),"",EDATE(E10,12*O10)) -> 45437 | Q10: =IF(E10="","",IFERROR(EDATE(E10,12*INDEX('State Rules'!$E$5:$E$11,MATCH($B10,'State Rules'!$A$5:$A$11,0))),"")) -> 46167 | R10: =IF(P10="","",IFERROR(IF(P10<=INDEX('State Rules'!$I$5:$I$11,MATCH($B10,'State Rules'!$A$5:$A$11,0)),"Yes","No"),"")) -> Yes | S10: =IF(Q10="","",IFERROR(IF(Q10<=INDEX('State Rules'!$I$5:$I$11,MATCH($B10,'State Rules'!$A$5:$A$11,0)),"Yes","No"),"")) -> Yes | Z10: =IF(Q10="","",IF(Q10<=$B$4,N(W10)+N(X10),0)) -> 0 | AA10: =IF(OR(LEFT(N10,6)="Larger",LEFT(N10,4)="Memo"),H10,0) -> 694.68
A11: Dallas | B11: =IFERROR(INDEX(Summary!$B$10:$B$17,MATCH($A11,Summary!$A$10:$A$17,0)),"") -> TX | C11: Dallas | D11: 25 | E11: 45106 | F11: 9478743248 | G11: Jaden International | H11: 500 | I11: 6050 N Central Exp 314-not for this address unsure of address | J11: No | K11: =IF(E11="","",($B$4-E11)/365.25) -> 3.2717317 | L11: =IF(K11="","no date",IF(K11<1,"0-1 yrs",IF(K11<2,"1-2 yrs",IF(K11<3,"2-3 yrs",IF(K11<5,"3-5 yrs","5+ yrs"))))) -> 3-5 yrs | M11: Yes | N11: =IF(M11="Yes","Memo flag - not ours / unknown / hold: resolve",IF(OR(COUNTIF(Summary!$C$4:$L$4,H11)>0,AND(A11="Philly",COUNTIF(Summary!$C$5:$L$5,H11)>0),AND(A11="TUR",COUNTIF(Summary!$C$6:$L$6,H11)>0)),"Fee amount - presumed company revenue",IF(H11<=Summary!$B$7,"Small amount - likely fee, review","Larger amount - likely includes agent commission"))) -> Memo flag - not ours / unknown / hold: resolve | O11: =IFERROR(INDEX('State Rules'!$C$5:$C$11,MATCH($B11,'State Rules'!$A$5:$A$11,0)),"") -> 1 | P11: =IF(OR(O11="",E11=""),"",EDATE(E11,12*O11)) -> 45472 | Q11: =IF(E11="","",IFERROR(EDATE(E11,12*INDEX('State Rules'!$E$5:$E$11,MATCH($B11,'State Rules'!$A$5:$A$11,0))),"")) -> 46202 | R11: =IF(P11="","",IFERROR(IF(P11<=INDEX('State Rules'!$I$5:$I$11,MATCH($B11,'State Rules'!$A$5:$A$11,0)),"Yes","No"),"")) -> Yes | S11: =IF(Q11="","",IFERROR(IF(Q11<=INDEX('State Rules'!$I$5:$I$11,MATCH($B11,'State Rules'!$A$5:$A$11,0)),"Yes","No"),"")) -> Yes | Z11: =IF(Q11="","",IF(Q11<=$B$4,N(W11)+N(X11),0)) -> 0 | AA11: =IF(OR(LEFT(N11,6)="Larger",LEFT(N11,4)="Memo"),H11,0) -> 500
A12: Dallas | B12: =IFERROR(INDEX(Summary!$B$10:$B$17,MATCH($A12,Summary!$A$10:$A$17,0)),"") -> TX | C12: Dallas | D12: 26 | E12: 45152 | F12: 310781 | G12: Colliers International | H12: 824.12 | J12: No | K12: =IF(E12="","",($B$4-E12)/365.25) -> 3.1457906 | L12: =IF(K12="","no date",IF(K12<1,"0-1 yrs",IF(K12<2,"1-2 yrs",IF(K12<3,"2-3 yrs",IF(K12<5,"3-5 yrs","5+ yrs"))))) -> 3-5 yrs | M12: No | N12: =IF(M12="Yes","Memo flag - not ours / unknown / hold: resolve",IF(OR(COUNTIF(Summary!$C$4:$L$4,H12)>0,AND(A12="Philly",COUNTIF(Summary!$C$5:$L$5,H12)>0),AND(A12="TUR",COUNTIF(Summary!$C$6:$L$6,H12)>0)),"Fee amount - presumed company revenue",IF(H12<=Summary!$B$7,"Small amount - likely fee, review","Larger amount - likely includes agent commission"))) -> Larger amount - likely includes agent commission | O12: =IFERROR(INDEX('State Rules'!$C$5:$C$11,MATCH($B12,'State Rules'!$A$5:$A$11,0)),"") -> 1 | P12: =IF(OR(O12="",E12=""),"",EDATE(E12,12*O12)) -> 45518 | Q12: =IF(E12="","",IFERROR(EDATE(E12,12*INDEX('State Rules'!$E$5:$E$11,MATCH($B12,'State Rules'!$A$5:$A$11,0))),"")) -> 46248 | R12: =IF(P12="","",IFERROR(IF(P12<=INDEX('State Rules'!$I$5:$I$11,MATCH($B12,'State Rules'!$A$5:$A$11,0)),"Yes","No"),"")) -> Yes | S12: =IF(Q12="","",IFERROR(IF(Q12<=INDEX('State Rules'!$I$5:$I$11,MATCH($B12,'State Rules'!$A$5:$A$11,0)),"Yes","No"),"")) -> Yes | Z12: =IF(Q12="","",IF(Q12<=$B$4,N(W12)+N(X12),0)) -> 0 | AA12: =IF(OR(LEFT(N12,6)="Larger",LEFT(N12,4)="Memo"),H12,0) -> 824.12
A13: Dallas | B13: =IFERROR(INDEX(Summary!$B$10:$B$17,MATCH($A13,Summary!$A$10:$A$17,0)),"") -> TX | C13: Dallas | D13: 27 | E13: 45176 | F13: 5384 | G13: Roxana Handal | H13: 91.5 | J13: No | K13: =IF(E13="","",($B$4-E13)/365.25) -> 3.0800821 | L13: =IF(K13="","no date",IF(K13<1,"0-1 yrs",IF(K13<2,"1-2 yrs",IF(K13<3,"2-3 yrs",IF(K13<5,"3-5 yrs","5+ yrs"))))) -> 3-5 yrs | M13: No | N13: =IF(M13="Yes","Memo flag - not ours / unknown / hold: resolve",IF(OR(COUNTIF(Summary!$C$4:$L$4,H13)>0,AND(A13="Philly",COUNTIF(Summary!$C$5:$L$5,H13)>0),AND(A13="TUR",COUNTIF(Summary!$C$6:$L$6,H13)>0)),"Fee amount - presumed company revenue",IF(H13<=Summary!$B$7,"Small amount - likely fee, review","Larger amount - likely includes agent commission"))) -> Small amount - likely fee, review | O13: =IFERROR(INDEX('State Rules'!$C$5:$C$11,MATCH($B13,'State Rules'!$A$5:$A$11,0)),"") -> 1 | P13: =IF(OR(O13="",E13=""),"",EDATE(E13,12*O13)) -> 45542 | Q13: =IF(E13="","",IFERROR(EDATE(E13,12*INDEX('State Rules'!$E$5:$E$11,MATCH($B13,'State Rules'!$A$5:$A$11,0))),"")) -> 46272 | R13: =IF(P13="","",IFERROR(IF(P13<=INDEX('State Rules'!$I$5:$I$11,MATCH($B13,'State Rules'!$A$5:$A$11,0)),"Yes","No"),"")) -> Yes | S13: =IF(Q13="","",IFERROR(IF(Q13<=INDEX('State Rules'!$I$5:$I$11,MATCH($B13,'State Rules'!$A$5:$A$11,0)),"Yes","No"),"")) -> Yes | Z13: =IF(Q13="","",IF(Q13<=$B$4,N(W13)+N(X13),0)) -> 0 | AA13: =IF(OR(LEFT(N13,6)="Larger",LEFT(N13,4)="Memo"),H13,0) -> 0
A14: Dallas | B14: =IFERROR(INDEX(Summary!$B$10:$B$17,MATCH($A14,Summary!$A$10:$A$17,0)),"") -> TX | C14: Dallas | D14: 28 | E14: 45183 | F14: 554402 | G14: Soleste West Gables c/o Waterton Residential | H14: 1000 | J14: No | K14: =IF(E14="","",($B$4-E14)/365.25) -> 3.0609172 | L14: =IF(K14="","no date",IF(K14<1,"0-1 yrs",IF(K14<2,"1-2 yrs",IF(K14<3,"2-3 yrs",IF(K14<5,"3-5 yrs","5+ yrs"))))) -> 3-5 yrs | M14: No | N14: =IF(M14="Yes","Memo flag - not ours / unknown / hold: resolve",IF(OR(COUNTIF(Summary!$C$4:$L$4,H14)>0,AND(A14="Philly",COUNTIF(Summary!$C$5:$L$5,H14)>0),AND(A14="TUR",COUNTIF(Summary!$C$6:$L$6,H14)>0)),"Fee amount - presumed company revenue",IF(H14<=Summary!$B$7,"Small amount - likely fee, review","Larger amount - likely includes agent commission"))) -> Larger amount - likely includes agent commission | O14: =IFERROR(INDEX('State Rules'!$C$5:$C$11,MATCH($B14,'State Rules'!$A$5:$A$11,0)),"") -> 1 | P14: =IF(OR(O14="",E14=""),"",EDATE(E14,12*O14)) -> 45549 | Q14: =IF(E14="","",IFERROR(EDATE(E14,12*INDEX('State Rules'!$E$5:$E$11,MATCH($B14,'State Rules'!$A$5:$A$11,0))),"")) -> 46279 | R14: =IF(P14="","",IFERROR(IF(P14<=INDEX('State Rules'!$I$5:$I$11,MATCH($B14,'State Rules'!$A$5:$A$11,0)),"Yes","No"),"")) -> Yes | S14: =IF(Q14="","",IFERROR(IF(Q14<=INDEX('State Rules'!$I$5:$I$11,MATCH($B14,'State Rules'!$A$5:$A$11,0)),"Yes","No"),"")) -> Yes | Z14: =IF(Q14="","",IF(Q14<=$B$4,N(W14)+N(X14),0)) -> 0 | AA14: =IF(OR(LEFT(N14,6)="Larger",LEFT(N14,4)="Memo"),H14,0) -> 1000
A15: Dallas | B15: =IFERROR(INDEX(Summary!$B$10:$B$17,MATCH($A15,Summary!$A$10:$A$17,0)),"") -> TX | C15: Dallas | D15: 29 | E15: 45237 | F15: 158770 | G15: McKnight Title | H15: 800 | J15: No | K15: =IF(E15="","",($B$4-E15)/365.25) -> 2.9130732 | L15: =IF(K15="","no date",IF(K15<1,"0-1 yrs",IF(K15<2,"1-2 yrs",IF(K15<3,"2-3 yrs",IF(K15<5,"3-5 yrs","5+ yrs"))))) -> 2-3 yrs | M15: No | N15: =IF(M15="Yes","Memo flag - not ours / unknown / hold: resolve",IF(OR(COUNTIF(Summary!$C$4:$L$4,H15)>0,AND(A15="Philly",COUNTIF(Summary!$C$5:$L$5,H15)>0),AND(A15="TUR",COUNTIF(Summary!$C$6:$L$6,H15)>0)),"Fee amount - presumed company revenue",IF(H15<=Summary!$B$7,"Small amount - likely fee, review","Larger amount - likely includes agent commission"))) -> Larger amount - likely includes agent commission | O15: =IFERROR(INDEX('State Rules'!$C$5:$C$11,MATCH($B15,'State Rules'!$A$5:$A$11,0)),"") -> 1 | P15: =IF(OR(O15="",E15=""),"",EDATE(E15,12*O15)) -> 45603 | Q15: =IF(E15="","",IFERROR(EDATE(E15,12*INDEX('State Rules'!$E$5:$E$11,MATCH($B15,'State Rules'!$A$5:$A$11,0))),"")) -> 46333 | R15: =IF(P15="","",IFERROR(IF(P15<=INDEX('State Rules'!$I$5:$I$11,MATCH($B15,'State Rules'!$A$5:$A$11,0)),"Yes","No"),"")) -> Yes | S15: =IF(Q15="","",IFERROR(IF(Q15<=INDEX('State Rules'!$I$5:$I$11,MATCH($B15,'State Rules'!$A$5:$A$11,0)),"Yes","No"),"")) -> Yes | Z15: =IF(Q15="","",IF(Q15<=$B$4,N(W15)+N(X15),0)) -> 0 | AA15: =IF(OR(LEFT(N15,6)="Larger",LEFT(N15,4)="Memo"),H15,0) -> 800
A16: Dallas | B16: =IFERROR(INDEX(Summary!$B$10:$B$17,MATCH($A16,Summary!$A$10:$A$17,0)),"") -> TX | C16: Dallas | D16: 30 | E16: 45344 | F16: 7201577987 | G16: Hampton on Jupiter | H16: 534.5 | I16: Summit Property Management | J16: No | K16: =IF(E16="","",($B$4-E16)/365.25) -> 2.6201232 | L16: =IF(K16="","no date",IF(K16<1,"0-1 yrs",IF(K16<2,"1-2 yrs",IF(K16<3,"2-3 yrs",IF(K16<5,"3-5 yrs","5+ yrs"))))) -> 2-3 yrs | M16: No | N16: =IF(M16="Yes","Memo flag - not ours / unknown / hold: resolve",IF(OR(COUNTIF(Summary!$C$4:$L$4,H16)>0,AND(A16="Philly",COUNTIF(Summary!$C$5:$L$5,H16)>0),AND(A16="TUR",COUNTIF(Summary!$C$6:$L$6,H16)>0)),"Fee amount - presumed company revenue",IF(H16<=Summary!$B$7,"Small amount - likely fee, review","Larger amount - likely includes agent commission"))) -> Larger amount - likely includes agent commission | O16: =IFERROR(INDEX('State Rules'!$C$5:$C$11,MATCH($B16,'State Rules'!$A$5:$A$11,0)),"") -> 1 | P16: =IF(OR(O16="",E16=""),"",EDATE(E16,12*O16)) -> 45710 | Q16: =IF(E16="","",IFERROR(EDATE(E16,12*INDEX('State Rules'!$E$5:$E$11,MATCH($B16,'State Rules'!$A$5:$A$11,0))),"")) -> 46440 | R16: =IF(P16="","",IFERROR(IF(P16<=INDEX('State Rules'!$I$5:$I$11,MATCH($B16,'State Rules'!$A$5:$A$11,0)),"Yes","No"),"")) -> Yes | S16: =IF(Q16="","",IFERROR(IF(Q16<=INDEX('State Rules'!$I$5:$I$11,MATCH($B16,'State Rules'!$A$5:$A$11,0)),"Yes","No"),"")) -> Yes | Z16: =IF(Q16="","",IF(Q16<=$B$4,N(W16)+N(X16),0)) -> 0 | AA16: =IF(OR(LEFT(N16,6)="Larger",LEFT(N16,4)="Memo"),H16,0) -> 534.5
A17: Dallas | B17: =IFERROR(INDEX(Summary!$B$10:$B$17,MATCH($A17,Summary!$A$10:$A$17,0)),"") -> TX | C17: Dallas | D17: 31 | E17: 45365 | F17: 3536 | G17: Guildford LLC | H17: 945 | I17: 709 Golden Bear- Junko Cummings- ck 3604 processed with this transaction(duplicate?) | J17: No | K17: =IF(E17="","",($B$4-E17)/365.25) -> 2.5626283 | L17: =IF(K17="","no date",IF(K17<1,"0-1 yrs",IF(K17<2,"1-2 yrs",IF(K17<3,"2-3 yrs",IF(K17<5,"3-5 yrs","5+ yrs"))))) -> 2-3 yrs | M17: Yes | N17: =IF(M17="Yes","Memo flag - not ours / unknown / hold: resolve",IF(OR(COUNTIF(Summary!$C$4:$L$4,H17)>0,AND(A17="Philly",COUNTIF(Summary!$C$5:$L$5,H17)>0),AND(A17="TUR",COUNTIF(Summary!$C$6:$L$6,H17)>0)),"Fee amount - presumed company revenue",IF(H17<=Summary!$B$7,"Small amount - likely fee, review","Larger amount - likely includes agent commission"))) -> Memo flag - not ours / unknown / hold: resolve | O17: =IFERROR(INDEX('State Rules'!$C$5:$C$11,MATCH($B17,'State Rules'!$A$5:$A$11,0)),"") -> 1 | P17: =IF(OR(O17="",E17=""),"",EDATE(E17,12*O17)) -> 45730 | Q17: =IF(E17="","",IFERROR(EDATE(E17,12*INDEX('State Rules'!$E$5:$E$11,MATCH($B17,'State Rules'!$A$5:$A$11,0))),"")) -> 46460 | R17: =IF(P17="","",IFERROR(IF(P17<=INDEX('State Rules'!$I$5:$I$11,MATCH($B17,'State Rules'!$A$5:$A$11,0)),"Yes","No"),"")) -> Yes | S17: =IF(Q17="","",IFERROR(IF(Q17<=INDEX('State Rules'!$I$5:$I$11,MATCH($B17,'State Rules'!$A$5:$A$11,0)),"Yes","No"),"")) -> No | Z17: =IF(Q17="","",IF(Q17<=$B$4,N(W17)+N(X17),0)) -> 0 | AA17: =IF(OR(LEFT(N17,6)="Larger",LEFT(N17,4)="Memo"),H17,0) -> 945
A18: Dallas | B18: =IFERROR(INDEX(Summary!$B$10:$B$17,MATCH($A18,Summary!$A$10:$A$17,0)),"") -> TX | C18: Dallas | D18: 32 | E18: 45379 | F18: 7725 | G18: Go Spring Branch | H18: 1000 | I18: 1311 12th St- Lease | J18: No | K18: =IF(E18="","",($B$4-E18)/365.25) -> 2.5242984 | L18: =IF(K18="","no date",IF(K18<1,"0-1 yrs",IF(K18<2,"1-2 yrs",IF(K18<3,"2-3 yrs",IF(K18<5,"3-5 yrs","5+ yrs"))))) -> 2-3 yrs | M18: No | N18: =IF(M18="Yes","Memo flag - not ours / unknown / hold: resolve",IF(OR(COUNTIF(Summary!$C$4:$L$4,H18)>0,AND(A18="Philly",COUNTIF(Summary!$C$5:$L$5,H18)>0),AND(A18="TUR",COUNTIF(Summary!$C$6:$L$6,H18)>0)),"Fee amount - presumed company revenue",IF(H18<=Summary!$B$7,"Small amount - likely fee, review","Larger amount - likely includes agent commission"))) -> Larger amount - likely includes agent commission | O18: =IFERROR(INDEX('State Rules'!$C$5:$C$11,MATCH($B18,'State Rules'!$A$5:$A$11,0)),"") -> 1 | P18: =IF(OR(O18="",E18=""),"",EDATE(E18,12*O18)) -> 45744 | Q18: =IF(E18="","",IFERROR(EDATE(E18,12*INDEX('State Rules'!$E$5:$E$11,MATCH($B18,'State Rules'!$A$5:$A$11,0))),"")) -> 46474 | R18: =IF(P18="","",IFERROR(IF(P18<=INDEX('State Rules'!$I$5:$I$11,MATCH($B18,'State Rules'!$A$5:$A$11,0)),"Yes","No"),"")) -> Yes | S18: =IF(Q18="","",IFERROR(IF(Q18<=INDEX('State Rules'!$I$5:$I$11,MATCH($B18,'State Rules'!$A$5:$A$11,0)),"Yes","No"),"")) -> No | Z18: =IF(Q18="","",IF(Q18<=$B$4,N(W18)+N(X18),0)) -> 0 | AA18: =IF(OR(LEFT(N18,6)="Larger",LEFT(N18,4)="Memo"),H18,0) -> 1000
A19: Dallas | B19: =IFERROR(INDEX(Summary!$B$10:$B$17,MATCH($A19,Summary!$A$10:$A$17,0)),"") -> TX | C19: Dallas | D19: 33 | E19: 45450 | F19: 22833 | H19: 44 | I19: 5740 Cutler Ln- waiting to hear back from title about missing portion | J19: No | K19: =IF(E19="","",($B$4-E19)/365.25) -> 2.329911 | L19: =IF(K19="","no date",IF(K19<1,"0-1 yrs",IF(K19<2,"1-2 yrs",IF(K19<3,"2-3 yrs",IF(K19<5,"3-5 yrs","5+ yrs"))))) -> 2-3 yrs | M19: No | N19: =IF(M19="Yes","Memo flag - not ours / unknown / hold: resolve",IF(OR(COUNTIF(Summary!$C$4:$L$4,H19)>0,AND(A19="Philly",COUNTIF(Summary!$C$5:$L$5,H19)>0),AND(A19="TUR",COUNTIF(Summary!$C$6:$L$6,H19)>0)),"Fee amount - presumed company revenue",IF(H19<=Summary!$B$7,"Small amount - likely fee, review","Larger amount - likely includes agent commission"))) -> Small amount - likely fee, review | O19: =IFERROR(INDEX('State Rules'!$C$5:$C$11,MATCH($B19,'State Rules'!$A$5:$A$11,0)),"") -> 1 | P19: =IF(OR(O19="",E19=""),"",EDATE(E19,12*O19)) -> 45815 | Q19: =IF(E19="","",IFERROR(EDATE(E19,12*INDEX('State Rules'!$E$5:$E$11,MATCH($B19,'State Rules'!$A$5:$A$11,0))),"")) -> 46545 | R19: =IF(P19="","",IFERROR(IF(P19<=INDEX('State Rules'!$I$5:$I$11,MATCH($B19,'State Rules'!$A$5:$A$11,0)),"Yes","No"),"")) -> Yes | S19: =IF(Q19="","",IFERROR(IF(Q19<=INDEX('State Rules'!$I$5:$I$11,MATCH($B19,'State Rules'!$A$5:$A$11,0)),"Yes","No"),"")) -> No | Z19: =IF(Q19="","",IF(Q19<=$B$4,N(W19)+N(X19),0)) -> 0 | AA19: =IF(OR(LEFT(N19,6)="Larger",LEFT(N19,4)="Memo"),H19,0) -> 0
A20: Dallas | B20: =IFERROR(INDEX(Summary!$B$10:$B$17,MATCH($A20,Summary!$A$10:$A$17,0)),"") -> TX | C20: Dallas | D20: 34 | E20: 45476 | F20: 3399 | G20: Texas Title Escrow Account | H20: 10 | J20: No | K20: =IF(E20="","",($B$4-E20)/365.25) -> 2.2587269 | L20: =IF(K20="","no date",IF(K20<1,"0-1 yrs",IF(K20<2,"1-2 yrs",IF(K20<3,"2-3 yrs",IF(K20<5,"3-5 yrs","5+ yrs"))))) -> 2-3 yrs | M20: No | N20: =IF(M20="Yes","Memo flag - not ours / unknown / hold: resolve",IF(OR(COUNTIF(Summary!$C$4:$L$4,H20)>0,AND(A20="Philly",COUNTIF(Summary!$C$5:$L$5,H20)>0),AND(A20="TUR",COUNTIF(Summary!$C$6:$L$6,H20)>0)),"Fee amount - presumed company revenue",IF(H20<=Summary!$B$7,"Small amount - likely fee, review","Larger amount - likely includes agent commission"))) -> Small amount - likely fee, review | O20: =IFERROR(INDEX('State Rules'!$C$5:$C$11,MATCH($B20,'State Rules'!$A$5:$A$11,0)),"") -> 1 | P20: =IF(OR(O20="",E20=""),"",EDATE(E20,12*O20)) -> 45841 | Q20: =IF(E20="","",IFERROR(EDATE(E20,12*INDEX('State Rules'!$E$5:$E$11,MATCH($B20,'State Rules'!$A$5:$A$11,0))),"")) -> 46571 | R20: =IF(P20="","",IFERROR(IF(P20<=INDEX('State Rules'!$I$5:$I$11,MATCH($B20,'State Rules'!$A$5:$A$11,0)),"Yes","No"),"")) -> Yes | S20: =IF(Q20="","",IFERROR(IF(Q20<=INDEX('State Rules'!$I$5:$I$11,MATCH($B20,'State Rules'!$A$5:$A$11,0)),"Yes","No"),"")) -> No | Z20: =IF(Q20="","",IF(Q20<=$B$4,N(W20)+N(X20),0)) -> 0 | AA20: =IF(OR(LEFT(N20,6)="Larger",LEFT(N20,4)="Memo"),H20,0) -> 0
A21: Dallas | B21: =IFERROR(INDEX(Summary!$B$10:$B$17,MATCH($A21,Summary!$A$10:$A$17,0)),"") -> TX | C21: Dallas | D21: 35 | E21: 45476 | F21: 3409 | G21: Texas Title Escrow Account | H21: 1549 | J21: No | K21: =IF(E21="","",($B$4-E21)/365.25) -> 2.2587269 | L21: =IF(K21="","no date",IF(K21<1,"0-1 yrs",IF(K21<2,"1-2 yrs",IF(K21<3,"2-3 yrs",IF(K21<5,"3-5 yrs","5+ yrs"))))) -> 2-3 yrs | M21: No | N21: =IF(M21="Yes","Memo flag - not ours / unknown / hold: resolve",IF(OR(COUNTIF(Summary!$C$4:$L$4,H21)>0,AND(A21="Philly",COUNTIF(Summary!$C$5:$L$5,H21)>0),AND(A21="TUR",COUNTIF(Summary!$C$6:$L$6,H21)>0)),"Fee amount - presumed company revenue",IF(H21<=Summary!$B$7,"Small amount - likely fee, review","Larger amount - likely includes agent commission"))) -> Larger amount - likely includes agent commission | O21: =IFERROR(INDEX('State Rules'!$C$5:$C$11,MATCH($B21,'State Rules'!$A$5:$A$11,0)),"") -> 1 | P21: =IF(OR(O21="",E21=""),"",EDATE(E21,12*O21)) -> 45841 | Q21: =IF(E21="","",IFERROR(EDATE(E21,12*INDEX('State Rules'!$E$5:$E$11,MATCH($B21,'State Rules'!$A$5:$A$11,0))),"")) -> 46571 | R21: =IF(P21="","",IFERROR(IF(P21<=INDEX('State Rules'!$I$5:$I$11,MATCH($B21,'State Rules'!$A$5:$A$11,0)),"Yes","No"),"")) -> Yes | S21: =IF(Q21="","",IFERROR(IF(Q21<=INDEX('State Rules'!$I$5:$I$11,MATCH($B21,'State Rules'!$A$5:$A$11,0)),"Yes","No"),"")) -> No | Z21: =IF(Q21="","",IF(Q21<=$B$4,N(W21)+N(X21),0)) -> 0 | AA21: =IF(OR(LEFT(N21,6)="Larger",LEFT(N21,4)="Memo"),H21,0) -> 1549
A22: Dallas | B22: =IFERROR(INDEX(Summary!$B$10:$B$17,MATCH($A22,Summary!$A$10:$A$17,0)),"") -> TX | C22: Dallas | D22: 36 | E22: 45485 | F22: 36710 | G22: TC Lincoln Centre- Cushman & Wakefield | H22: 609.24 | J22: No | K22: =IF(E22="","",($B$4-E22)/365.25) -> 2.2340862 | L22: =IF(K22="","no date",IF(K22<1,"0-1 yrs",IF(K22<2,"1-2 yrs",IF(K22<3,"2-3 yrs",IF(K22<5,"3-5 yrs","5+ yrs"))))) -> 2-3 yrs | M22: No | N22: =IF(M22="Yes","Memo flag - not ours / unknown / hold: resolve",IF(OR(COUNTIF(Summary!$C$4:$L$4,H22)>0,AND(A22="Philly",COUNTIF(Summary!$C$5:$L$5,H22)>0),AND(A22="TUR",COUNTIF(Summary!$C$6:$L$6,H22)>0)),"Fee amount - presumed company revenue",IF(H22<=Summary!$B$7,"Small amount - likely fee, review","Larger amount - likely includes agent commission"))) -> Larger amount - likely includes agent commission | O22: =IFERROR(INDEX('State Rules'!$C$5:$C$11,MATCH($B22,'State Rules'!$A$5:$A$11,0)),"") -> 1 | P22: =IF(OR(O22="",E22=""),"",EDATE(E22,12*O22)) -> 45850 | Q22: =IF(E22="","",IFERROR(EDATE(E22,12*INDEX('State Rules'!$E$5:$E$11,MATCH($B22,'State Rules'!$A$5:$A$11,0))),"")) -> 46580 | R22: =IF(P22="","",IFERROR(IF(P22<=INDEX('State Rules'!$I$5:$I$11,MATCH($B22,'State Rules'!$A$5:$A$11,0)),"Yes","No"),"")) -> Yes | S22: =IF(Q22="","",IFERROR(IF(Q22<=INDEX('State Rules'!$I$5:$I$11,MATCH($B22,'State Rules'!$A$5:$A$11,0)),"Yes","No"),"")) -> No | Z22: =IF(Q22="","",IF(Q22<=$B$4,N(W22)+N(X22),0)) -> 0 | AA22: =IF(OR(LEFT(N22,6)="Larger",LEFT(N22,4)="Memo"),H22,0) -> 609.24
A23: Dallas | B23: =IFERROR(INDEX(Summary!$B$10:$B$17,MATCH($A23,Summary!$A$10:$A$17,0)),"") -> TX | C23: Dallas | D23: 37 | E23: 45488 | F23: 30197 | G23: Diversified National Title | H23: 644 | J23: No | K23: =IF(E23="","",($B$4-E23)/365.25) -> 2.2258727 | L23: =IF(K23="","no date",IF(K23<1,"0-1 yrs",IF(K23<2,"1-2 yrs",IF(K23<3,"2-3 yrs",IF(K23<5,"3-5 yrs","5+ yrs"))))) -> 2-3 yrs | M23: No | N23: =IF(M23="Yes","Memo flag - not ours / unknown / hold: resolve",IF(OR(COUNTIF(Summary!$C$4:$L$4,H23)>0,AND(A23="Philly",COUNTIF(Summary!$C$5:$L$5,H23)>0),AND(A23="TUR",COUNTIF(Summary!$C$6:$L$6,H23)>0)),"Fee amount - presumed company revenue",IF(H23<=Summary!$B$7,"Small amount - likely fee, review","Larger amount - likely includes agent commission"))) -> Fee amount - presumed company revenue | O23: =IFERROR(INDEX('State Rules'!$C$5:$C$11,MATCH($B23,'State Rules'!$A$5:$A$11,0)),"") -> 1 | P23: =IF(OR(O23="",E23=""),"",EDATE(E23,12*O23)) -> 45853 | Q23: =IF(E23="","",IFERROR(EDATE(E23,12*INDEX('State Rules'!$E$5:$E$11,MATCH($B23,'State Rules'!$A$5:$A$11,0))),"")) -> 46583 | R23: =IF(P23="","",IFERROR(IF(P23<=INDEX('State Rules'!$I$5:$I$11,MATCH($B23,'State Rules'!$A$5:$A$11,0)),"Yes","No"),"")) -> Yes | S23: =IF(Q23="","",IFERROR(IF(Q23<=INDEX('State Rules'!$I$5:$I$11,MATCH($B23,'State Rules'!$A$5:$A$11,0)),"Yes","No"),"")) -> No | Z23: =IF(Q23="","",IF(Q23<=$B$4,N(W23)+N(X23),0)) -> 0 | AA23: =IF(OR(LEFT(N23,6)="Larger",LEFT(N23,4)="Memo"),H23,0) -> 0
A24: Dallas | B24: =IFERROR(INDEX(Summary!$B$10:$B$17,MATCH($A24,Summary!$A$10:$A$17,0)),"") -> TX | C24: Dallas | D24: 38 | E24: 45506 | F24: 103232 | H24: 1044 | J24: No | K24: =IF(E24="","",($B$4-E24)/365.25) -> 2.1765914 | L24: =IF(K24="","no date",IF(K24<1,"0-1 yrs",IF(K24<2,"1-2 yrs",IF(K24<3,"2-3 yrs",IF(K24<5,"3-5 yrs","5+ yrs"))))) -> 2-3 yrs | M24: No | N24: =IF(M24="Yes","Memo flag - not ours / unknown / hold: resolve",IF(OR(COUNTIF(Summary!$C$4:$L$4,H24)>0,AND(A24="Philly",COUNTIF(Summary!$C$5:$L$5,H24)>0),AND(A24="TUR",COUNTIF(Summary!$C$6:$L$6,H24)>0)),"Fee amount - presumed company revenue",IF(H24<=Summary!$B$7,"Small amount - likely fee, review","Larger amount - likely includes agent commission"))) -> Fee amount - presumed company revenue | O24: =IFERROR(INDEX('State Rules'!$C$5:$C$11,MATCH($B24,'State Rules'!$A$5:$A$11,0)),"") -> 1 | P24: =IF(OR(O24="",E24=""),"",EDATE(E24,12*O24)) -> 45871 | Q24: =IF(E24="","",IFERROR(EDATE(E24,12*INDEX('State Rules'!$E$5:$E$11,MATCH($B24,'State Rules'!$A$5:$A$11,0))),"")) -> 46601 | R24: =IF(P24="","",IFERROR(IF(P24<=INDEX('State Rules'!$I$5:$I$11,MATCH($B24,'State Rules'!$A$5:$A$11,0)),"Yes","No"),"")) -> Yes | S24: =IF(Q24="","",IFERROR(IF(Q24<=INDEX('State Rules'!$I$5:$I$11,MATCH($B24,'State Rules'!$A$5:$A$11,0)),"Yes","No"),"")) -> No | Z24: =IF(Q24="","",IF(Q24<=$B$4,N(W24)+N(X24),0)) -> 0 | AA24: =IF(OR(LEFT(N24,6)="Larger",LEFT(N24,4)="Memo"),H24,0) -> 0
A25: Dallas | B25: =IFERROR(INDEX(Summary!$B$10:$B$17,MATCH($A25,Summary!$A$10:$A$17,0)),"") -> TX | C25: Dallas | D25: 39 | E25: 45579 | F25: CK 3000000008 | H25: 449.75 | I25: 2304 Magnolia-Not in PP, not sure who agent is | J25: No | K25: =IF(E25="","",($B$4-E25)/365.25) -> 1.9767283 | L25: =IF(K25="","no date",IF(K25<1,"0-1 yrs",IF(K25<2,"1-2 yrs",IF(K25<3,"2-3 yrs",IF(K25<5,"3-5 yrs","5+ yrs"))))) -> 1-2 yrs | M25: Yes | N25: =IF(M25="Yes","Memo flag - not ours / unknown / hold: resolve",IF(OR(COUNTIF(Summary!$C$4:$L$4,H25)>0,AND(A25="Philly",COUNTIF(Summary!$C$5:$L$5,H25)>0),AND(A25="TUR",COUNTIF(Summary!$C$6:$L$6,H25)>0)),"Fee amount - presumed company revenue",IF(H25<=Summary!$B$7,"Small amount - likely fee, review","Larger amount - likely includes agent commission"))) -> Memo flag - not ours / unknown / hold: resolve | O25: =IFERROR(INDEX('State Rules'!$C$5:$C$11,MATCH($B25,'State Rules'!$A$5:$A$11,0)),"") -> 1 | P25: =IF(OR(O25="",E25=""),"",EDATE(E25,12*O25)) -> 45944 | Q25: =IF(E25="","",IFERROR(EDATE(E25,12*INDEX('State Rules'!$E$5:$E$11,MATCH($B25,'State Rules'!$A$5:$A$11,0))),"")) -> 46674 | R25: =IF(P25="","",IFERROR(IF(P25<=INDEX('State Rules'!$I$5:$I$11,MATCH($B25,'State Rules'!$A$5:$A$11,0)),"Yes","No"),"")) -> Yes | S25: =IF(Q25="","",IFERROR(IF(Q25<=INDEX('State Rules'!$I$5:$I$11,MATCH($B25,'State Rules'!$A$5:$A$11,0)),"Yes","No"),"")) -> No | Z25: =IF(Q25="","",IF(Q25<=$B$4,N(W25)+N(X25),0)) -> 0 | AA25: =IF(OR(LEFT(N25,6)="Larger",LEFT(N25,4)="Memo"),H25,0) -> 449.75
A26: Dallas | B26: =IFERROR(INDEX(Summary!$B$10:$B$17,MATCH($A26,Summary!$A$10:$A$17,0)),"") -> TX | C26: Dallas | D26: 40 | E26: 45611 | F26: CK 14122 | H26: 800 | I26: 5322 Columbia Ave (their transaction #059210-A)-Not in PP | J26: No | K26: =IF(E26="","",($B$4-E26)/365.25) -> 1.889117 | L26: =IF(K26="","no date",IF(K26<1,"0-1 yrs",IF(K26<2,"1-2 yrs",IF(K26<3,"2-3 yrs",IF(K26<5,"3-5 yrs","5+ yrs"))))) -> 1-2 yrs | M26: Yes | N26: =IF(M26="Yes","Memo flag - not ours / unknown / hold: resolve",IF(OR(COUNTIF(Summary!$C$4:$L$4,H26)>0,AND(A26="Philly",COUNTIF(Summary!$C$5:$L$5,H26)>0),AND(A26="TUR",COUNTIF(Summary!$C$6:$L$6,H26)>0)),"Fee amount - presumed company revenue",IF(H26<=Summary!$B$7,"Small amount - likely fee, review","Larger amount - likely includes agent commission"))) -> Memo flag - not ours / unknown / hold: resolve | O26: =IFERROR(INDEX('State Rules'!$C$5:$C$11,MATCH($B26,'State Rules'!$A$5:$A$11,0)),"") -> 1 | P26: =IF(OR(O26="",E26=""),"",EDATE(E26,12*O26)) -> 45976 | Q26: =IF(E26="","",IFERROR(EDATE(E26,12*INDEX('State Rules'!$E$5:$E$11,MATCH($B26,'State Rules'!$A$5:$A$11,0))),"")) -> 46706 | R26: =IF(P26="","",IFERROR(IF(P26<=INDEX('State Rules'!$I$5:$I$11,MATCH($B26,'State Rules'!$A$5:$A$11,0)),"Yes","No"),"")) -> Yes | S26: =IF(Q26="","",IFERROR(IF(Q26<=INDEX('State Rules'!$I$5:$I$11,MATCH($B26,'State Rules'!$A$5:$A$11,0)),"Yes","No"),"")) -> No | Z26: =IF(Q26="","",IF(Q26<=$B$4,N(W26)+N(X26),0)) -> 0 | AA26: =IF(OR(LEFT(N26,6)="Larger",LEFT(N26,4)="Memo"),H26,0) -> 800
A27: Dallas | B27: =IFERROR(INDEX(Summary!$B$10:$B$17,MATCH($A27,Summary!$A$10:$A$17,0)),"") -> TX | C27: Dallas | D27: 41 | E27: 45615 | F27: CK 2704 | H27: 4.5 | I27: 18333 Roehampton- supposed to be for 450 | J27: No | K27: =IF(E27="","",($B$4-E27)/365.25) -> 1.8781656 | L27: =IF(K27="","no date",IF(K27<1,"0-1 yrs",IF(K27<2,"1-2 yrs",IF(K27<3,"2-3 yrs",IF(K27<5,"3-5 yrs","5+ yrs"))))) -> 1-2 yrs | M27: Yes | N27: =IF(M27="Yes","Memo flag - not ours / unknown / hold: resolve",IF(OR(COUNTIF(Summary!$C$4:$L$4,H27)>0,AND(A27="Philly",COUNTIF(Summary!$C$5:$L$5,H27)>0),AND(A27="TUR",COUNTIF(Summary!$C$6:$L$6,H27)>0)),"Fee amount - presumed company revenue",IF(H27<=Summary!$B$7,"Small amount - likely fee, review","Larger amount - likely includes agent commission"))) -> Memo flag - not ours / unknown / hold: resolve | O27: =IFERROR(INDEX('State Rules'!$C$5:$C$11,MATCH($B27,'State Rules'!$A$5:$A$11,0)),"") -> 1 | P27: =IF(OR(O27="",E27=""),"",EDATE(E27,12*O27)) -> 45980 | Q27: =IF(E27="","",IFERROR(EDATE(E27,12*INDEX('State Rules'!$E$5:$E$11,MATCH($B27,'State Rules'!$A$5:$A$11,0))),"")) -> 46710 | R27: =IF(P27="","",IFERROR(IF(P27<=INDEX('State Rules'!$I$5:$I$11,MATCH($B27,'State Rules'!$A$5:$A$11,0)),"Yes","No"),"")) -> Yes | S27: =IF(Q27="","",IFERROR(IF(Q27<=INDEX('State Rules'!$I$5:$I$11,MATCH($B27,'State Rules'!$A$5:$A$11,0)),"Yes","No"),"")) -> No | Z27: =IF(Q27="","",IF(Q27<=$B$4,N(W27)+N(X27),0)) -> 0 | AA27: =IF(OR(LEFT(N27,6)="Larger",LEFT(N27,4)="Memo"),H27,0) -> 4.5
A28: Dallas | B28: =IFERROR(INDEX(Summary!$B$10:$B$17,MATCH($A28,Summary!$A$10:$A$17,0)),"") -> TX | C28: Dallas | D28: 42 | E28: 45616 | F28: CK 5603 | H28: 2865 | I28: The Ashton-not sure of property address or agent | J28: No | K28: =IF(E28="","",($B$4-E28)/365.25) -> 1.8754278 | L28: =IF(K28="","no date",IF(K28<1,"0-1 yrs",IF(K28<2,"1-2 yrs",IF(K28<3,"2-3 yrs",IF(K28<5,"3-5 yrs","5+ yrs"))))) -> 1-2 yrs | M28: Yes | N28: =IF(M28="Yes","Memo flag - not ours / unknown / hold: resolve",IF(OR(COUNTIF(Summary!$C$4:$L$4,H28)>0,AND(A28="Philly",COUNTIF(Summary!$C$5:$L$5,H28)>0),AND(A28="TUR",COUNTIF(Summary!$C$6:$L$6,H28)>0)),"Fee amount - presumed company revenue",IF(H28<=Summary!$B$7,"Small amount - likely fee, review","Larger amount - likely includes agent commission"))) -> Memo flag - not ours / unknown / hold: resolve | O28: =IFERROR(INDEX('State Rules'!$C$5:$C$11,MATCH($B28,'State Rules'!$A$5:$A$11,0)),"") -> 1 | P28: =IF(OR(O28="",E28=""),"",EDATE(E28,12*O28)) -> 45981 | Q28: =IF(E28="","",IFERROR(EDATE(E28,12*INDEX('State Rules'!$E$5:$E$11,MATCH($B28,'State Rules'!$A$5:$A$11,0))),"")) -> 46711 | R28: =IF(P28="","",IFERROR(IF(P28<=INDEX('State Rules'!$I$5:$I$11,MATCH($B28,'State Rules'!$A$5:$A$11,0)),"Yes","No"),"")) -> Yes | S28: =IF(Q28="","",IFERROR(IF(Q28<=INDEX('State Rules'!$I$5:$I$11,MATCH($B28,'State Rules'!$A$5:$A$11,0)),"Yes","No"),"")) -> No | Z28: =IF(Q28="","",IF(Q28<=$B$4,N(W28)+N(X28),0)) -> 0 | AA28: =IF(OR(LEFT(N28,6)="Larger",LEFT(N28,4)="Memo"),H28,0) -> 2865
A29: Dallas | B29: =IFERROR(INDEX(Summary!$B$10:$B$17,MATCH($A29,Summary!$A$10:$A$17,0)),"") -> TX | C29: Dallas | D29: 43 | E29: 45708 | F29: 7005146010 | H29: 106.96 | J29: No | K29: =IF(E29="","",($B$4-E29)/365.25) -> 1.6235455 | L29: =IF(K29="","no date",IF(K29<1,"0-1 yrs",IF(K29<2,"1-2 yrs",IF(K29<3,"2-3 yrs",IF(K29<5,"3-5 yrs","5+ yrs"))))) -> 1-2 yrs | M29: No | N29: =IF(M29="Yes","Memo flag - not ours / unknown / hold: resolve",IF(OR(COUNTIF(Summary!$C$4:$L$4,H29)>0,AND(A29="Philly",COUNTIF(Summary!$C$5:$L$5,H29)>0),AND(A29="TUR",COUNTIF(Summary!$C$6:$L$6,H29)>0)),"Fee amount - presumed company revenue",IF(H29<=Summary!$B$7,"Small amount - likely fee, review","Larger amount - likely includes agent commission"))) -> Small amount - likely fee, review | O29: =IFERROR(INDEX('State Rules'!$C$5:$C$11,MATCH($B29,'State Rules'!$A$5:$A$11,0)),"") -> 1 | P29: =IF(OR(O29="",E29=""),"",EDATE(E29,12*O29)) -> 46073 | Q29: =IF(E29="","",IFERROR(EDATE(E29,12*INDEX('State Rules'!$E$5:$E$11,MATCH($B29,'State Rules'!$A$5:$A$11,0))),"")) -> 46803 | R29: =IF(P29="","",IFERROR(IF(P29<=INDEX('State Rules'!$I$5:$I$11,MATCH($B29,'State Rules'!$A$5:$A$11,0)),"Yes","No"),"")) -> Yes | S29: =IF(Q29="","",IFERROR(IF(Q29<=INDEX('State Rules'!$I$5:$I$11,MATCH($B29,'State Rules'!$A$5:$A$11,0)),"Yes","No"),"")) -> No | Z29: =IF(Q29="","",IF(Q29<=$B$4,N(W29)+N(X29),0)) -> 0 | AA29: =IF(OR(LEFT(N29,6)="Larger",LEFT(N29,4)="Memo"),H29,0) -> 0
A30: Dallas | B30: =IFERROR(INDEX(Summary!$B$10:$B$17,MATCH($A30,Summary!$A$10:$A$17,0)),"") -> TX | C30: Dallas | D30: 44 | E30: 45716 | F30: 37572 | H30: 644 | I30: 1423 Main St. | J30: No | K30: =IF(E30="","",($B$4-E30)/365.25) -> 1.6016427 | L30: =IF(K30="","no date",IF(K30<1,"0-1 yrs",IF(K30<2,"1-2 yrs",IF(K30<3,"2-3 yrs",IF(K30<5,"3-5 yrs","5+ yrs"))))) -> 1-2 yrs | M30: No | N30: =IF(M30="Yes","Memo flag - not ours / unknown / hold: resolve",IF(OR(COUNTIF(Summary!$C$4:$L$4,H30)>0,AND(A30="Philly",COUNTIF(Summary!$C$5:$L$5,H30)>0),AND(A30="TUR",COUNTIF(Summary!$C$6:$L$6,H30)>0)),"Fee amount - presumed company revenue",IF(H30<=Summary!$B$7,"Small amount - likely fee, review","Larger amount - likely includes agent commission"))) -> Fee amount - presumed company revenue | O30: =IFERROR(INDEX('State Rules'!$C$5:$C$11,MATCH($B30,'State Rules'!$A$5:$A$11,0)),"") -> 1 | P30: =IF(OR(O30="",E30=""),"",EDATE(E30,12*O30)) -> 46081 | Q30: =IF(E30="","",IFERROR(EDATE(E30,12*INDEX('State Rules'!$E$5:$E$11,MATCH($B30,'State Rules'!$A$5:$A$11,0))),"")) -> 46811 | R30: =IF(P30="","",IFERROR(IF(P30<=INDEX('State Rules'!$I$5:$I$11,MATCH($B30,'State Rules'!$A$5:$A$11,0)),"Yes","No"),"")) -> Yes | S30: =IF(Q30="","",IFERROR(IF(Q30<=INDEX('State Rules'!$I$5:$I$11,MATCH($B30,'State Rules'!$A$5:$A$11,0)),"Yes","No"),"")) -> No | Z30: =IF(Q30="","",IF(Q30<=$B$4,N(W30)+N(X30),0)) -> 0 | AA30: =IF(OR(LEFT(N30,6)="Larger",LEFT(N30,4)="Memo"),H30,0) -> 0
A31: Dallas | B31: =IFERROR(INDEX(Summary!$B$10:$B$17,MATCH($A31,Summary!$A$10:$A$17,0)),"") -> TX | C31: Dallas | D31: 45 | E31: 45740 | F31: 502001684 | H31: 750 | I31: 3430 Calhoun Ave | J31: No | K31: =IF(E31="","",($B$4-E31)/365.25) -> 1.5359343 | L31: =IF(K31="","no date",IF(K31<1,"0-1 yrs",IF(K31<2,"1-2 yrs",IF(K31<3,"2-3 yrs",IF(K31<5,"3-5 yrs","5+ yrs"))))) -> 1-2 yrs | M31: No | N31: =IF(M31="Yes","Memo flag - not ours / unknown / hold: resolve",IF(OR(COUNTIF(Summary!$C$4:$L$4,H31)>0,AND(A31="Philly",COUNTIF(Summary!$C$5:$L$5,H31)>0),AND(A31="TUR",COUNTIF(Summary!$C$6:$L$6,H31)>0)),"Fee amount - presumed company revenue",IF(H31<=Summary!$B$7,"Small amount - likely fee, review","Larger amount - likely includes agent commission"))) -> Larger amount - likely includes agent commission | O31: =IFERROR(INDEX('State Rules'!$C$5:$C$11,MATCH($B31,'State Rules'!$A$5:$A$11,0)),"") -> 1 | P31: =IF(OR(O31="",E31=""),"",EDATE(E31,12*O31)) -> 46105 | Q31: =IF(E31="","",IFERROR(EDATE(E31,12*INDEX('State Rules'!$E$5:$E$11,MATCH($B31,'State Rules'!$A$5:$A$11,0))),"")) -> 46836 | R31: =IF(P31="","",IFERROR(IF(P31<=INDEX('State Rules'!$I$5:$I$11,MATCH($B31,'State Rules'!$A$5:$A$11,0)),"Yes","No"),"")) -> Yes | S31: =IF(Q31="","",IFERROR(IF(Q31<=INDEX('State Rules'!$I$5:$I$11,MATCH($B31,'State Rules'!$A$5:$A$11,0)),"Yes","No"),"")) -> No | Z31: =IF(Q31="","",IF(Q31<=$B$4,N(W31)+N(X31),0)) -> 0 | AA31: =IF(OR(LEFT(N31,6)="Larger",LEFT(N31,4)="Memo"),H31,0) -> 750
A32: Dallas | B32: =IFERROR(INDEX(Summary!$B$10:$B$17,MATCH($A32,Summary!$A$10:$A$17,0)),"") -> TX | C32: Dallas | D32: 46 | E32: 45819 | F32: 2209 | H32: 324.75 | I32: Whitney Williams written by Danny Elms | J32: No | K32: =IF(E32="","",($B$4-E32)/365.25) -> 1.3196441 | L32: =IF(K32="","no date",IF(K32<1,"0-1 yrs",IF(K32<2,"1-2 yrs",IF(K32<3,"2-3 yrs",IF(K32<5,"3-5 yrs","5+ yrs"))))) -> 1-2 yrs | M32: No | N32: =IF(M32="Yes","Memo flag - not ours / unknown / hold: resolve",IF(OR(COUNTIF(Summary!$C$4:$L$4,H32)>0,AND(A32="Philly",COUNTIF(Summary!$C$5:$L$5,H32)>0),AND(A32="TUR",COUNTIF(Summary!$C$6:$L$6,H32)>0)),"Fee amount - presumed company revenue",IF(H32<=Summary!$B$7,"Small amount - likely fee, review","Larger amount - likely includes agent commission"))) -> Larger amount - likely includes agent commission | O32: =IFERROR(INDEX('State Rules'!$C$5:$C$11,MATCH($B32,'State Rules'!$A$5:$A$11,0)),"") -> 1 | P32: =IF(OR(O32="",E32=""),"",EDATE(E32,12*O32)) -> 46184 | Q32: =IF(E32="","",IFERROR(EDATE(E32,12*INDEX('State Rules'!$E$5:$E$11,MATCH($B32,'State Rules'!$A$5:$A$11,0))),"")) -> 46915 | R32: =IF(P32="","",IFERROR(IF(P32<=INDEX('State Rules'!$I$5:$I$11,MATCH($B32,'State Rules'!$A$5:$A$11,0)),"Yes","No"),"")) -> Yes | S32: =IF(Q32="","",IFERROR(IF(Q32<=INDEX('State Rules'!$I$5:$I$11,MATCH($B32,'State Rules'!$A$5:$A$11,0)),"Yes","No"),"")) -> No | Z32: =IF(Q32="","",IF(Q32<=$B$4,N(W32)+N(X32),0)) -> 0 | AA32: =IF(OR(LEFT(N32,6)="Larger",LEFT(N32,4)="Memo"),H32,0) -> 324.75
A33: Dallas | B33: =IFERROR(INDEX(Summary!$B$10:$B$17,MATCH($A33,Summary!$A$10:$A$17,0)),"") -> TX | C33: Dallas | D33: 47 | E33: 45831 | F33: 41343 | H33: 300 | I33: 7618 Harbor Dr | J33: No | K33: =IF(E33="","",($B$4-E33)/365.25) -> 1.2867899 | L33: =IF(K33="","no date",IF(K33<1,"0-1 yrs",IF(K33<2,"1-2 yrs",IF(K33<3,"2-3 yrs",IF(K33<5,"3-5 yrs","5+ yrs"))))) -> 1-2 yrs | M33: No | N33: =IF(M33="Yes","Memo flag - not ours / unknown / hold: resolve",IF(OR(COUNTIF(Summary!$C$4:$L$4,H33)>0,AND(A33="Philly",COUNTIF(Summary!$C$5:$L$5,H33)>0),AND(A33="TUR",COUNTIF(Summary!$C$6:$L$6,H33)>0)),"Fee amount - presumed company revenue",IF(H33<=Summary!$B$7,"Small amount - likely fee, review","Larger amount - likely includes agent commission"))) -> Larger amount - likely includes agent commission | O33: =IFERROR(INDEX('State Rules'!$C$5:$C$11,MATCH($B33,'State Rules'!$A$5:$A$11,0)),"") -> 1 | P33: =IF(OR(O33="",E33=""),"",EDATE(E33,12*O33)) -> 46196 | Q33: =IF(E33="","",IFERROR(EDATE(E33,12*INDEX('State Rules'!$E$5:$E$11,MATCH($B33,'State Rules'!$A$5:$A$11,0))),"")) -> 46927 | R33: =IF(P33="","",IFERROR(IF(P33<=INDEX('State Rules'!$I$5:$I$11,MATCH($B33,'State Rules'!$A$5:$A$11,0)),"Yes","No"),"")) -> Yes | S33: =IF(Q33="","",IFERROR(IF(Q33<=INDEX('State Rules'!$I$5:$I$11,MATCH($B33,'State Rules'!$A$5:$A$11,0)),"Yes","No"),"")) -> No | Z33: =IF(Q33="","",IF(Q33<=$B$4,N(W33)+N(X33),0)) -> 0 | AA33: =IF(OR(LEFT(N33,6)="Larger",LEFT(N33,4)="Memo"),H33,0) -> 300
A34: Dallas | B34: =IFERROR(INDEX(Summary!$B$10:$B$17,MATCH($A34,Summary!$A$10:$A$17,0)),"") -> TX | C34: Dallas | D34: 48 | E34: 45968 | F34: 1233 | H34: 1239 | J34: No | K34: =IF(E34="","",($B$4-E34)/365.25) -> 0.91170431 | L34: =IF(K34="","no date",IF(K34<1,"0-1 yrs",IF(K34<2,"1-2 yrs",IF(K34<3,"2-3 yrs",IF(K34<5,"3-5 yrs","5+ yrs"))))) -> 0-1 yrs | M34: No | N34: =IF(M34="Yes","Memo flag - not ours / unknown / hold: resolve",IF(OR(COUNTIF(Summary!$C$4:$L$4,H34)>0,AND(A34="Philly",COUNTIF(Summary!$C$5:$L$5,H34)>0),AND(A34="TUR",COUNTIF(Summary!$C$6:$L$6,H34)>0)),"Fee amount - presumed company revenue",IF(H34<=Summary!$B$7,"Small amount - likely fee, review","Larger amount - likely includes agent commission"))) -> Larger amount - likely includes agent commission | O34: =IFERROR(INDEX('State Rules'!$C$5:$C$11,MATCH($B34,'State Rules'!$A$5:$A$11,0)),"") -> 1 | P34: =IF(OR(O34="",E34=""),"",EDATE(E34,12*O34)) -> 46333 | Q34: =IF(E34="","",IFERROR(EDATE(E34,12*INDEX('State Rules'!$E$5:$E$11,MATCH($B34,'State Rules'!$A$5:$A$11,0))),"")) -> 47064 | R34: =IF(P34="","",IFERROR(IF(P34<=INDEX('State Rules'!$I$5:$I$11,MATCH($B34,'State Rules'!$A$5:$A$11,0)),"Yes","No"),"")) -> Yes | S34: =IF(Q34="","",IFERROR(IF(Q34<=INDEX('State Rules'!$I$5:$I$11,MATCH($B34,'State Rules'!$A$5:$A$11,0)),"Yes","No"),"")) -> No | Z34: =IF(Q34="","",IF(Q34<=$B$4,N(W34)+N(X34),0)) -> 0 | AA34: =IF(OR(LEFT(N34,6)="Larger",LEFT(N34,4)="Memo"),H34,0) -> 1239
A35: Dallas | B35: =IFERROR(INDEX(Summary!$B$10:$B$17,MATCH($A35,Summary!$A$10:$A$17,0)),"") -> TX | C35: Dallas | D35: 49 | E35: 45996 | F35: 3356 | H35: 800 | I35: 208 Glenwic Place, agent: Deba Cadet | J35: No | K35: =IF(E35="","",($B$4-E35)/365.25) -> 0.83504449 | L35: =IF(K35="","no date",IF(K35<1,"0-1 yrs",IF(K35<2,"1-2 yrs",IF(K35<3,"2-3 yrs",IF(K35<5,"3-5 yrs","5+ yrs"))))) -> 0-1 yrs | M35: No | N35: =IF(M35="Yes","Memo flag - not ours / unknown / hold: resolve",IF(OR(COUNTIF(Summary!$C$4:$L$4,H35)>0,AND(A35="Philly",COUNTIF(Summary!$C$5:$L$5,H35)>0),AND(A35="TUR",COUNTIF(Summary!$C$6:$L$6,H35)>0)),"Fee amount - presumed company revenue",IF(H35<=Summary!$B$7,"Small amount - likely fee, review","Larger amount - likely includes agent commission"))) -> Larger amount - likely includes agent commission | O35: =IFERROR(INDEX('State Rules'!$C$5:$C$11,MATCH($B35,'State Rules'!$A$5:$A$11,0)),"") -> 1 | P35: =IF(OR(O35="",E35=""),"",EDATE(E35,12*O35)) -> 46361 | Q35: =IF(E35="","",IFERROR(EDATE(E35,12*INDEX('State Rules'!$E$5:$E$11,MATCH($B35,'State Rules'!$A$5:$A$11,0))),"")) -> 47092 | R35: =IF(P35="","",IFERROR(IF(P35<=INDEX('State Rules'!$I$5:$I$11,MATCH($B35,'State Rules'!$A$5:$A$11,0)),"Yes","No"),"")) -> Yes | S35: =IF(Q35="","",IFERROR(IF(Q35<=INDEX('State Rules'!$I$5:$I$11,MATCH($B35,'State Rules'!$A$5:$A$11,0)),"Yes","No"),"")) -> No | Z35: =IF(Q35="","",IF(Q35<=$B$4,N(W35)+N(X35),0)) -> 0 | AA35: =IF(OR(LEFT(N35,6)="Larger",LEFT(N35,4)="Memo"),H35,0) -> 800
A36: Dallas | B36: =IFERROR(INDEX(Summary!$B$10:$B$17,MATCH($A36,Summary!$A$10:$A$17,0)),"") -> TX | C36: Dallas | D36: 50 | E36: 46000 | F36: 353531 | H36: 824.12 | J36: No | K36: =IF(E36="","",($B$4-E36)/365.25) -> 0.82409309 | L36: =IF(K36="","no date",IF(K36<1,"0-1 yrs",IF(K36<2,"1-2 yrs",IF(K36<3,"2-3 yrs",IF(K36<5,"3-5 yrs","5+ yrs"))))) -> 0-1 yrs | M36: No | N36: =IF(M36="Yes","Memo flag - not ours / unknown / hold: resolve",IF(OR(COUNTIF(Summary!$C$4:$L$4,H36)>0,AND(A36="Philly",COUNTIF(Summary!$C$5:$L$5,H36)>0),AND(A36="TUR",COUNTIF(Summary!$C$6:$L$6,H36)>0)),"Fee amount - presumed company revenue",IF(H36<=Summary!$B$7,"Small amount - likely fee, review","Larger amount - likely includes agent commission"))) -> Larger amount - likely includes agent commission | O36: =IFERROR(INDEX('State Rules'!$C$5:$C$11,MATCH($B36,'State Rules'!$A$5:$A$11,0)),"") -> 1 | P36: =IF(OR(O36="",E36=""),"",EDATE(E36,12*O36)) -> 46365 | Q36: =IF(E36="","",IFERROR(EDATE(E36,12*INDEX('State Rules'!$E$5:$E$11,MATCH($B36,'State Rules'!$A$5:$A$11,0))),"")) -> 47096 | R36: =IF(P36="","",IFERROR(IF(P36<=INDEX('State Rules'!$I$5:$I$11,MATCH($B36,'State Rules'!$A$5:$A$11,0)),"Yes","No"),"")) -> Yes | S36: =IF(Q36="","",IFERROR(IF(Q36<=INDEX('State Rules'!$I$5:$I$11,MATCH($B36,'State Rules'!$A$5:$A$11,0)),"Yes","No"),"")) -> No | Z36: =IF(Q36="","",IF(Q36<=$B$4,N(W36)+N(X36),0)) -> 0 | AA36: =IF(OR(LEFT(N36,6)="Larger",LEFT(N36,4)="Memo"),H36,0) -> 824.12
A37: Dallas | B37: =IFERROR(INDEX(Summary!$B$10:$B$17,MATCH($A37,Summary!$A$10:$A$17,0)),"") -> TX | C37: Dallas | D37: 51 | E37: 46000 | F37: 515 | H37: 1450 | I37: Referral Fees R. Shaw #208 | J37: No | K37: =IF(E37="","",($B$4-E37)/365.25) -> 0.82409309 | L37: =IF(K37="","no date",IF(K37<1,"0-1 yrs",IF(K37<2,"1-2 yrs",IF(K37<3,"2-3 yrs",IF(K37<5,"3-5 yrs","5+ yrs"))))) -> 0-1 yrs | M37: No | N37: =IF(M37="Yes","Memo flag - not ours / unknown / hold: resolve",IF(OR(COUNTIF(Summary!$C$4:$L$4,H37)>0,AND(A37="Philly",COUNTIF(Summary!$C$5:$L$5,H37)>0),AND(A37="TUR",COUNTIF(Summary!$C$6:$L$6,H37)>0)),"Fee amount - presumed company revenue",IF(H37<=Summary!$B$7,"Small amount - likely fee, review","Larger amount - likely includes agent commission"))) -> Larger amount - likely includes agent commission | O37: =IFERROR(INDEX('State Rules'!$C$5:$C$11,MATCH($B37,'State Rules'!$A$5:$A$11,0)),"") -> 1 | P37: =IF(OR(O37="",E37=""),"",EDATE(E37,12*O37)) -> 46365 | Q37: =IF(E37="","",IFERROR(EDATE(E37,12*INDEX('State Rules'!$E$5:$E$11,MATCH($B37,'State Rules'!$A$5:$A$11,0))),"")) -> 47096 | R37: =IF(P37="","",IFERROR(IF(P37<=INDEX('State Rules'!$I$5:$I$11,MATCH($B37,'State Rules'!$A$5:$A$11,0)),"Yes","No"),"")) -> Yes | S37: =IF(Q37="","",IFERROR(IF(Q37<=INDEX('State Rules'!$I$5:$I$11,MATCH($B37,'State Rules'!$A$5:$A$11,0)),"Yes","No"),"")) -> No | Z37: =IF(Q37="","",IF(Q37<=$B$4,N(W37)+N(X37),0)) -> 0 | AA37: =IF(OR(LEFT(N37,6)="Larger",LEFT(N37,4)="Memo"),H37,0) -> 1450
A38: Dallas | B38: =IFERROR(INDEX(Summary!$B$10:$B$17,MATCH($A38,Summary!$A$10:$A$17,0)),"") -> TX | C38: Dallas | D38: 52 | E38: 46064 | F38: 27966 | G38: Coastal Realty Information | H38: 41.87 | J38: No | K38: =IF(E38="","",($B$4-E38)/365.25) -> 0.64887064 | L38: =IF(K38="","no date",IF(K38<1,"0-1 yrs",IF(K38<2,"1-2 yrs",IF(K38<3,"2-3 yrs",IF(K38<5,"3-5 yrs","5+ yrs"))))) -> 0-1 yrs | M38: No | N38: =IF(M38="Yes","Memo flag - not ours / unknown / hold: resolve",IF(OR(COUNTIF(Summary!$C$4:$L$4,H38)>0,AND(A38="Philly",COUNTIF(Summary!$C$5:$L$5,H38)>0),AND(A38="TUR",COUNTIF(Summary!$C$6:$L$6,H38)>0)),"Fee amount - presumed company revenue",IF(H38<=Summary!$B$7,"Small amount - likely fee, review","Larger amount - likely includes agent commission"))) -> Small amount - likely fee, review | O38: =IFERROR(INDEX('State Rules'!$C$5:$C$11,MATCH($B38,'State Rules'!$A$5:$A$11,0)),"") -> 1 | P38: =IF(OR(O38="",E38=""),"",EDATE(E38,12*O38)) -> 46429 | Q38: =IF(E38="","",IFERROR(EDATE(E38,12*INDEX('State Rules'!$E$5:$E$11,MATCH($B38,'State Rules'!$A$5:$A$11,0))),"")) -> 47160 | R38: =IF(P38="","",IFERROR(IF(P38<=INDEX('State Rules'!$I$5:$I$11,MATCH($B38,'State Rules'!$A$5:$A$11,0)),"Yes","No"),"")) -> Yes | S38: =IF(Q38="","",IFERROR(IF(Q38<=INDEX('State Rules'!$I$5:$I$11,MATCH($B38,'State Rules'!$A$5:$A$11,0)),"Yes","No"),"")) -> No | Z38: =IF(Q38="","",IF(Q38<=$B$4,N(W38)+N(X38),0)) -> 0 | AA38: =IF(OR(LEFT(N38,6)="Larger",LEFT(N38,4)="Memo"),H38,0) -> 0
A39: Dallas | B39: =IFERROR(INDEX(Summary!$B$10:$B$17,MATCH($A39,Summary!$A$10:$A$17,0)),"") -> TX | C39: Dallas | D39: 53 | E39: 46134 | F39: 573013801 | G39: Chicago Title of Texas | H39: 394 | I39: Commissions | J39: No | K39: =IF(E39="","",($B$4-E39)/365.25) -> 0.45722108 | L39: =IF(K39="","no date",IF(K39<1,"0-1 yrs",IF(K39<2,"1-2 yrs",IF(K39<3,"2-3 yrs",IF(K39<5,"3-5 yrs","5+ yrs"))))) -> 0-1 yrs | M39: No | N39: =IF(M39="Yes","Memo flag - not ours / unknown / hold: resolve",IF(OR(COUNTIF(Summary!$C$4:$L$4,H39)>0,AND(A39="Philly",COUNTIF(Summary!$C$5:$L$5,H39)>0),AND(A39="TUR",COUNTIF(Summary!$C$6:$L$6,H39)>0)),"Fee amount - presumed company revenue",IF(H39<=Summary!$B$7,"Small amount - likely fee, review","Larger amount - likely includes agent commission"))) -> Larger amount - likely includes agent commission | O39: =IFERROR(INDEX('State Rules'!$C$5:$C$11,MATCH($B39,'State Rules'!$A$5:$A$11,0)),"") -> 1 | P39: =IF(OR(O39="",E39=""),"",EDATE(E39,12*O39)) -> 46499 | Q39: =IF(E39="","",IFERROR(EDATE(E39,12*INDEX('State Rules'!$E$5:$E$11,MATCH($B39,'State Rules'!$A$5:$A$11,0))),"")) -> 47230 | R39: =IF(P39="","",IFERROR(IF(P39<=INDEX('State Rules'!$I$5:$I$11,MATCH($B39,'State Rules'!$A$5:$A$11,0)),"Yes","No"),"")) -> No | S39: =IF(Q39="","",IFERROR(IF(Q39<=INDEX('State Rules'!$I$5:$I$11,MATCH($B39,'State Rules'!$A$5:$A$11,0)),"Yes","No"),"")) -> No | Z39: =IF(Q39="","",IF(Q39<=$B$4,N(W39)+N(X39),0)) -> 0 | AA39: =IF(OR(LEFT(N39,6)="Larger",LEFT(N39,4)="Memo"),H39,0) -> 394
A40: Dallas | B40: =IFERROR(INDEX(Summary!$B$10:$B$17,MATCH($A40,Summary!$A$10:$A$17,0)),"") -> TX | C40: Dallas | D40: 54 | E40: 46146 | F40: 3601909 | H40: 540 | J40: No | K40: =IF(E40="","",($B$4-E40)/365.25) -> 0.42436687 | L40: =IF(K40="","no date",IF(K40<1,"0-1 yrs",IF(K40<2,"1-2 yrs",IF(K40<3,"2-3 yrs",IF(K40<5,"3-5 yrs","5+ yrs"))))) -> 0-1 yrs | M40: No | N40: =IF(M40="Yes","Memo flag - not ours / unknown / hold: resolve",IF(OR(COUNTIF(Summary!$C$4:$L$4,H40)>0,AND(A40="Philly",COUNTIF(Summary!$C$5:$L$5,H40)>0),AND(A40="TUR",COUNTIF(Summary!$C$6:$L$6,H40)>0)),"Fee amount - presumed company revenue",IF(H40<=Summary!$B$7,"Small amount - likely fee, review","Larger amount - likely includes agent commission"))) -> Larger amount - likely includes agent commission | O40: =IFERROR(INDEX('State Rules'!$C$5:$C$11,MATCH($B40,'State Rules'!$A$5:$A$11,0)),"") -> 1 | P40: =IF(OR(O40="",E40=""),"",EDATE(E40,12*O40)) -> 46511 | Q40: =IF(E40="","",IFERROR(EDATE(E40,12*INDEX('State Rules'!$E$5:$E$11,MATCH($B40,'State Rules'!$A$5:$A$11,0))),"")) -> 47242 | R40: =IF(P40="","",IFERROR(IF(P40<=INDEX('State Rules'!$I$5:$I$11,MATCH($B40,'State Rules'!$A$5:$A$11,0)),"Yes","No"),"")) -> No | S40: =IF(Q40="","",IFERROR(IF(Q40<=INDEX('State Rules'!$I$5:$I$11,MATCH($B40,'State Rules'!$A$5:$A$11,0)),"Yes","No"),"")) -> No | Z40: =IF(Q40="","",IF(Q40<=$B$4,N(W40)+N(X40),0)) -> 0 | AA40: =IF(OR(LEFT(N40,6)="Larger",LEFT(N40,4)="Memo"),H40,0) -> 540
A41: Dallas | B41: =IFERROR(INDEX(Summary!$B$10:$B$17,MATCH($A41,Summary!$A$10:$A$17,0)),"") -> TX | C41: Dallas | D41: 56 | E41: 46195 | F41: 104315 | G41: Phillips Edison Grocery Center | H41: 9761.14 | I41: Cashier's Check - No memo | J41: No | K41: =IF(E41="","",($B$4-E41)/365.25) -> 0.29021218 | L41: =IF(K41="","no date",IF(K41<1,"0-1 yrs",IF(K41<2,"1-2 yrs",IF(K41<3,"2-3 yrs",IF(K41<5,"3-5 yrs","5+ yrs"))))) -> 0-1 yrs | M41: Yes | N41: =IF(M41="Yes","Memo flag - not ours / unknown / hold: resolve",IF(OR(COUNTIF(Summary!$C$4:$L$4,H41)>0,AND(A41="Philly",COUNTIF(Summary!$C$5:$L$5,H41)>0),AND(A41="TUR",COUNTIF(Summary!$C$6:$L$6,H41)>0)),"Fee amount - presumed company revenue",IF(H41<=Summary!$B$7,"Small amount - likely fee, review","Larger amount - likely includes agent commission"))) -> Memo flag - not ours / unknown / hold: resolve | O41: =IFERROR(INDEX('State Rules'!$C$5:$C$11,MATCH($B41,'State Rules'!$A$5:$A$11,0)),"") -> 1 | P41: =IF(OR(O41="",E41=""),"",EDATE(E41,12*O41)) -> 46560 | Q41: =IF(E41="","",IFERROR(EDATE(E41,12*INDEX('State Rules'!$E$5:$E$11,MATCH($B41,'State Rules'!$A$5:$A$11,0))),"")) -> 47291 | R41: =IF(P41="","",IFERROR(IF(P41<=INDEX('State Rules'!$I$5:$I$11,MATCH($B41,'State Rules'!$A$5:$A$11,0)),"Yes","No"),"")) -> No | S41: =IF(Q41="","",IFERROR(IF(Q41<=INDEX('State Rules'!$I$5:$I$11,MATCH($B41,'State Rules'!$A$5:$A$11,0)),"Yes","No"),"")) -> No | Z41: =IF(Q41="","",IF(Q41<=$B$4,N(W41)+N(X41),0)) -> 0 | AA41: =IF(OR(LEFT(N41,6)="Larger",LEFT(N41,4)="Memo"),H41,0) -> 9761.14
A42: Dallas | B42: =IFERROR(INDEX(Summary!$B$10:$B$17,MATCH($A42,Summary!$A$10:$A$17,0)),"") -> TX | C42: Dallas | D42: 57 | E42: 46202 | F42: 1638 | G42: LROC, LLC | H42: 4176 | J42: No | K42: =IF(E42="","",($B$4-E42)/365.25) -> 0.27104723 | L42: =IF(K42="","no date",IF(K42<1,"0-1 yrs",IF(K42<2,"1-2 yrs",IF(K42<3,"2-3 yrs",IF(K42<5,"3-5 yrs","5+ yrs"))))) -> 0-1 yrs | M42: No | N42: =IF(M42="Yes","Memo flag - not ours / unknown / hold: resolve",IF(OR(COUNTIF(Summary!$C$4:$L$4,H42)>0,AND(A42="Philly",COUNTIF(Summary!$C$5:$L$5,H42)>0),AND(A42="TUR",COUNTIF(Summary!$C$6:$L$6,H42)>0)),"Fee amount - presumed company revenue",IF(H42<=Summary!$B$7,"Small amount - likely fee, review","Larger amount - likely includes agent commission"))) -> Larger amount - likely includes agent commission | O42: =IFERROR(INDEX('State Rules'!$C$5:$C$11,MATCH($B42,'State Rules'!$A$5:$A$11,0)),"") -> 1 | P42: =IF(OR(O42="",E42=""),"",EDATE(E42,12*O42)) -> 46567 | Q42: =IF(E42="","",IFERROR(EDATE(E42,12*INDEX('State Rules'!$E$5:$E$11,MATCH($B42,'State Rules'!$A$5:$A$11,0))),"")) -> 47298 | R42: =IF(P42="","",IFERROR(IF(P42<=INDEX('State Rules'!$I$5:$I$11,MATCH($B42,'State Rules'!$A$5:$A$11,0)),"Yes","No"),"")) -> No | S42: =IF(Q42="","",IFERROR(IF(Q42<=INDEX('State Rules'!$I$5:$I$11,MATCH($B42,'State Rules'!$A$5:$A$11,0)),"Yes","No"),"")) -> No | Z42: =IF(Q42="","",IF(Q42<=$B$4,N(W42)+N(X42),0)) -> 0 | AA42: =IF(OR(LEFT(N42,6)="Larger",LEFT(N42,4)="Memo"),H42,0) -> 4176
A43: Dallas | B43: =IFERROR(INDEX(Summary!$B$10:$B$17,MATCH($A43,Summary!$A$10:$A$17,0)),"") -> TX | C43: Dallas | D43: 58 | E43: 46213 | F43: 7226642918 | G43: Bellrock Upper North(?) | H43: 2280 | I43: [review check stub] | J43: No | K43: =IF(E43="","",($B$4-E43)/365.25) -> 0.24093087 | L43: =IF(K43="","no date",IF(K43<1,"0-1 yrs",IF(K43<2,"1-2 yrs",IF(K43<3,"2-3 yrs",IF(K43<5,"3-5 yrs","5+ yrs"))))) -> 0-1 yrs | M43: Yes | N43: =IF(M43="Yes","Memo flag - not ours / unknown / hold: resolve",IF(OR(COUNTIF(Summary!$C$4:$L$4,H43)>0,AND(A43="Philly",COUNTIF(Summary!$C$5:$L$5,H43)>0),AND(A43="TUR",COUNTIF(Summary!$C$6:$L$6,H43)>0)),"Fee amount - presumed company revenue",IF(H43<=Summary!$B$7,"Small amount - likely fee, review","Larger amount - likely includes agent commission"))) -> Memo flag - not ours / unknown / hold: resolve | O43: =IFERROR(INDEX('State Rules'!$C$5:$C$11,MATCH($B43,'State Rules'!$A$5:$A$11,0)),"") -> 1 | P43: =IF(OR(O43="",E43=""),"",EDATE(E43,12*O43)) -> 46578 | Q43: =IF(E43="","",IFERROR(EDATE(E43,12*INDEX('State Rules'!$E$5:$E$11,MATCH($B43,'State Rules'!$A$5:$A$11,0))),"")) -> 47309 | R43: =IF(P43="","",IFERROR(IF(P43<=INDEX('State Rules'!$I$5:$I$11,MATCH($B43,'State Rules'!$A$5:$A$11,0)),"Yes","No"),"")) -> No | S43: =IF(Q43="","",IFERROR(IF(Q43<=INDEX('State Rules'!$I$5:$I$11,MATCH($B43,'State Rules'!$A$5:$A$11,0)),"Yes","No"),"")) -> No | Z43: =IF(Q43="","",IF(Q43<=$B$4,N(W43)+N(X43),0)) -> 0 | AA43: =IF(OR(LEFT(N43,6)="Larger",LEFT(N43,4)="Memo"),H43,0) -> 2280
A44: Dallas | B44: =IFERROR(INDEX(Summary!$B$10:$B$17,MATCH($A44,Summary!$A$10:$A$17,0)),"") -> TX | C44: Dallas | D44: 59 | E44: 46216 | F44: 1480 | G44: NEIMAX LLC | H44: 238 | I44: Rental Commission | J44: No | K44: =IF(E44="","",($B$4-E44)/365.25) -> 0.23271732 | L44: =IF(K44="","no date",IF(K44<1,"0-1 yrs",IF(K44<2,"1-2 yrs",IF(K44<3,"2-3 yrs",IF(K44<5,"3-5 yrs","5+ yrs"))))) -> 0-1 yrs | M44: No | N44: =IF(M44="Yes","Memo flag - not ours / unknown / hold: resolve",IF(OR(COUNTIF(Summary!$C$4:$L$4,H44)>0,AND(A44="Philly",COUNTIF(Summary!$C$5:$L$5,H44)>0),AND(A44="TUR",COUNTIF(Summary!$C$6:$L$6,H44)>0)),"Fee amount - presumed company revenue",IF(H44<=Summary!$B$7,"Small amount - likely fee, review","Larger amount - likely includes agent commission"))) -> Small amount - likely fee, review | O44: =IFERROR(INDEX('State Rules'!$C$5:$C$11,MATCH($B44,'State Rules'!$A$5:$A$11,0)),"") -> 1 | P44: =IF(OR(O44="",E44=""),"",EDATE(E44,12*O44)) -> 46581 | Q44: =IF(E44="","",IFERROR(EDATE(E44,12*INDEX('State Rules'!$E$5:$E$11,MATCH($B44,'State Rules'!$A$5:$A$11,0))),"")) -> 47312 | R44: =IF(P44="","",IFERROR(IF(P44<=INDEX('State Rules'!$I$5:$I$11,MATCH($B44,'State Rules'!$A$5:$A$11,0)),"Yes","No"),"")) -> No | S44: =IF(Q44="","",IFERROR(IF(Q44<=INDEX('State Rules'!$I$5:$I$11,MATCH($B44,'State Rules'!$A$5:$A$11,0)),"Yes","No"),"")) -> No | Z44: =IF(Q44="","",IF(Q44<=$B$4,N(W44)+N(X44),0)) -> 0 | AA44: =IF(OR(LEFT(N44,6)="Larger",LEFT(N44,4)="Memo"),H44,0) -> 0
A45: Dallas | B45: =IFERROR(INDEX(Summary!$B$10:$B$17,MATCH($A45,Summary!$A$10:$A$17,0)),"") -> TX | C45: Dallas | D45: 60 | E45: 46216 | F45: 928546934 | H45: 89.75 | I45: 630 Woodacre | J45: No | K45: =IF(E45="","",($B$4-E45)/365.25) -> 0.23271732 | L45: =IF(K45="","no date",IF(K45<1,"0-1 yrs",IF(K45<2,"1-2 yrs",IF(K45<3,"2-3 yrs",IF(K45<5,"3-5 yrs","5+ yrs"))))) -> 0-1 yrs | M45: No | N45: =IF(M45="Yes","Memo flag - not ours / unknown / hold: resolve",IF(OR(COUNTIF(Summary!$C$4:$L$4,H45)>0,AND(A45="Philly",COUNTIF(Summary!$C$5:$L$5,H45)>0),AND(A45="TUR",COUNTIF(Summary!$C$6:$L$6,H45)>0)),"Fee amount - presumed company revenue",IF(H45<=Summary!$B$7,"Small amount - likely fee, review","Larger amount - likely includes agent commission"))) -> Small amount - likely fee, review | O45: =IFERROR(INDEX('State Rules'!$C$5:$C$11,MATCH($B45,'State Rules'!$A$5:$A$11,0)),"") -> 1 | P45: =IF(OR(O45="",E45=""),"",EDATE(E45,12*O45)) -> 46581 | Q45: =IF(E45="","",IFERROR(EDATE(E45,12*INDEX('State Rules'!$E$5:$E$11,MATCH($B45,'State Rules'!$A$5:$A$11,0))),"")) -> 47312 | R45: =IF(P45="","",IFERROR(IF(P45<=INDEX('State Rules'!$I$5:$I$11,MATCH($B45,'State Rules'!$A$5:$A$11,0)),"Yes","No"),"")) -> No | S45: =IF(Q45="","",IFERROR(IF(Q45<=INDEX('State Rules'!$I$5:$I$11,MATCH($B45,'State Rules'!$A$5:$A$11,0)),"Yes","No"),"")) -> No | Z45: =IF(Q45="","",IF(Q45<=$B$4,N(W45)+N(X45),0)) -> 0 | AA45: =IF(OR(LEFT(N45,6)="Larger",LEFT(N45,4)="Memo"),H45,0) -> 0
A46: Dallas | B46: =IFERROR(INDEX(Summary!$B$10:$B$17,MATCH($A46,Summary!$A$10:$A$17,0)),"") -> TX | C46: Dallas | D46: 61 | E46: 46223 | F46: 103690 | G46: MH Title | H46: 69 | I46: 510 Simmons Dr | J46: No | K46: =IF(E46="","",($B$4-E46)/365.25) -> 0.21355236 | L46: =IF(K46="","no date",IF(K46<1,"0-1 yrs",IF(K46<2,"1-2 yrs",IF(K46<3,"2-3 yrs",IF(K46<5,"3-5 yrs","5+ yrs"))))) -> 0-1 yrs | M46: No | N46: =IF(M46="Yes","Memo flag - not ours / unknown / hold: resolve",IF(OR(COUNTIF(Summary!$C$4:$L$4,H46)>0,AND(A46="Philly",COUNTIF(Summary!$C$5:$L$5,H46)>0),AND(A46="TUR",COUNTIF(Summary!$C$6:$L$6,H46)>0)),"Fee amount - presumed company revenue",IF(H46<=Summary!$B$7,"Small amount - likely fee, review","Larger amount - likely includes agent commission"))) -> Fee amount - presumed company revenue | O46: =IFERROR(INDEX('State Rules'!$C$5:$C$11,MATCH($B46,'State Rules'!$A$5:$A$11,0)),"") -> 1 | P46: =IF(OR(O46="",E46=""),"",EDATE(E46,12*O46)) -> 46588 | Q46: =IF(E46="","",IFERROR(EDATE(E46,12*INDEX('State Rules'!$E$5:$E$11,MATCH($B46,'State Rules'!$A$5:$A$11,0))),"")) -> 47319 | R46: =IF(P46="","",IFERROR(IF(P46<=INDEX('State Rules'!$I$5:$I$11,MATCH($B46,'State Rules'!$A$5:$A$11,0)),"Yes","No"),"")) -> No | S46: =IF(Q46="","",IFERROR(IF(Q46<=INDEX('State Rules'!$I$5:$I$11,MATCH($B46,'State Rules'!$A$5:$A$11,0)),"Yes","No"),"")) -> No | Z46: =IF(Q46="","",IF(Q46<=$B$4,N(W46)+N(X46),0)) -> 0 | AA46: =IF(OR(LEFT(N46,6)="Larger",LEFT(N46,4)="Memo"),H46,0) -> 0
A47: Dallas | B47: =IFERROR(INDEX(Summary!$B$10:$B$17,MATCH($A47,Summary!$A$10:$A$17,0)),"") -> TX | C47: Dallas | D47: 62 | E47: 46224 | F47: 82931 | G47: Steward Title | H47: 6078 | I47: UR25025(?) | J47: No | K47: =IF(E47="","",($B$4-E47)/365.25) -> 0.21081451 | L47: =IF(K47="","no date",IF(K47<1,"0-1 yrs",IF(K47<2,"1-2 yrs",IF(K47<3,"2-3 yrs",IF(K47<5,"3-5 yrs","5+ yrs"))))) -> 0-1 yrs | M47: Yes | N47: =IF(M47="Yes","Memo flag - not ours / unknown / hold: resolve",IF(OR(COUNTIF(Summary!$C$4:$L$4,H47)>0,AND(A47="Philly",COUNTIF(Summary!$C$5:$L$5,H47)>0),AND(A47="TUR",COUNTIF(Summary!$C$6:$L$6,H47)>0)),"Fee amount - presumed company revenue",IF(H47<=Summary!$B$7,"Small amount - likely fee, review","Larger amount - likely includes agent commission"))) -> Memo flag - not ours / unknown / hold: resolve | O47: =IFERROR(INDEX('State Rules'!$C$5:$C$11,MATCH($B47,'State Rules'!$A$5:$A$11,0)),"") -> 1 | P47: =IF(OR(O47="",E47=""),"",EDATE(E47,12*O47)) -> 46589 | Q47: =IF(E47="","",IFERROR(EDATE(E47,12*INDEX('State Rules'!$E$5:$E$11,MATCH($B47,'State Rules'!$A$5:$A$11,0))),"")) -> 47320 | R47: =IF(P47="","",IFERROR(IF(P47<=INDEX('State Rules'!$I$5:$I$11,MATCH($B47,'State Rules'!$A$5:$A$11,0)),"Yes","No"),"")) -> No | S47: =IF(Q47="","",IFERROR(IF(Q47<=INDEX('State Rules'!$I$5:$I$11,MATCH($B47,'State Rules'!$A$5:$A$11,0)),"Yes","No"),"")) -> No | Z47: =IF(Q47="","",IF(Q47<=$B$4,N(W47)+N(X47),0)) -> 0 | AA47: =IF(OR(LEFT(N47,6)="Larger",LEFT(N47,4)="Memo"),H47,0) -> 6078
A48: Dallas | B48: =IFERROR(INDEX(Summary!$B$10:$B$17,MATCH($A48,Summary!$A$10:$A$17,0)),"") -> TX | C48: Dallas | D48: 63 | E48: 46231 | F48: 392627 | G48: Long Realty | H48: 701.5 | I48: 37753 S. Golf Course Dr.(?) | J48: No | K48: =IF(E48="","",($B$4-E48)/365.25) -> 0.19164956 | L48: =IF(K48="","no date",IF(K48<1,"0-1 yrs",IF(K48<2,"1-2 yrs",IF(K48<3,"2-3 yrs",IF(K48<5,"3-5 yrs","5+ yrs"))))) -> 0-1 yrs | M48: Yes | N48: =IF(M48="Yes","Memo flag - not ours / unknown / hold: resolve",IF(OR(COUNTIF(Summary!$C$4:$L$4,H48)>0,AND(A48="Philly",COUNTIF(Summary!$C$5:$L$5,H48)>0),AND(A48="TUR",COUNTIF(Summary!$C$6:$L$6,H48)>0)),"Fee amount - presumed company revenue",IF(H48<=Summary!$B$7,"Small amount - likely fee, review","Larger amount - likely includes agent commission"))) -> Memo flag - not ours / unknown / hold: resolve | O48: =IFERROR(INDEX('State Rules'!$C$5:$C$11,MATCH($B48,'State Rules'!$A$5:$A$11,0)),"") -> 1 | P48: =IF(OR(O48="",E48=""),"",EDATE(E48,12*O48)) -> 46596 | Q48: =IF(E48="","",IFERROR(EDATE(E48,12*INDEX('State Rules'!$E$5:$E$11,MATCH($B48,'State Rules'!$A$5:$A$11,0))),"")) -> 47327 | R48: =IF(P48="","",IFERROR(IF(P48<=INDEX('State Rules'!$I$5:$I$11,MATCH($B48,'State Rules'!$A$5:$A$11,0)),"Yes","No"),"")) -> No | S48: =IF(Q48="","",IFERROR(IF(Q48<=INDEX('State Rules'!$I$5:$I$11,MATCH($B48,'State Rules'!$A$5:$A$11,0)),"Yes","No"),"")) -> No | Z48: =IF(Q48="","",IF(Q48<=$B$4,N(W48)+N(X48),0)) -> 0 | AA48: =IF(OR(LEFT(N48,6)="Larger",LEFT(N48,4)="Memo"),H48,0) -> 701.5
A49: Dallas | B49: =IFERROR(INDEX(Summary!$B$10:$B$17,MATCH($A49,Summary!$A$10:$A$17,0)),"") -> TX | C49: Dallas | D49: 66 | E49: 46241 | F49: 2500 | G49: S2 Hyde Park | H49: 532.5 | J49: No | K49: =IF(E49="","",($B$4-E49)/365.25) -> 0.16427105 | L49: =IF(K49="","no date",IF(K49<1,"0-1 yrs",IF(K49<2,"1-2 yrs",IF(K49<3,"2-3 yrs",IF(K49<5,"3-5 yrs","5+ yrs"))))) -> 0-1 yrs | M49: No | N49: =IF(M49="Yes","Memo flag - not ours / unknown / hold: resolve",IF(OR(COUNTIF(Summary!$C$4:$L$4,H49)>0,AND(A49="Philly",COUNTIF(Summary!$C$5:$L$5,H49)>0),AND(A49="TUR",COUNTIF(Summary!$C$6:$L$6,H49)>0)),"Fee amount - presumed company revenue",IF(H49<=Summary!$B$7,"Small amount - likely fee, review","Larger amount - likely includes agent commission"))) -> Larger amount - likely includes agent commission | O49: =IFERROR(INDEX('State Rules'!$C$5:$C$11,MATCH($B49,'State Rules'!$A$5:$A$11,0)),"") -> 1 | P49: =IF(OR(O49="",E49=""),"",EDATE(E49,12*O49)) -> 46606 | Q49: =IF(E49="","",IFERROR(EDATE(E49,12*INDEX('State Rules'!$E$5:$E$11,MATCH($B49,'State Rules'!$A$5:$A$11,0))),"")) -> 47337 | R49: =IF(P49="","",IFERROR(IF(P49<=INDEX('State Rules'!$I$5:$I$11,MATCH($B49,'State Rules'!$A$5:$A$11,0)),"Yes","No"),"")) -> No | S49: =IF(Q49="","",IFERROR(IF(Q49<=INDEX('State Rules'!$I$5:$I$11,MATCH($B49,'State Rules'!$A$5:$A$11,0)),"Yes","No"),"")) -> No | Z49: =IF(Q49="","",IF(Q49<=$B$4,N(W49)+N(X49),0)) -> 0 | AA49: =IF(OR(LEFT(N49,6)="Larger",LEFT(N49,4)="Memo"),H49,0) -> 532.5
A50: Dallas | B50: =IFERROR(INDEX(Summary!$B$10:$B$17,MATCH($A50,Summary!$A$10:$A$17,0)),"") -> TX | C50: Dallas | D50: 67 | E50: 46244 | F50: 2285 | G50: Rendon Realty | H50: 2691 | I50: 3205 Harvard St | J50: No | K50: =IF(E50="","",($B$4-E50)/365.25) -> 0.15605749 | L50: =IF(K50="","no date",IF(K50<1,"0-1 yrs",IF(K50<2,"1-2 yrs",IF(K50<3,"2-3 yrs",IF(K50<5,"3-5 yrs","5+ yrs"))))) -> 0-1 yrs | M50: No | N50: =IF(M50="Yes","Memo flag - not ours / unknown / hold: resolve",IF(OR(COUNTIF(Summary!$C$4:$L$4,H50)>0,AND(A50="Philly",COUNTIF(Summary!$C$5:$L$5,H50)>0),AND(A50="TUR",COUNTIF(Summary!$C$6:$L$6,H50)>0)),"Fee amount - presumed company revenue",IF(H50<=Summary!$B$7,"Small amount - likely fee, review","Larger amount - likely includes agent commission"))) -> Larger amount - likely includes agent commission | O50: =IFERROR(INDEX('State Rules'!$C$5:$C$11,MATCH($B50,'State Rules'!$A$5:$A$11,0)),"") -> 1 | P50: =IF(OR(O50="",E50=""),"",EDATE(E50,12*O50)) -> 46609 | Q50: =IF(E50="","",IFERROR(EDATE(E50,12*INDEX('State Rules'!$E$5:$E$11,MATCH($B50,'State Rules'!$A$5:$A$11,0))),"")) -> 47340 | R50: =IF(P50="","",IFERROR(IF(P50<=INDEX('State Rules'!$I$5:$I$11,MATCH($B50,'State Rules'!$A$5:$A$11,0)),"Yes","No"),"")) -> No | S50: =IF(Q50="","",IFERROR(IF(Q50<=INDEX('State Rules'!$I$5:$I$11,MATCH($B50,'State Rules'!$A$5:$A$11,0)),"Yes","No"),"")) -> No | Z50: =IF(Q50="","",IF(Q50<=$B$4,N(W50)+N(X50),0)) -> 0 | AA50: =IF(OR(LEFT(N50,6)="Larger",LEFT(N50,4)="Memo"),H50,0) -> 2691
A51: Dallas | B51: =IFERROR(INDEX(Summary!$B$10:$B$17,MATCH($A51,Summary!$A$10:$A$17,0)),"") -> TX | C51: Dallas | D51: 68 | E51: 46245 | F51: 2257 | G51: Daniel Elms | H51: 1000 | I51: 5110 Lyndsley | J51: No | K51: =IF(E51="","",($B$4-E51)/365.25) -> 0.15331964 | L51: =IF(K51="","no date",IF(K51<1,"0-1 yrs",IF(K51<2,"1-2 yrs",IF(K51<3,"2-3 yrs",IF(K51<5,"3-5 yrs","5+ yrs"))))) -> 0-1 yrs | M51: No | N51: =IF(M51="Yes","Memo flag - not ours / unknown / hold: resolve",IF(OR(COUNTIF(Summary!$C$4:$L$4,H51)>0,AND(A51="Philly",COUNTIF(Summary!$C$5:$L$5,H51)>0),AND(A51="TUR",COUNTIF(Summary!$C$6:$L$6,H51)>0)),"Fee amount - presumed company revenue",IF(H51<=Summary!$B$7,"Small amount - likely fee, review","Larger amount - likely includes agent commission"))) -> Larger amount - likely includes agent commission | O51: =IFERROR(INDEX('State Rules'!$C$5:$C$11,MATCH($B51,'State Rules'!$A$5:$A$11,0)),"") -> 1 | P51: =IF(OR(O51="",E51=""),"",EDATE(E51,12*O51)) -> 46610 | Q51: =IF(E51="","",IFERROR(EDATE(E51,12*INDEX('State Rules'!$E$5:$E$11,MATCH($B51,'State Rules'!$A$5:$A$11,0))),"")) -> 47341 | R51: =IF(P51="","",IFERROR(IF(P51<=INDEX('State Rules'!$I$5:$I$11,MATCH($B51,'State Rules'!$A$5:$A$11,0)),"Yes","No"),"")) -> No | S51: =IF(Q51="","",IFERROR(IF(Q51<=INDEX('State Rules'!$I$5:$I$11,MATCH($B51,'State Rules'!$A$5:$A$11,0)),"Yes","No"),"")) -> No | Z51: =IF(Q51="","",IF(Q51<=$B$4,N(W51)+N(X51),0)) -> 0 | AA51: =IF(OR(LEFT(N51,6)="Larger",LEFT(N51,4)="Memo"),H51,0) -> 1000
A52: Dallas | B52: =IFERROR(INDEX(Summary!$B$10:$B$17,MATCH($A52,Summary!$A$10:$A$17,0)),"") -> TX | C52: Dallas | D52: 72 | E52: 46255 | F52: 1675 | G52: Tracy Realty | H52: 900 | I52: 410 E. Brackett | J52: No | K52: =IF(E52="","",($B$4-E52)/365.25) -> 0.12594114 | L52: =IF(K52="","no date",IF(K52<1,"0-1 yrs",IF(K52<2,"1-2 yrs",IF(K52<3,"2-3 yrs",IF(K52<5,"3-5 yrs","5+ yrs"))))) -> 0-1 yrs | M52: No | N52: =IF(M52="Yes","Memo flag - not ours / unknown / hold: resolve",IF(OR(COUNTIF(Summary!$C$4:$L$4,H52)>0,AND(A52="Philly",COUNTIF(Summary!$C$5:$L$5,H52)>0),AND(A52="TUR",COUNTIF(Summary!$C$6:$L$6,H52)>0)),"Fee amount - presumed company revenue",IF(H52<=Summary!$B$7,"Small amount - likely fee, review","Larger amount - likely includes agent commission"))) -> Larger amount - likely includes agent commission | O52: =IFERROR(INDEX('State Rules'!$C$5:$C$11,MATCH($B52,'State Rules'!$A$5:$A$11,0)),"") -> 1 | P52: =IF(OR(O52="",E52=""),"",EDATE(E52,12*O52)) -> 46620 | Q52: =IF(E52="","",IFERROR(EDATE(E52,12*INDEX('State Rules'!$E$5:$E$11,MATCH($B52,'State Rules'!$A$5:$A$11,0))),"")) -> 47351 | R52: =IF(P52="","",IFERROR(IF(P52<=INDEX('State Rules'!$I$5:$I$11,MATCH($B52,'State Rules'!$A$5:$A$11,0)),"Yes","No"),"")) -> No | S52: =IF(Q52="","",IFERROR(IF(Q52<=INDEX('State Rules'!$I$5:$I$11,MATCH($B52,'State Rules'!$A$5:$A$11,0)),"Yes","No"),"")) -> No | Z52: =IF(Q52="","",IF(Q52<=$B$4,N(W52)+N(X52),0)) -> 0 | AA52: =IF(OR(LEFT(N52,6)="Larger",LEFT(N52,4)="Memo"),H52,0) -> 900
A53: Dallas | B53: =IFERROR(INDEX(Summary!$B$10:$B$17,MATCH($A53,Summary!$A$10:$A$17,0)),"") -> TX | C53: Dallas | D53: 73 | E53: 46255 | F53: 178460 | G53: eXp Realty | H53: 875 | I53: 1012 Bessie Dr, | J53: No | K53: =IF(E53="","",($B$4-E53)/365.25) -> 0.12594114 | L53: =IF(K53="","no date",IF(K53<1,"0-1 yrs",IF(K53<2,"1-2 yrs",IF(K53<3,"2-3 yrs",IF(K53<5,"3-5 yrs","5+ yrs"))))) -> 0-1 yrs | M53: No | N53: =IF(M53="Yes","Memo flag - not ours / unknown / hold: resolve",IF(OR(COUNTIF(Summary!$C$4:$L$4,H53)>0,AND(A53="Philly",COUNTIF(Summary!$C$5:$L$5,H53)>0),AND(A53="TUR",COUNTIF(Summary!$C$6:$L$6,H53)>0)),"Fee amount - presumed company revenue",IF(H53<=Summary!$B$7,"Small amount - likely fee, review","Larger amount - likely includes agent commission"))) -> Larger amount - likely includes agent commission | O53: =IFERROR(INDEX('State Rules'!$C$5:$C$11,MATCH($B53,'State Rules'!$A$5:$A$11,0)),"") -> 1 | P53: =IF(OR(O53="",E53=""),"",EDATE(E53,12*O53)) -> 46620 | Q53: =IF(E53="","",IFERROR(EDATE(E53,12*INDEX('State Rules'!$E$5:$E$11,MATCH($B53,'State Rules'!$A$5:$A$11,0))),"")) -> 47351 | R53: =IF(P53="","",IFERROR(IF(P53<=INDEX('State Rules'!$I$5:$I$11,MATCH($B53,'State Rules'!$A$5:$A$11,0)),"Yes","No"),"")) -> No | S53: =IF(Q53="","",IFERROR(IF(Q53<=INDEX('State Rules'!$I$5:$I$11,MATCH($B53,'State Rules'!$A$5:$A$11,0)),"Yes","No"),"")) -> No | Z53: =IF(Q53="","",IF(Q53<=$B$4,N(W53)+N(X53),0)) -> 0 | AA53: =IF(OR(LEFT(N53,6)="Larger",LEFT(N53,4)="Memo"),H53,0) -> 875
A54: Dallas | B54: =IFERROR(INDEX(Summary!$B$10:$B$17,MATCH($A54,Summary!$A$10:$A$17,0)),"") -> TX | C54: Dallas | D54: 78 | E54: 46262 | F54: 1235 | G54: Mazahra Pasha Mohammad | H54: 1400 | I54: 6401 Everest Dr | J54: No | K54: =IF(E54="","",($B$4-E54)/365.25) -> 0.10677618 | L54: =IF(K54="","no date",IF(K54<1,"0-1 yrs",IF(K54<2,"1-2 yrs",IF(K54<3,"2-3 yrs",IF(K54<5,"3-5 yrs","5+ yrs"))))) -> 0-1 yrs | M54: No | N54: =IF(M54="Yes","Memo flag - not ours / unknown / hold: resolve",IF(OR(COUNTIF(Summary!$C$4:$L$4,H54)>0,AND(A54="Philly",COUNTIF(Summary!$C$5:$L$5,H54)>0),AND(A54="TUR",COUNTIF(Summary!$C$6:$L$6,H54)>0)),"Fee amount - presumed company revenue",IF(H54<=Summary!$B$7,"Small amount - likely fee, review","Larger amount - likely includes agent commission"))) -> Larger amount - likely includes agent commission | O54: =IFERROR(INDEX('State Rules'!$C$5:$C$11,MATCH($B54,'State Rules'!$A$5:$A$11,0)),"") -> 1 | P54: =IF(OR(O54="",E54=""),"",EDATE(E54,12*O54)) -> 46627 | Q54: =IF(E54="","",IFERROR(EDATE(E54,12*INDEX('State Rules'!$E$5:$E$11,MATCH($B54,'State Rules'!$A$5:$A$11,0))),"")) -> 47358 | R54: =IF(P54="","",IFERROR(IF(P54<=INDEX('State Rules'!$I$5:$I$11,MATCH($B54,'State Rules'!$A$5:$A$11,0)),"Yes","No"),"")) -> No | S54: =IF(Q54="","",IFERROR(IF(Q54<=INDEX('State Rules'!$I$5:$I$11,MATCH($B54,'State Rules'!$A$5:$A$11,0)),"Yes","No"),"")) -> No | Z54: =IF(Q54="","",IF(Q54<=$B$4,N(W54)+N(X54),0)) -> 0 | AA54: =IF(OR(LEFT(N54,6)="Larger",LEFT(N54,4)="Memo"),H54,0) -> 1400
A55: Dallas | B55: =IFERROR(INDEX(Summary!$B$10:$B$17,MATCH($A55,Summary!$A$10:$A$17,0)),"") -> TX | C55: Dallas | D55: 79 | E55: 46262 | F55: 4790 | H55: 2936.74 | I55: 2402 Navigation(?) Blvd. 316 & 843 | J55: No | K55: =IF(E55="","",($B$4-E55)/365.25) -> 0.10677618 | L55: =IF(K55="","no date",IF(K55<1,"0-1 yrs",IF(K55<2,"1-2 yrs",IF(K55<3,"2-3 yrs",IF(K55<5,"3-5 yrs","5+ yrs"))))) -> 0-1 yrs | M55: Yes | N55: =IF(M55="Yes","Memo flag - not ours / unknown / hold: resolve",IF(OR(COUNTIF(Summary!$C$4:$L$4,H55)>0,AND(A55="Philly",COUNTIF(Summary!$C$5:$L$5,H55)>0),AND(A55="TUR",COUNTIF(Summary!$C$6:$L$6,H55)>0)),"Fee amount - presumed company revenue",IF(H55<=Summary!$B$7,"Small amount - likely fee, review","Larger amount - likely includes agent commission"))) -> Memo flag - not ours / unknown / hold: resolve | O55: =IFERROR(INDEX('State Rules'!$C$5:$C$11,MATCH($B55,'State Rules'!$A$5:$A$11,0)),"") -> 1 | P55: =IF(OR(O55="",E55=""),"",EDATE(E55,12*O55)) -> 46627 | Q55: =IF(E55="","",IFERROR(EDATE(E55,12*INDEX('State Rules'!$E$5:$E$11,MATCH($B55,'State Rules'!$A$5:$A$11,0))),"")) -> 47358 | R55: =IF(P55="","",IFERROR(IF(P55<=INDEX('State Rules'!$I$5:$I$11,MATCH($B55,'State Rules'!$A$5:$A$11,0)),"Yes","No"),"")) -> No | S55: =IF(Q55="","",IFERROR(IF(Q55<=INDEX('State Rules'!$I$5:$I$11,MATCH($B55,'State Rules'!$A$5:$A$11,0)),"Yes","No"),"")) -> No | Z55: =IF(Q55="","",IF(Q55<=$B$4,N(W55)+N(X55),0)) -> 0 | AA55: =IF(OR(LEFT(N55,6)="Larger",LEFT(N55,4)="Memo"),H55,0) -> 2936.74
A56: Dallas | B56: =IFERROR(INDEX(Summary!$B$10:$B$17,MATCH($A56,Summary!$A$10:$A$17,0)),"") -> TX | C56: Dallas | D56: 80 | E56: 46265 | F56: 1515 | G56: Blue Bpmmet Properties | H56: 750 | I56: Gaylord Drive 8931 #157 | J56: No | K56: =IF(E56="","",($B$4-E56)/365.25) -> 0.098562628 | L56: =IF(K56="","no date",IF(K56<1,"0-1 yrs",IF(K56<2,"1-2 yrs",IF(K56<3,"2-3 yrs",IF(K56<5,"3-5 yrs","5+ yrs"))))) -> 0-1 yrs | M56: No | N56: =IF(M56="Yes","Memo flag - not ours / unknown / hold: resolve",IF(OR(COUNTIF(Summary!$C$4:$L$4,H56)>0,AND(A56="Philly",COUNTIF(Summary!$C$5:$L$5,H56)>0),AND(A56="TUR",COUNTIF(Summary!$C$6:$L$6,H56)>0)),"Fee amount - presumed company revenue",IF(H56<=Summary!$B$7,"Small amount - likely fee, review","Larger amount - likely includes agent commission"))) -> Larger amount - likely includes agent commission | O56: =IFERROR(INDEX('State Rules'!$C$5:$C$11,MATCH($B56,'State Rules'!$A$5:$A$11,0)),"") -> 1 | P56: =IF(OR(O56="",E56=""),"",EDATE(E56,12*O56)) -> 46630 | Q56: =IF(E56="","",IFERROR(EDATE(E56,12*INDEX('State Rules'!$E$5:$E$11,MATCH($B56,'State Rules'!$A$5:$A$11,0))),"")) -> 47361 | R56: =IF(P56="","",IFERROR(IF(P56<=INDEX('State Rules'!$I$5:$I$11,MATCH($B56,'State Rules'!$A$5:$A$11,0)),"Yes","No"),"")) -> No | S56: =IF(Q56="","",IFERROR(IF(Q56<=INDEX('State Rules'!$I$5:$I$11,MATCH($B56,'State Rules'!$A$5:$A$11,0)),"Yes","No"),"")) -> No | Z56: =IF(Q56="","",IF(Q56<=$B$4,N(W56)+N(X56),0)) -> 0 | AA56: =IF(OR(LEFT(N56,6)="Larger",LEFT(N56,4)="Memo"),H56,0) -> 750
A57: Houston | B57: =IFERROR(INDEX(Summary!$B$10:$B$17,MATCH($A57,Summary!$A$10:$A$17,0)),"") -> TX | C57: Houston | D57: 21 | E57: 44592 | F57: 17830 | H57: 539.6 | J57: No | K57: =IF(E57="","",($B$4-E57)/365.25) -> 4.678987 | L57: =IF(K57="","no date",IF(K57<1,"0-1 yrs",IF(K57<2,"1-2 yrs",IF(K57<3,"2-3 yrs",IF(K57<5,"3-5 yrs","5+ yrs"))))) -> 3-5 yrs | M57: No | N57: =IF(M57="Yes","Memo flag - not ours / unknown / hold: resolve",IF(OR(COUNTIF(Summary!$C$4:$L$4,H57)>0,AND(A57="Philly",COUNTIF(Summary!$C$5:$L$5,H57)>0),AND(A57="TUR",COUNTIF(Summary!$C$6:$L$6,H57)>0)),"Fee amount - presumed company revenue",IF(H57<=Summary!$B$7,"Small amount - likely fee, review","Larger amount - likely includes agent commission"))) -> Larger amount - likely includes agent commission | O57: =IFERROR(INDEX('State Rules'!$C$5:$C$11,MATCH($B57,'State Rules'!$A$5:$A$11,0)),"") -> 1 | P57: =IF(OR(O57="",E57=""),"",EDATE(E57,12*O57)) -> 44957 | Q57: =IF(E57="","",IFERROR(EDATE(E57,12*INDEX('State Rules'!$E$5:$E$11,MATCH($B57,'State Rules'!$A$5:$A$11,0))),"")) -> 45688 | R57: =IF(P57="","",IFERROR(IF(P57<=INDEX('State Rules'!$I$5:$I$11,MATCH($B57,'State Rules'!$A$5:$A$11,0)),"Yes","No"),"")) -> Yes | S57: =IF(Q57="","",IFERROR(IF(Q57<=INDEX('State Rules'!$I$5:$I$11,MATCH($B57,'State Rules'!$A$5:$A$11,0)),"Yes","No"),"")) -> Yes | Z57: =IF(Q57="","",IF(Q57<=$B$4,N(W57)+N(X57),0)) -> 0 | AA57: =IF(OR(LEFT(N57,6)="Larger",LEFT(N57,4)="Memo"),H57,0) -> 539.6
A58: Houston | B58: =IFERROR(INDEX(Summary!$B$10:$B$17,MATCH($A58,Summary!$A$10:$A$17,0)),"") -> TX | C58: Houston | D58: 22 | E58: 44649 | F58: 26398 | H58: 300 | J58: No | K58: =IF(E58="","",($B$4-E58)/365.25) -> 4.5229295 | L58: =IF(K58="","no date",IF(K58<1,"0-1 yrs",IF(K58<2,"1-2 yrs",IF(K58<3,"2-3 yrs",IF(K58<5,"3-5 yrs","5+ yrs"))))) -> 3-5 yrs | M58: No | N58: =IF(M58="Yes","Memo flag - not ours / unknown / hold: resolve",IF(OR(COUNTIF(Summary!$C$4:$L$4,H58)>0,AND(A58="Philly",COUNTIF(Summary!$C$5:$L$5,H58)>0),AND(A58="TUR",COUNTIF(Summary!$C$6:$L$6,H58)>0)),"Fee amount - presumed company revenue",IF(H58<=Summary!$B$7,"Small amount - likely fee, review","Larger amount - likely includes agent commission"))) -> Larger amount - likely includes agent commission | O58: =IFERROR(INDEX('State Rules'!$C$5:$C$11,MATCH($B58,'State Rules'!$A$5:$A$11,0)),"") -> 1 | P58: =IF(OR(O58="",E58=""),"",EDATE(E58,12*O58)) -> 45014 | Q58: =IF(E58="","",IFERROR(EDATE(E58,12*INDEX('State Rules'!$E$5:$E$11,MATCH($B58,'State Rules'!$A$5:$A$11,0))),"")) -> 45745 | R58: =IF(P58="","",IFERROR(IF(P58<=INDEX('State Rules'!$I$5:$I$11,MATCH($B58,'State Rules'!$A$5:$A$11,0)),"Yes","No"),"")) -> Yes | S58: =IF(Q58="","",IFERROR(IF(Q58<=INDEX('State Rules'!$I$5:$I$11,MATCH($B58,'State Rules'!$A$5:$A$11,0)),"Yes","No"),"")) -> Yes | Z58: =IF(Q58="","",IF(Q58<=$B$4,N(W58)+N(X58),0)) -> 0 | AA58: =IF(OR(LEFT(N58,6)="Larger",LEFT(N58,4)="Memo"),H58,0) -> 300
A59: Houston | B59: =IFERROR(INDEX(Summary!$B$10:$B$17,MATCH($A59,Summary!$A$10:$A$17,0)),"") -> TX | C59: Houston | D59: 23 | E59: 44762 | F59: 4357 | G59: Aaron Shorey | H59: 1260 | I59: 185 Country Rd 709 | J59: No | K59: =IF(E59="","",($B$4-E59)/365.25) -> 4.2135524 | L59: =IF(K59="","no date",IF(K59<1,"0-1 yrs",IF(K59<2,"1-2 yrs",IF(K59<3,"2-3 yrs",IF(K59<5,"3-5 yrs","5+ yrs"))))) -> 3-5 yrs | M59: No | N59: =IF(M59="Yes","Memo flag - not ours / unknown / hold: resolve",IF(OR(COUNTIF(Summary!$C$4:$L$4,H59)>0,AND(A59="Philly",COUNTIF(Summary!$C$5:$L$5,H59)>0),AND(A59="TUR",COUNTIF(Summary!$C$6:$L$6,H59)>0)),"Fee amount - presumed company revenue",IF(H59<=Summary!$B$7,"Small amount - likely fee, review","Larger amount - likely includes agent commission"))) -> Larger amount - likely includes agent commission | O59: =IFERROR(INDEX('State Rules'!$C$5:$C$11,MATCH($B59,'State Rules'!$A$5:$A$11,0)),"") -> 1 | P59: =IF(OR(O59="",E59=""),"",EDATE(E59,12*O59)) -> 45127 | Q59: =IF(E59="","",IFERROR(EDATE(E59,12*INDEX('State Rules'!$E$5:$E$11,MATCH($B59,'State Rules'!$A$5:$A$11,0))),"")) -> 45858 | R59: =IF(P59="","",IFERROR(IF(P59<=INDEX('State Rules'!$I$5:$I$11,MATCH($B59,'State Rules'!$A$5:$A$11,0)),"Yes","No"),"")) -> Yes | S59: =IF(Q59="","",IFERROR(IF(Q59<=INDEX('State Rules'!$I$5:$I$11,MATCH($B59,'State Rules'!$A$5:$A$11,0)),"Yes","No"),"")) -> Yes | Z59: =IF(Q59="","",IF(Q59<=$B$4,N(W59)+N(X59),0)) -> 0 | AA59: =IF(OR(LEFT(N59,6)="Larger",LEFT(N59,4)="Memo"),H59,0) -> 1260
A60: Houston | B60: =IFERROR(INDEX(Summary!$B$10:$B$17,MATCH($A60,Summary!$A$10:$A$17,0)),"") -> TX | C60: Houston | D60: 24 | E60: 44775 | F60: 14812016 | G60: Stewart Title Company | H60: 1000 | I60: File:22339037767 | J60: No | K60: =IF(E60="","",($B$4-E60)/365.25) -> 4.1779603 | L60: =IF(K60="","no date",IF(K60<1,"0-1 yrs",IF(K60<2,"1-2 yrs",IF(K60<3,"2-3 yrs",IF(K60<5,"3-5 yrs","5+ yrs"))))) -> 3-5 yrs | M60: No | N60: =IF(M60="Yes","Memo flag - not ours / unknown / hold: resolve",IF(OR(COUNTIF(Summary!$C$4:$L$4,H60)>0,AND(A60="Philly",COUNTIF(Summary!$C$5:$L$5,H60)>0),AND(A60="TUR",COUNTIF(Summary!$C$6:$L$6,H60)>0)),"Fee amount - presumed company revenue",IF(H60<=Summary!$B$7,"Small amount - likely fee, review","Larger amount - likely includes agent commission"))) -> Larger amount - likely includes agent commission | O60: =IFERROR(INDEX('State Rules'!$C$5:$C$11,MATCH($B60,'State Rules'!$A$5:$A$11,0)),"") -> 1 | P60: =IF(OR(O60="",E60=""),"",EDATE(E60,12*O60)) -> 45140 | Q60: =IF(E60="","",IFERROR(EDATE(E60,12*INDEX('State Rules'!$E$5:$E$11,MATCH($B60,'State Rules'!$A$5:$A$11,0))),"")) -> 45871 | R60: =IF(P60="","",IFERROR(IF(P60<=INDEX('State Rules'!$I$5:$I$11,MATCH($B60,'State Rules'!$A$5:$A$11,0)),"Yes","No"),"")) -> Yes | S60: =IF(Q60="","",IFERROR(IF(Q60<=INDEX('State Rules'!$I$5:$I$11,MATCH($B60,'State Rules'!$A$5:$A$11,0)),"Yes","No"),"")) -> Yes | Z60: =IF(Q60="","",IF(Q60<=$B$4,N(W60)+N(X60),0)) -> 0 | AA60: =IF(OR(LEFT(N60,6)="Larger",LEFT(N60,4)="Memo"),H60,0) -> 1000
A61: Houston | B61: =IFERROR(INDEX(Summary!$B$10:$B$17,MATCH($A61,Summary!$A$10:$A$17,0)),"") -> TX | C61: Houston | D61: 25 | E61: 45008 | F61: 2127 | G61: WY-TX CO LLC | H61: 340 | I61: 3525 Sage #1009 | J61: No | K61: =IF(E61="","",($B$4-E61)/365.25) -> 3.5400411 | L61: =IF(K61="","no date",IF(K61<1,"0-1 yrs",IF(K61<2,"1-2 yrs",IF(K61<3,"2-3 yrs",IF(K61<5,"3-5 yrs","5+ yrs"))))) -> 3-5 yrs | M61: No | N61: =IF(M61="Yes","Memo flag - not ours / unknown / hold: resolve",IF(OR(COUNTIF(Summary!$C$4:$L$4,H61)>0,AND(A61="Philly",COUNTIF(Summary!$C$5:$L$5,H61)>0),AND(A61="TUR",COUNTIF(Summary!$C$6:$L$6,H61)>0)),"Fee amount - presumed company revenue",IF(H61<=Summary!$B$7,"Small amount - likely fee, review","Larger amount - likely includes agent commission"))) -> Larger amount - likely includes agent commission | O61: =IFERROR(INDEX('State Rules'!$C$5:$C$11,MATCH($B61,'State Rules'!$A$5:$A$11,0)),"") -> 1 | P61: =IF(OR(O61="",E61=""),"",EDATE(E61,12*O61)) -> 45374 | Q61: =IF(E61="","",IFERROR(EDATE(E61,12*INDEX('State Rules'!$E$5:$E$11,MATCH($B61,'State Rules'!$A$5:$A$11,0))),"")) -> 46104 | R61: =IF(P61="","",IFERROR(IF(P61<=INDEX('State Rules'!$I$5:$I$11,MATCH($B61,'State Rules'!$A$5:$A$11,0)),"Yes","No"),"")) -> Yes | S61: =IF(Q61="","",IFERROR(IF(Q61<=INDEX('State Rules'!$I$5:$I$11,MATCH($B61,'State Rules'!$A$5:$A$11,0)),"Yes","No"),"")) -> Yes | Z61: =IF(Q61="","",IF(Q61<=$B$4,N(W61)+N(X61),0)) -> 0 | AA61: =IF(OR(LEFT(N61,6)="Larger",LEFT(N61,4)="Memo"),H61,0) -> 340
A62: Houston | B62: =IFERROR(INDEX(Summary!$B$10:$B$17,MATCH($A62,Summary!$A$10:$A$17,0)),"") -> TX | C62: Houston | D62: 26 | E62: 45008 | F62: 2128 | G62: WY-TX CO LLC | H62: 340 | I62: 3525 Sage #1009 | J62: No | K62: =IF(E62="","",($B$4-E62)/365.25) -> 3.5400411 | L62: =IF(K62="","no date",IF(K62<1,"0-1 yrs",IF(K62<2,"1-2 yrs",IF(K62<3,"2-3 yrs",IF(K62<5,"3-5 yrs","5+ yrs"))))) -> 3-5 yrs | M62: No | N62: =IF(M62="Yes","Memo flag - not ours / unknown / hold: resolve",IF(OR(COUNTIF(Summary!$C$4:$L$4,H62)>0,AND(A62="Philly",COUNTIF(Summary!$C$5:$L$5,H62)>0),AND(A62="TUR",COUNTIF(Summary!$C$6:$L$6,H62)>0)),"Fee amount - presumed company revenue",IF(H62<=Summary!$B$7,"Small amount - likely fee, review","Larger amount - likely includes agent commission"))) -> Larger amount - likely includes agent commission | O62: =IFERROR(INDEX('State Rules'!$C$5:$C$11,MATCH($B62,'State Rules'!$A$5:$A$11,0)),"") -> 1 | P62: =IF(OR(O62="",E62=""),"",EDATE(E62,12*O62)) -> 45374 | Q62: =IF(E62="","",IFERROR(EDATE(E62,12*INDEX('State Rules'!$E$5:$E$11,MATCH($B62,'State Rules'!$A$5:$A$11,0))),"")) -> 46104 | R62: =IF(P62="","",IFERROR(IF(P62<=INDEX('State Rules'!$I$5:$I$11,MATCH($B62,'State Rules'!$A$5:$A$11,0)),"Yes","No"),"")) -> Yes | S62: =IF(Q62="","",IFERROR(IF(Q62<=INDEX('State Rules'!$I$5:$I$11,MATCH($B62,'State Rules'!$A$5:$A$11,0)),"Yes","No"),"")) -> Yes | Z62: =IF(Q62="","",IF(Q62<=$B$4,N(W62)+N(X62),0)) -> 0 | AA62: =IF(OR(LEFT(N62,6)="Larger",LEFT(N62,4)="Memo"),H62,0) -> 340
A63: Houston | B63: =IFERROR(INDEX(Summary!$B$10:$B$17,MATCH($A63,Summary!$A$10:$A$17,0)),"") -> TX | C63: Houston | D63: 27 | E63: 45125 | F63: 103164 | G63: Exp Realty | H63: 1500 | I63: 6223 Millbridge-on hold due to agent commiting fraud- n not disburse per law enforcement and TREC | J63: No | K63: =IF(E63="","",($B$4-E63)/365.25) -> 3.2197125 | L63: =IF(K63="","no date",IF(K63<1,"0-1 yrs",IF(K63<2,"1-2 yrs",IF(K63<3,"2-3 yrs",IF(K63<5,"3-5 yrs","5+ yrs"))))) -> 3-5 yrs | M63: Yes | N63: =IF(M63="Yes","Memo flag - not ours / unknown / hold: resolve",IF(OR(COUNTIF(Summary!$C$4:$L$4,H63)>0,AND(A63="Philly",COUNTIF(Summary!$C$5:$L$5,H63)>0),AND(A63="TUR",COUNTIF(Summary!$C$6:$L$6,H63)>0)),"Fee amount - presumed company revenue",IF(H63<=Summary!$B$7,"Small amount - likely fee, review","Larger amount - likely includes agent commission"))) -> Memo flag - not ours / unknown / hold: resolve | O63: =IFERROR(INDEX('State Rules'!$C$5:$C$11,MATCH($B63,'State Rules'!$A$5:$A$11,0)),"") -> 1 | P63: =IF(OR(O63="",E63=""),"",EDATE(E63,12*O63)) -> 45491 | Q63: =IF(E63="","",IFERROR(EDATE(E63,12*INDEX('State Rules'!$E$5:$E$11,MATCH($B63,'State Rules'!$A$5:$A$11,0))),"")) -> 46221 | R63: =IF(P63="","",IFERROR(IF(P63<=INDEX('State Rules'!$I$5:$I$11,MATCH($B63,'State Rules'!$A$5:$A$11,0)),"Yes","No"),"")) -> Yes | S63: =IF(Q63="","",IFERROR(IF(Q63<=INDEX('State Rules'!$I$5:$I$11,MATCH($B63,'State Rules'!$A$5:$A$11,0)),"Yes","No"),"")) -> Yes | Z63: =IF(Q63="","",IF(Q63<=$B$4,N(W63)+N(X63),0)) -> 0 | AA63: =IF(OR(LEFT(N63,6)="Larger",LEFT(N63,4)="Memo"),H63,0) -> 1500
A64: Houston | B64: =IFERROR(INDEX(Summary!$B$10:$B$17,MATCH($A64,Summary!$A$10:$A$17,0)),"") -> TX | C64: Houston | D64: 28 | E64: 45125 | F64: 593013245 | G64: Fidelity National Title | H64: 357 | J64: No | K64: =IF(E64="","",($B$4-E64)/365.25) -> 3.2197125 | L64: =IF(K64="","no date",IF(K64<1,"0-1 yrs",IF(K64<2,"1-2 yrs",IF(K64<3,"2-3 yrs",IF(K64<5,"3-5 yrs","5+ yrs"))))) -> 3-5 yrs | M64: No | N64: =IF(M64="Yes","Memo flag - not ours / unknown / hold: resolve",IF(OR(COUNTIF(Summary!$C$4:$L$4,H64)>0,AND(A64="Philly",COUNTIF(Summary!$C$5:$L$5,H64)>0),AND(A64="TUR",COUNTIF(Summary!$C$6:$L$6,H64)>0)),"Fee amount - presumed company revenue",IF(H64<=Summary!$B$7,"Small amount - likely fee, review","Larger amount - likely includes agent commission"))) -> Larger amount - likely includes agent commission | O64: =IFERROR(INDEX('State Rules'!$C$5:$C$11,MATCH($B64,'State Rules'!$A$5:$A$11,0)),"") -> 1 | P64: =IF(OR(O64="",E64=""),"",EDATE(E64,12*O64)) -> 45491 | Q64: =IF(E64="","",IFERROR(EDATE(E64,12*INDEX('State Rules'!$E$5:$E$11,MATCH($B64,'State Rules'!$A$5:$A$11,0))),"")) -> 46221 | R64: =IF(P64="","",IFERROR(IF(P64<=INDEX('State Rules'!$I$5:$I$11,MATCH($B64,'State Rules'!$A$5:$A$11,0)),"Yes","No"),"")) -> Yes | S64: =IF(Q64="","",IFERROR(IF(Q64<=INDEX('State Rules'!$I$5:$I$11,MATCH($B64,'State Rules'!$A$5:$A$11,0)),"Yes","No"),"")) -> Yes | Z64: =IF(Q64="","",IF(Q64<=$B$4,N(W64)+N(X64),0)) -> 0 | AA64: =IF(OR(LEFT(N64,6)="Larger",LEFT(N64,4)="Memo"),H64,0) -> 357
A65: Houston | B65: =IFERROR(INDEX(Summary!$B$10:$B$17,MATCH($A65,Summary!$A$10:$A$17,0)),"") -> TX | C65: Houston | D65: 29 | E65: 45232 | F65: 330721 | H65: 375 | I65: cant locate | J65: No | K65: =IF(E65="","",($B$4-E65)/365.25) -> 2.9267625 | L65: =IF(K65="","no date",IF(K65<1,"0-1 yrs",IF(K65<2,"1-2 yrs",IF(K65<3,"2-3 yrs",IF(K65<5,"3-5 yrs","5+ yrs"))))) -> 2-3 yrs | M65: Yes | N65: =IF(M65="Yes","Memo flag - not ours / unknown / hold: resolve",IF(OR(COUNTIF(Summary!$C$4:$L$4,H65)>0,AND(A65="Philly",COUNTIF(Summary!$C$5:$L$5,H65)>0),AND(A65="TUR",COUNTIF(Summary!$C$6:$L$6,H65)>0)),"Fee amount - presumed company revenue",IF(H65<=Summary!$B$7,"Small amount - likely fee, review","Larger amount - likely includes agent commission"))) -> Memo flag - not ours / unknown / hold: resolve | O65: =IFERROR(INDEX('State Rules'!$C$5:$C$11,MATCH($B65,'State Rules'!$A$5:$A$11,0)),"") -> 1 | P65: =IF(OR(O65="",E65=""),"",EDATE(E65,12*O65)) -> 45598 | Q65: =IF(E65="","",IFERROR(EDATE(E65,12*INDEX('State Rules'!$E$5:$E$11,MATCH($B65,'State Rules'!$A$5:$A$11,0))),"")) -> 46328 | R65: =IF(P65="","",IFERROR(IF(P65<=INDEX('State Rules'!$I$5:$I$11,MATCH($B65,'State Rules'!$A$5:$A$11,0)),"Yes","No"),"")) -> Yes | S65: =IF(Q65="","",IFERROR(IF(Q65<=INDEX('State Rules'!$I$5:$I$11,MATCH($B65,'State Rules'!$A$5:$A$11,0)),"Yes","No"),"")) -> Yes | Z65: =IF(Q65="","",IF(Q65<=$B$4,N(W65)+N(X65),0)) -> 0 | AA65: =IF(OR(LEFT(N65,6)="Larger",LEFT(N65,4)="Memo"),H65,0) -> 375
A66: Houston | B66: =IFERROR(INDEX(Summary!$B$10:$B$17,MATCH($A66,Summary!$A$10:$A$17,0)),"") -> TX | C66: Houston | D66: 30 | E66: 45412 | F66: 3007 | G66: Secured Title of Texas | H66: 517.5 | I66: SWSTG4645 | J66: No | K66: =IF(E66="","",($B$4-E66)/365.25) -> 2.4339493 | L66: =IF(K66="","no date",IF(K66<1,"0-1 yrs",IF(K66<2,"1-2 yrs",IF(K66<3,"2-3 yrs",IF(K66<5,"3-5 yrs","5+ yrs"))))) -> 2-3 yrs | M66: No | N66: =IF(M66="Yes","Memo flag - not ours / unknown / hold: resolve",IF(OR(COUNTIF(Summary!$C$4:$L$4,H66)>0,AND(A66="Philly",COUNTIF(Summary!$C$5:$L$5,H66)>0),AND(A66="TUR",COUNTIF(Summary!$C$6:$L$6,H66)>0)),"Fee amount - presumed company revenue",IF(H66<=Summary!$B$7,"Small amount - likely fee, review","Larger amount - likely includes agent commission"))) -> Larger amount - likely includes agent commission | O66: =IFERROR(INDEX('State Rules'!$C$5:$C$11,MATCH($B66,'State Rules'!$A$5:$A$11,0)),"") -> 1 | P66: =IF(OR(O66="",E66=""),"",EDATE(E66,12*O66)) -> 45777 | Q66: =IF(E66="","",IFERROR(EDATE(E66,12*INDEX('State Rules'!$E$5:$E$11,MATCH($B66,'State Rules'!$A$5:$A$11,0))),"")) -> 46507 | R66: =IF(P66="","",IFERROR(IF(P66<=INDEX('State Rules'!$I$5:$I$11,MATCH($B66,'State Rules'!$A$5:$A$11,0)),"Yes","No"),"")) -> Yes | S66: =IF(Q66="","",IFERROR(IF(Q66<=INDEX('State Rules'!$I$5:$I$11,MATCH($B66,'State Rules'!$A$5:$A$11,0)),"Yes","No"),"")) -> No | Z66: =IF(Q66="","",IF(Q66<=$B$4,N(W66)+N(X66),0)) -> 0 | AA66: =IF(OR(LEFT(N66,6)="Larger",LEFT(N66,4)="Memo"),H66,0) -> 517.5
A67: Houston | B67: =IFERROR(INDEX(Summary!$B$10:$B$17,MATCH($A67,Summary!$A$10:$A$17,0)),"") -> TX | C67: Houston | D67: 31 | E67: 45432 | F67: 323248 | G67: Southland Title | H67: 49 | J67: No | K67: =IF(E67="","",($B$4-E67)/365.25) -> 2.3791923 | L67: =IF(K67="","no date",IF(K67<1,"0-1 yrs",IF(K67<2,"1-2 yrs",IF(K67<3,"2-3 yrs",IF(K67<5,"3-5 yrs","5+ yrs"))))) -> 2-3 yrs | M67: No | N67: =IF(M67="Yes","Memo flag - not ours / unknown / hold: resolve",IF(OR(COUNTIF(Summary!$C$4:$L$4,H67)>0,AND(A67="Philly",COUNTIF(Summary!$C$5:$L$5,H67)>0),AND(A67="TUR",COUNTIF(Summary!$C$6:$L$6,H67)>0)),"Fee amount - presumed company revenue",IF(H67<=Summary!$B$7,"Small amount - likely fee, review","Larger amount - likely includes agent commission"))) -> Fee amount - presumed company revenue | O67: =IFERROR(INDEX('State Rules'!$C$5:$C$11,MATCH($B67,'State Rules'!$A$5:$A$11,0)),"") -> 1 | P67: =IF(OR(O67="",E67=""),"",EDATE(E67,12*O67)) -> 45797 | Q67: =IF(E67="","",IFERROR(EDATE(E67,12*INDEX('State Rules'!$E$5:$E$11,MATCH($B67,'State Rules'!$A$5:$A$11,0))),"")) -> 46527 | R67: =IF(P67="","",IFERROR(IF(P67<=INDEX('State Rules'!$I$5:$I$11,MATCH($B67,'State Rules'!$A$5:$A$11,0)),"Yes","No"),"")) -> Yes | S67: =IF(Q67="","",IFERROR(IF(Q67<=INDEX('State Rules'!$I$5:$I$11,MATCH($B67,'State Rules'!$A$5:$A$11,0)),"Yes","No"),"")) -> No | Z67: =IF(Q67="","",IF(Q67<=$B$4,N(W67)+N(X67),0)) -> 0 | AA67: =IF(OR(LEFT(N67,6)="Larger",LEFT(N67,4)="Memo"),H67,0) -> 0
A68: Houston | B68: =IFERROR(INDEX(Summary!$B$10:$B$17,MATCH($A68,Summary!$A$10:$A$17,0)),"") -> TX | C68: Houston | D68: 32 | E68: 45456 | F68: 323050 | G68: Southland Title | H68: 100 | J68: No | K68: =IF(E68="","",($B$4-E68)/365.25) -> 2.3134839 | L68: =IF(K68="","no date",IF(K68<1,"0-1 yrs",IF(K68<2,"1-2 yrs",IF(K68<3,"2-3 yrs",IF(K68<5,"3-5 yrs","5+ yrs"))))) -> 2-3 yrs | M68: No | N68: =IF(M68="Yes","Memo flag - not ours / unknown / hold: resolve",IF(OR(COUNTIF(Summary!$C$4:$L$4,H68)>0,AND(A68="Philly",COUNTIF(Summary!$C$5:$L$5,H68)>0),AND(A68="TUR",COUNTIF(Summary!$C$6:$L$6,H68)>0)),"Fee amount - presumed company revenue",IF(H68<=Summary!$B$7,"Small amount - likely fee, review","Larger amount - likely includes agent commission"))) -> Small amount - likely fee, review | O68: =IFERROR(INDEX('State Rules'!$C$5:$C$11,MATCH($B68,'State Rules'!$A$5:$A$11,0)),"") -> 1 | P68: =IF(OR(O68="",E68=""),"",EDATE(E68,12*O68)) -> 45821 | Q68: =IF(E68="","",IFERROR(EDATE(E68,12*INDEX('State Rules'!$E$5:$E$11,MATCH($B68,'State Rules'!$A$5:$A$11,0))),"")) -> 46551 | R68: =IF(P68="","",IFERROR(IF(P68<=INDEX('State Rules'!$I$5:$I$11,MATCH($B68,'State Rules'!$A$5:$A$11,0)),"Yes","No"),"")) -> Yes | S68: =IF(Q68="","",IFERROR(IF(Q68<=INDEX('State Rules'!$I$5:$I$11,MATCH($B68,'State Rules'!$A$5:$A$11,0)),"Yes","No"),"")) -> No | Z68: =IF(Q68="","",IF(Q68<=$B$4,N(W68)+N(X68),0)) -> 0 | AA68: =IF(OR(LEFT(N68,6)="Larger",LEFT(N68,4)="Memo"),H68,0) -> 0
A69: Houston | B69: =IFERROR(INDEX(Summary!$B$10:$B$17,MATCH($A69,Summary!$A$10:$A$17,0)),"") -> TX | C69: Houston | D69: 33 | E69: 45456 | F69: 323054 | G69: Southland Title | H69: 644 | J69: No | K69: =IF(E69="","",($B$4-E69)/365.25) -> 2.3134839 | L69: =IF(K69="","no date",IF(K69<1,"0-1 yrs",IF(K69<2,"1-2 yrs",IF(K69<3,"2-3 yrs",IF(K69<5,"3-5 yrs","5+ yrs"))))) -> 2-3 yrs | M69: No | N69: =IF(M69="Yes","Memo flag - not ours / unknown / hold: resolve",IF(OR(COUNTIF(Summary!$C$4:$L$4,H69)>0,AND(A69="Philly",COUNTIF(Summary!$C$5:$L$5,H69)>0),AND(A69="TUR",COUNTIF(Summary!$C$6:$L$6,H69)>0)),"Fee amount - presumed company revenue",IF(H69<=Summary!$B$7,"Small amount - likely fee, review","Larger amount - likely includes agent commission"))) -> Fee amount - presumed company revenue | O69: =IFERROR(INDEX('State Rules'!$C$5:$C$11,MATCH($B69,'State Rules'!$A$5:$A$11,0)),"") -> 1 | P69: =IF(OR(O69="",E69=""),"",EDATE(E69,12*O69)) -> 45821 | Q69: =IF(E69="","",IFERROR(EDATE(E69,12*INDEX('State Rules'!$E$5:$E$11,MATCH($B69,'State Rules'!$A$5:$A$11,0))),"")) -> 46551 | R69: =IF(P69="","",IFERROR(IF(P69<=INDEX('State Rules'!$I$5:$I$11,MATCH($B69,'State Rules'!$A$5:$A$11,0)),"Yes","No"),"")) -> Yes | S69: =IF(Q69="","",IFERROR(IF(Q69<=INDEX('State Rules'!$I$5:$I$11,MATCH($B69,'State Rules'!$A$5:$A$11,0)),"Yes","No"),"")) -> No | Z69: =IF(Q69="","",IF(Q69<=$B$4,N(W69)+N(X69),0)) -> 0 | AA69: =IF(OR(LEFT(N69,6)="Larger",LEFT(N69,4)="Memo"),H69,0) -> 0
A70: Houston | B70: =IFERROR(INDEX(Summary!$B$10:$B$17,MATCH($A70,Summary!$A$10:$A$17,0)),"") -> TX | C70: Houston | D70: 34 | E70: 45474 | F70: 42740 | G70: Capital Title of Texas | H70: 7500 | J70: No | K70: =IF(E70="","",($B$4-E70)/365.25) -> 2.2642026 | L70: =IF(K70="","no date",IF(K70<1,"0-1 yrs",IF(K70<2,"1-2 yrs",IF(K70<3,"2-3 yrs",IF(K70<5,"3-5 yrs","5+ yrs"))))) -> 2-3 yrs | M70: No | N70: =IF(M70="Yes","Memo flag - not ours / unknown / hold: resolve",IF(OR(COUNTIF(Summary!$C$4:$L$4,H70)>0,AND(A70="Philly",COUNTIF(Summary!$C$5:$L$5,H70)>0),AND(A70="TUR",COUNTIF(Summary!$C$6:$L$6,H70)>0)),"Fee amount - presumed company revenue",IF(H70<=Summary!$B$7,"Small amount - likely fee, review","Larger amount - likely includes agent commission"))) -> Larger amount - likely includes agent commission | O70: =IFERROR(INDEX('State Rules'!$C$5:$C$11,MATCH($B70,'State Rules'!$A$5:$A$11,0)),"") -> 1 | P70: =IF(OR(O70="",E70=""),"",EDATE(E70,12*O70)) -> 45839 | Q70: =IF(E70="","",IFERROR(EDATE(E70,12*INDEX('State Rules'!$E$5:$E$11,MATCH($B70,'State Rules'!$A$5:$A$11,0))),"")) -> 46569 | R70: =IF(P70="","",IFERROR(IF(P70<=INDEX('State Rules'!$I$5:$I$11,MATCH($B70,'State Rules'!$A$5:$A$11,0)),"Yes","No"),"")) -> Yes | S70: =IF(Q70="","",IFERROR(IF(Q70<=INDEX('State Rules'!$I$5:$I$11,MATCH($B70,'State Rules'!$A$5:$A$11,0)),"Yes","No"),"")) -> No | Z70: =IF(Q70="","",IF(Q70<=$B$4,N(W70)+N(X70),0)) -> 0 | AA70: =IF(OR(LEFT(N70,6)="Larger",LEFT(N70,4)="Memo"),H70,0) -> 7500
A71: Houston | B71: =IFERROR(INDEX(Summary!$B$10:$B$17,MATCH($A71,Summary!$A$10:$A$17,0)),"") -> TX | C71: Houston | D71: 35 | E71: 45574 | F71: 591110199 | G71: Fidelity National Title Agency | H71: 495 | I71: Commissions | J71: No | K71: =IF(E71="","",($B$4-E71)/365.25) -> 1.9904175 | L71: =IF(K71="","no date",IF(K71<1,"0-1 yrs",IF(K71<2,"1-2 yrs",IF(K71<3,"2-3 yrs",IF(K71<5,"3-5 yrs","5+ yrs"))))) -> 1-2 yrs | M71: No | N71: =IF(M71="Yes","Memo flag - not ours / unknown / hold: resolve",IF(OR(COUNTIF(Summary!$C$4:$L$4,H71)>0,AND(A71="Philly",COUNTIF(Summary!$C$5:$L$5,H71)>0),AND(A71="TUR",COUNTIF(Summary!$C$6:$L$6,H71)>0)),"Fee amount - presumed company revenue",IF(H71<=Summary!$B$7,"Small amount - likely fee, review","Larger amount - likely includes agent commission"))) -> Larger amount - likely includes agent commission | O71: =IFERROR(INDEX('State Rules'!$C$5:$C$11,MATCH($B71,'State Rules'!$A$5:$A$11,0)),"") -> 1 | P71: =IF(OR(O71="",E71=""),"",EDATE(E71,12*O71)) -> 45939 | Q71: =IF(E71="","",IFERROR(EDATE(E71,12*INDEX('State Rules'!$E$5:$E$11,MATCH($B71,'State Rules'!$A$5:$A$11,0))),"")) -> 46669 | R71: =IF(P71="","",IFERROR(IF(P71<=INDEX('State Rules'!$I$5:$I$11,MATCH($B71,'State Rules'!$A$5:$A$11,0)),"Yes","No"),"")) -> Yes | S71: =IF(Q71="","",IFERROR(IF(Q71<=INDEX('State Rules'!$I$5:$I$11,MATCH($B71,'State Rules'!$A$5:$A$11,0)),"Yes","No"),"")) -> No | Z71: =IF(Q71="","",IF(Q71<=$B$4,N(W71)+N(X71),0)) -> 0 | AA71: =IF(OR(LEFT(N71,6)="Larger",LEFT(N71,4)="Memo"),H71,0) -> 495
A72: Houston | B72: =IFERROR(INDEX(Summary!$B$10:$B$17,MATCH($A72,Summary!$A$10:$A$17,0)),"") -> TX | C72: Houston | D72: 36 | E72: 45649 | F72: 7213229449 | H72: 999.99 | I72: Dallas Transaction 4110 Fairmount 2171 | J72: No | K72: =IF(E72="","",($B$4-E72)/365.25) -> 1.7850787 | L72: =IF(K72="","no date",IF(K72<1,"0-1 yrs",IF(K72<2,"1-2 yrs",IF(K72<3,"2-3 yrs",IF(K72<5,"3-5 yrs","5+ yrs"))))) -> 1-2 yrs | M72: No | N72: =IF(M72="Yes","Memo flag - not ours / unknown / hold: resolve",IF(OR(COUNTIF(Summary!$C$4:$L$4,H72)>0,AND(A72="Philly",COUNTIF(Summary!$C$5:$L$5,H72)>0),AND(A72="TUR",COUNTIF(Summary!$C$6:$L$6,H72)>0)),"Fee amount - presumed company revenue",IF(H72<=Summary!$B$7,"Small amount - likely fee, review","Larger amount - likely includes agent commission"))) -> Larger amount - likely includes agent commission | O72: =IFERROR(INDEX('State Rules'!$C$5:$C$11,MATCH($B72,'State Rules'!$A$5:$A$11,0)),"") -> 1 | P72: =IF(OR(O72="",E72=""),"",EDATE(E72,12*O72)) -> 46014 | Q72: =IF(E72="","",IFERROR(EDATE(E72,12*INDEX('State Rules'!$E$5:$E$11,MATCH($B72,'State Rules'!$A$5:$A$11,0))),"")) -> 46744 | R72: =IF(P72="","",IFERROR(IF(P72<=INDEX('State Rules'!$I$5:$I$11,MATCH($B72,'State Rules'!$A$5:$A$11,0)),"Yes","No"),"")) -> Yes | S72: =IF(Q72="","",IFERROR(IF(Q72<=INDEX('State Rules'!$I$5:$I$11,MATCH($B72,'State Rules'!$A$5:$A$11,0)),"Yes","No"),"")) -> No | Z72: =IF(Q72="","",IF(Q72<=$B$4,N(W72)+N(X72),0)) -> 0 | AA72: =IF(OR(LEFT(N72,6)="Larger",LEFT(N72,4)="Memo"),H72,0) -> 999.99
A73: Houston | B73: =IFERROR(INDEX(Summary!$B$10:$B$17,MATCH($A73,Summary!$A$10:$A$17,0)),"") -> TX | C73: Houston | D73: 37 | E73: 45688 | F73: 275615 | G73: Move Sales, Inc | H73: 305.91 | J73: No | K73: =IF(E73="","",($B$4-E73)/365.25) -> 1.6783025 | L73: =IF(K73="","no date",IF(K73<1,"0-1 yrs",IF(K73<2,"1-2 yrs",IF(K73<3,"2-3 yrs",IF(K73<5,"3-5 yrs","5+ yrs"))))) -> 1-2 yrs | M73: No | N73: =IF(M73="Yes","Memo flag - not ours / unknown / hold: resolve",IF(OR(COUNTIF(Summary!$C$4:$L$4,H73)>0,AND(A73="Philly",COUNTIF(Summary!$C$5:$L$5,H73)>0),AND(A73="TUR",COUNTIF(Summary!$C$6:$L$6,H73)>0)),"Fee amount - presumed company revenue",IF(H73<=Summary!$B$7,"Small amount - likely fee, review","Larger amount - likely includes agent commission"))) -> Larger amount - likely includes agent commission | O73: =IFERROR(INDEX('State Rules'!$C$5:$C$11,MATCH($B73,'State Rules'!$A$5:$A$11,0)),"") -> 1 | P73: =IF(OR(O73="",E73=""),"",EDATE(E73,12*O73)) -> 46053 | Q73: =IF(E73="","",IFERROR(EDATE(E73,12*INDEX('State Rules'!$E$5:$E$11,MATCH($B73,'State Rules'!$A$5:$A$11,0))),"")) -> 46783 | R73: =IF(P73="","",IFERROR(IF(P73<=INDEX('State Rules'!$I$5:$I$11,MATCH($B73,'State Rules'!$A$5:$A$11,0)),"Yes","No"),"")) -> Yes | S73: =IF(Q73="","",IFERROR(IF(Q73<=INDEX('State Rules'!$I$5:$I$11,MATCH($B73,'State Rules'!$A$5:$A$11,0)),"Yes","No"),"")) -> No | Z73: =IF(Q73="","",IF(Q73<=$B$4,N(W73)+N(X73),0)) -> 0 | AA73: =IF(OR(LEFT(N73,6)="Larger",LEFT(N73,4)="Memo"),H73,0) -> 305.91
A74: Houston | B74: =IFERROR(INDEX(Summary!$B$10:$B$17,MATCH($A74,Summary!$A$10:$A$17,0)),"") -> TX | C74: Houston | D74: 38 | E74: 45825 | F74: 3045688 | H74: 1044 | I74: Old Republic Title | J74: No | K74: =IF(E74="","",($B$4-E74)/365.25) -> 1.303217 | L74: =IF(K74="","no date",IF(K74<1,"0-1 yrs",IF(K74<2,"1-2 yrs",IF(K74<3,"2-3 yrs",IF(K74<5,"3-5 yrs","5+ yrs"))))) -> 1-2 yrs | M74: No | N74: =IF(M74="Yes","Memo flag - not ours / unknown / hold: resolve",IF(OR(COUNTIF(Summary!$C$4:$L$4,H74)>0,AND(A74="Philly",COUNTIF(Summary!$C$5:$L$5,H74)>0),AND(A74="TUR",COUNTIF(Summary!$C$6:$L$6,H74)>0)),"Fee amount - presumed company revenue",IF(H74<=Summary!$B$7,"Small amount - likely fee, review","Larger amount - likely includes agent commission"))) -> Fee amount - presumed company revenue | O74: =IFERROR(INDEX('State Rules'!$C$5:$C$11,MATCH($B74,'State Rules'!$A$5:$A$11,0)),"") -> 1 | P74: =IF(OR(O74="",E74=""),"",EDATE(E74,12*O74)) -> 46190 | Q74: =IF(E74="","",IFERROR(EDATE(E74,12*INDEX('State Rules'!$E$5:$E$11,MATCH($B74,'State Rules'!$A$5:$A$11,0))),"")) -> 46921 | R74: =IF(P74="","",IFERROR(IF(P74<=INDEX('State Rules'!$I$5:$I$11,MATCH($B74,'State Rules'!$A$5:$A$11,0)),"Yes","No"),"")) -> Yes | S74: =IF(Q74="","",IFERROR(IF(Q74<=INDEX('State Rules'!$I$5:$I$11,MATCH($B74,'State Rules'!$A$5:$A$11,0)),"Yes","No"),"")) -> No | Z74: =IF(Q74="","",IF(Q74<=$B$4,N(W74)+N(X74),0)) -> 0 | AA74: =IF(OR(LEFT(N74,6)="Larger",LEFT(N74,4)="Memo"),H74,0) -> 0
A75: Houston | B75: =IFERROR(INDEX(Summary!$B$10:$B$17,MATCH($A75,Summary!$A$10:$A$17,0)),"") -> TX | C75: Houston | D75: 39 | E75: 45840 | F75: 14111 | G75: HomeRiver Group - Houston | H75: 250 | J75: No | K75: =IF(E75="","",($B$4-E75)/365.25) -> 1.2621492 | L75: =IF(K75="","no date",IF(K75<1,"0-1 yrs",IF(K75<2,"1-2 yrs",IF(K75<3,"2-3 yrs",IF(K75<5,"3-5 yrs","5+ yrs"))))) -> 1-2 yrs | M75: No | N75: =IF(M75="Yes","Memo flag - not ours / unknown / hold: resolve",IF(OR(COUNTIF(Summary!$C$4:$L$4,H75)>0,AND(A75="Philly",COUNTIF(Summary!$C$5:$L$5,H75)>0),AND(A75="TUR",COUNTIF(Summary!$C$6:$L$6,H75)>0)),"Fee amount - presumed company revenue",IF(H75<=Summary!$B$7,"Small amount - likely fee, review","Larger amount - likely includes agent commission"))) -> Small amount - likely fee, review | O75: =IFERROR(INDEX('State Rules'!$C$5:$C$11,MATCH($B75,'State Rules'!$A$5:$A$11,0)),"") -> 1 | P75: =IF(OR(O75="",E75=""),"",EDATE(E75,12*O75)) -> 46205 | Q75: =IF(E75="","",IFERROR(EDATE(E75,12*INDEX('State Rules'!$E$5:$E$11,MATCH($B75,'State Rules'!$A$5:$A$11,0))),"")) -> 46936 | R75: =IF(P75="","",IFERROR(IF(P75<=INDEX('State Rules'!$I$5:$I$11,MATCH($B75,'State Rules'!$A$5:$A$11,0)),"Yes","No"),"")) -> Yes | S75: =IF(Q75="","",IFERROR(IF(Q75<=INDEX('State Rules'!$I$5:$I$11,MATCH($B75,'State Rules'!$A$5:$A$11,0)),"Yes","No"),"")) -> No | Z75: =IF(Q75="","",IF(Q75<=$B$4,N(W75)+N(X75),0)) -> 0 | AA75: =IF(OR(LEFT(N75,6)="Larger",LEFT(N75,4)="Memo"),H75,0) -> 0
A76: Houston | B76: =IFERROR(INDEX(Summary!$B$10:$B$17,MATCH($A76,Summary!$A$10:$A$17,0)),"") -> TX | C76: Houston | D76: 40 | E76: 45853 | F76: 31310 | G76: Keller Williams Realty Professionals | H76: 475 | I76: 5803 Southmund St #B | J76: No | K76: =IF(E76="","",($B$4-E76)/365.25) -> 1.2265572 | L76: =IF(K76="","no date",IF(K76<1,"0-1 yrs",IF(K76<2,"1-2 yrs",IF(K76<3,"2-3 yrs",IF(K76<5,"3-5 yrs","5+ yrs"))))) -> 1-2 yrs | M76: No | N76: =IF(M76="Yes","Memo flag - not ours / unknown / hold: resolve",IF(OR(COUNTIF(Summary!$C$4:$L$4,H76)>0,AND(A76="Philly",COUNTIF(Summary!$C$5:$L$5,H76)>0),AND(A76="TUR",COUNTIF(Summary!$C$6:$L$6,H76)>0)),"Fee amount - presumed company revenue",IF(H76<=Summary!$B$7,"Small amount - likely fee, review","Larger amount - likely includes agent commission"))) -> Larger amount - likely includes agent commission | O76: =IFERROR(INDEX('State Rules'!$C$5:$C$11,MATCH($B76,'State Rules'!$A$5:$A$11,0)),"") -> 1 | P76: =IF(OR(O76="",E76=""),"",EDATE(E76,12*O76)) -> 46218 | Q76: =IF(E76="","",IFERROR(EDATE(E76,12*INDEX('State Rules'!$E$5:$E$11,MATCH($B76,'State Rules'!$A$5:$A$11,0))),"")) -> 46949 | R76: =IF(P76="","",IFERROR(IF(P76<=INDEX('State Rules'!$I$5:$I$11,MATCH($B76,'State Rules'!$A$5:$A$11,0)),"Yes","No"),"")) -> Yes | S76: =IF(Q76="","",IFERROR(IF(Q76<=INDEX('State Rules'!$I$5:$I$11,MATCH($B76,'State Rules'!$A$5:$A$11,0)),"Yes","No"),"")) -> No | Z76: =IF(Q76="","",IF(Q76<=$B$4,N(W76)+N(X76),0)) -> 0 | AA76: =IF(OR(LEFT(N76,6)="Larger",LEFT(N76,4)="Memo"),H76,0) -> 475
A77: Houston | B77: =IFERROR(INDEX(Summary!$B$10:$B$17,MATCH($A77,Summary!$A$10:$A$17,0)),"") -> TX | C77: Houston | D77: 41 | E77: 45854 | F77: 1179006686 | H77: 263 | J77: No | K77: =IF(E77="","",($B$4-E77)/365.25) -> 1.2238193 | L77: =IF(K77="","no date",IF(K77<1,"0-1 yrs",IF(K77<2,"1-2 yrs",IF(K77<3,"2-3 yrs",IF(K77<5,"3-5 yrs","5+ yrs"))))) -> 1-2 yrs | M77: No | N77: =IF(M77="Yes","Memo flag - not ours / unknown / hold: resolve",IF(OR(COUNTIF(Summary!$C$4:$L$4,H77)>0,AND(A77="Philly",COUNTIF(Summary!$C$5:$L$5,H77)>0),AND(A77="TUR",COUNTIF(Summary!$C$6:$L$6,H77)>0)),"Fee amount - presumed company revenue",IF(H77<=Summary!$B$7,"Small amount - likely fee, review","Larger amount - likely includes agent commission"))) -> Larger amount - likely includes agent commission | O77: =IFERROR(INDEX('State Rules'!$C$5:$C$11,MATCH($B77,'State Rules'!$A$5:$A$11,0)),"") -> 1 | P77: =IF(OR(O77="",E77=""),"",EDATE(E77,12*O77)) -> 46219 | Q77: =IF(E77="","",IFERROR(EDATE(E77,12*INDEX('State Rules'!$E$5:$E$11,MATCH($B77,'State Rules'!$A$5:$A$11,0))),"")) -> 46950 | R77: =IF(P77="","",IFERROR(IF(P77<=INDEX('State Rules'!$I$5:$I$11,MATCH($B77,'State Rules'!$A$5:$A$11,0)),"Yes","No"),"")) -> Yes | S77: =IF(Q77="","",IFERROR(IF(Q77<=INDEX('State Rules'!$I$5:$I$11,MATCH($B77,'State Rules'!$A$5:$A$11,0)),"Yes","No"),"")) -> No | Z77: =IF(Q77="","",IF(Q77<=$B$4,N(W77)+N(X77),0)) -> 0 | AA77: =IF(OR(LEFT(N77,6)="Larger",LEFT(N77,4)="Memo"),H77,0) -> 263
A78: Houston | B78: =IFERROR(INDEX(Summary!$B$10:$B$17,MATCH($A78,Summary!$A$10:$A$17,0)),"") -> TX | C78: Houston | D78: 42 | E78: 45866 | F78: 674 | G78: Fresh Start Home Services | H78: 3750 | I78: 310 Magnolia | J78: No | K78: =IF(E78="","",($B$4-E78)/365.25) -> 1.1909651 | L78: =IF(K78="","no date",IF(K78<1,"0-1 yrs",IF(K78<2,"1-2 yrs",IF(K78<3,"2-3 yrs",IF(K78<5,"3-5 yrs","5+ yrs"))))) -> 1-2 yrs | M78: No | N78: =IF(M78="Yes","Memo flag - not ours / unknown / hold: resolve",IF(OR(COUNTIF(Summary!$C$4:$L$4,H78)>0,AND(A78="Philly",COUNTIF(Summary!$C$5:$L$5,H78)>0),AND(A78="TUR",COUNTIF(Summary!$C$6:$L$6,H78)>0)),"Fee amount - presumed company revenue",IF(H78<=Summary!$B$7,"Small amount - likely fee, review","Larger amount - likely includes agent commission"))) -> Larger amount - likely includes agent commission | O78: =IFERROR(INDEX('State Rules'!$C$5:$C$11,MATCH($B78,'State Rules'!$A$5:$A$11,0)),"") -> 1 | P78: =IF(OR(O78="",E78=""),"",EDATE(E78,12*O78)) -> 46231 | Q78: =IF(E78="","",IFERROR(EDATE(E78,12*INDEX('State Rules'!$E$5:$E$11,MATCH($B78,'State Rules'!$A$5:$A$11,0))),"")) -> 46962 | R78: =IF(P78="","",IFERROR(IF(P78<=INDEX('State Rules'!$I$5:$I$11,MATCH($B78,'State Rules'!$A$5:$A$11,0)),"Yes","No"),"")) -> Yes | S78: =IF(Q78="","",IFERROR(IF(Q78<=INDEX('State Rules'!$I$5:$I$11,MATCH($B78,'State Rules'!$A$5:$A$11,0)),"Yes","No"),"")) -> No | Z78: =IF(Q78="","",IF(Q78<=$B$4,N(W78)+N(X78),0)) -> 0 | AA78: =IF(OR(LEFT(N78,6)="Larger",LEFT(N78,4)="Memo"),H78,0) -> 3750
A79: Houston | B79: =IFERROR(INDEX(Summary!$B$10:$B$17,MATCH($A79,Summary!$A$10:$A$17,0)),"") -> TX | C79: Houston | D79: 43 | E79: 45869 | F79: 103931 | G79: InFocus Title LLC | H79: 10600 | J79: No | K79: =IF(E79="","",($B$4-E79)/365.25) -> 1.1827515 | L79: =IF(K79="","no date",IF(K79<1,"0-1 yrs",IF(K79<2,"1-2 yrs",IF(K79<3,"2-3 yrs",IF(K79<5,"3-5 yrs","5+ yrs"))))) -> 1-2 yrs | M79: No | N79: =IF(M79="Yes","Memo flag - not ours / unknown / hold: resolve",IF(OR(COUNTIF(Summary!$C$4:$L$4,H79)>0,AND(A79="Philly",COUNTIF(Summary!$C$5:$L$5,H79)>0),AND(A79="TUR",COUNTIF(Summary!$C$6:$L$6,H79)>0)),"Fee amount - presumed company revenue",IF(H79<=Summary!$B$7,"Small amount - likely fee, review","Larger amount - likely includes agent commission"))) -> Larger amount - likely includes agent commission | O79: =IFERROR(INDEX('State Rules'!$C$5:$C$11,MATCH($B79,'State Rules'!$A$5:$A$11,0)),"") -> 1 | P79: =IF(OR(O79="",E79=""),"",EDATE(E79,12*O79)) -> 46234 | Q79: =IF(E79="","",IFERROR(EDATE(E79,12*INDEX('State Rules'!$E$5:$E$11,MATCH($B79,'State Rules'!$A$5:$A$11,0))),"")) -> 46965 | R79: =IF(P79="","",IFERROR(IF(P79<=INDEX('State Rules'!$I$5:$I$11,MATCH($B79,'State Rules'!$A$5:$A$11,0)),"Yes","No"),"")) -> Yes | S79: =IF(Q79="","",IFERROR(IF(Q79<=INDEX('State Rules'!$I$5:$I$11,MATCH($B79,'State Rules'!$A$5:$A$11,0)),"Yes","No"),"")) -> No | Z79: =IF(Q79="","",IF(Q79<=$B$4,N(W79)+N(X79),0)) -> 0 | AA79: =IF(OR(LEFT(N79,6)="Larger",LEFT(N79,4)="Memo"),H79,0) -> 10600
A80: Houston | B80: =IFERROR(INDEX(Summary!$B$10:$B$17,MATCH($A80,Summary!$A$10:$A$17,0)),"") -> TX | C80: Houston | D80: 44 | E80: 45877 | F80: 7042 | H80: 531.25 | I80: 2507 Montrose 22 | J80: No | K80: =IF(E80="","",($B$4-E80)/365.25) -> 1.1608487 | L80: =IF(K80="","no date",IF(K80<1,"0-1 yrs",IF(K80<2,"1-2 yrs",IF(K80<3,"2-3 yrs",IF(K80<5,"3-5 yrs","5+ yrs"))))) -> 1-2 yrs | M80: No | N80: =IF(M80="Yes","Memo flag - not ours / unknown / hold: resolve",IF(OR(COUNTIF(Summary!$C$4:$L$4,H80)>0,AND(A80="Philly",COUNTIF(Summary!$C$5:$L$5,H80)>0),AND(A80="TUR",COUNTIF(Summary!$C$6:$L$6,H80)>0)),"Fee amount - presumed company revenue",IF(H80<=Summary!$B$7,"Small amount - likely fee, review","Larger amount - likely includes agent commission"))) -> Larger amount - likely includes agent commission | O80: =IFERROR(INDEX('State Rules'!$C$5:$C$11,MATCH($B80,'State Rules'!$A$5:$A$11,0)),"") -> 1 | P80: =IF(OR(O80="",E80=""),"",EDATE(E80,12*O80)) -> 46242 | Q80: =IF(E80="","",IFERROR(EDATE(E80,12*INDEX('State Rules'!$E$5:$E$11,MATCH($B80,'State Rules'!$A$5:$A$11,0))),"")) -> 46973 | R80: =IF(P80="","",IFERROR(IF(P80<=INDEX('State Rules'!$I$5:$I$11,MATCH($B80,'State Rules'!$A$5:$A$11,0)),"Yes","No"),"")) -> Yes | S80: =IF(Q80="","",IFERROR(IF(Q80<=INDEX('State Rules'!$I$5:$I$11,MATCH($B80,'State Rules'!$A$5:$A$11,0)),"Yes","No"),"")) -> No | Z80: =IF(Q80="","",IF(Q80<=$B$4,N(W80)+N(X80),0)) -> 0 | AA80: =IF(OR(LEFT(N80,6)="Larger",LEFT(N80,4)="Memo"),H80,0) -> 531.25
A81: Houston | B81: =IFERROR(INDEX(Summary!$B$10:$B$17,MATCH($A81,Summary!$A$10:$A$17,0)),"") -> TX | C81: Houston | D81: 45 | E81: 45888 | F81: 533019415 | H81: 16200 | I81: 2332 Shadow Falls Ln | J81: No | K81: =IF(E81="","",($B$4-E81)/365.25) -> 1.1307324 | L81: =IF(K81="","no date",IF(K81<1,"0-1 yrs",IF(K81<2,"1-2 yrs",IF(K81<3,"2-3 yrs",IF(K81<5,"3-5 yrs","5+ yrs"))))) -> 1-2 yrs | M81: No | N81: =IF(M81="Yes","Memo flag - not ours / unknown / hold: resolve",IF(OR(COUNTIF(Summary!$C$4:$L$4,H81)>0,AND(A81="Philly",COUNTIF(Summary!$C$5:$L$5,H81)>0),AND(A81="TUR",COUNTIF(Summary!$C$6:$L$6,H81)>0)),"Fee amount - presumed company revenue",IF(H81<=Summary!$B$7,"Small amount - likely fee, review","Larger amount - likely includes agent commission"))) -> Larger amount - likely includes agent commission | O81: =IFERROR(INDEX('State Rules'!$C$5:$C$11,MATCH($B81,'State Rules'!$A$5:$A$11,0)),"") -> 1 | P81: =IF(OR(O81="",E81=""),"",EDATE(E81,12*O81)) -> 46253 | Q81: =IF(E81="","",IFERROR(EDATE(E81,12*INDEX('State Rules'!$E$5:$E$11,MATCH($B81,'State Rules'!$A$5:$A$11,0))),"")) -> 46984 | R81: =IF(P81="","",IFERROR(IF(P81<=INDEX('State Rules'!$I$5:$I$11,MATCH($B81,'State Rules'!$A$5:$A$11,0)),"Yes","No"),"")) -> Yes | S81: =IF(Q81="","",IFERROR(IF(Q81<=INDEX('State Rules'!$I$5:$I$11,MATCH($B81,'State Rules'!$A$5:$A$11,0)),"Yes","No"),"")) -> No | Z81: =IF(Q81="","",IF(Q81<=$B$4,N(W81)+N(X81),0)) -> 0 | AA81: =IF(OR(LEFT(N81,6)="Larger",LEFT(N81,4)="Memo"),H81,0) -> 16200
A82: Houston | B82: =IFERROR(INDEX(Summary!$B$10:$B$17,MATCH($A82,Summary!$A$10:$A$17,0)),"") -> TX | C82: Houston | D82: 46 | E82: 45916 | F82: 1527 | H82: 636.75 | J82: No | K82: =IF(E82="","",($B$4-E82)/365.25) -> 1.0540726 | L82: =IF(K82="","no date",IF(K82<1,"0-1 yrs",IF(K82<2,"1-2 yrs",IF(K82<3,"2-3 yrs",IF(K82<5,"3-5 yrs","5+ yrs"))))) -> 1-2 yrs | M82: No | N82: =IF(M82="Yes","Memo flag - not ours / unknown / hold: resolve",IF(OR(COUNTIF(Summary!$C$4:$L$4,H82)>0,AND(A82="Philly",COUNTIF(Summary!$C$5:$L$5,H82)>0),AND(A82="TUR",COUNTIF(Summary!$C$6:$L$6,H82)>0)),"Fee amount - presumed company revenue",IF(H82<=Summary!$B$7,"Small amount - likely fee, review","Larger amount - likely includes agent commission"))) -> Larger amount - likely includes agent commission | O82: =IFERROR(INDEX('State Rules'!$C$5:$C$11,MATCH($B82,'State Rules'!$A$5:$A$11,0)),"") -> 1 | P82: =IF(OR(O82="",E82=""),"",EDATE(E82,12*O82)) -> 46281 | Q82: =IF(E82="","",IFERROR(EDATE(E82,12*INDEX('State Rules'!$E$5:$E$11,MATCH($B82,'State Rules'!$A$5:$A$11,0))),"")) -> 47012 | R82: =IF(P82="","",IFERROR(IF(P82<=INDEX('State Rules'!$I$5:$I$11,MATCH($B82,'State Rules'!$A$5:$A$11,0)),"Yes","No"),"")) -> Yes | S82: =IF(Q82="","",IFERROR(IF(Q82<=INDEX('State Rules'!$I$5:$I$11,MATCH($B82,'State Rules'!$A$5:$A$11,0)),"Yes","No"),"")) -> No | Z82: =IF(Q82="","",IF(Q82<=$B$4,N(W82)+N(X82),0)) -> 0 | AA82: =IF(OR(LEFT(N82,6)="Larger",LEFT(N82,4)="Memo"),H82,0) -> 636.75
A83: Houston | B83: =IFERROR(INDEX(Summary!$B$10:$B$17,MATCH($A83,Summary!$A$10:$A$17,0)),"") -> TX | C83: Houston | D83: 47 | E83: 45930 | F83: 104004 | H83: 100 | J83: No | K83: =IF(E83="","",($B$4-E83)/365.25) -> 1.0157426 | L83: =IF(K83="","no date",IF(K83<1,"0-1 yrs",IF(K83<2,"1-2 yrs",IF(K83<3,"2-3 yrs",IF(K83<5,"3-5 yrs","5+ yrs"))))) -> 1-2 yrs | M83: No | N83: =IF(M83="Yes","Memo flag - not ours / unknown / hold: resolve",IF(OR(COUNTIF(Summary!$C$4:$L$4,H83)>0,AND(A83="Philly",COUNTIF(Summary!$C$5:$L$5,H83)>0),AND(A83="TUR",COUNTIF(Summary!$C$6:$L$6,H83)>0)),"Fee amount - presumed company revenue",IF(H83<=Summary!$B$7,"Small amount - likely fee, review","Larger amount - likely includes agent commission"))) -> Small amount - likely fee, review | O83: =IFERROR(INDEX('State Rules'!$C$5:$C$11,MATCH($B83,'State Rules'!$A$5:$A$11,0)),"") -> 1 | P83: =IF(OR(O83="",E83=""),"",EDATE(E83,12*O83)) -> 46295 | Q83: =IF(E83="","",IFERROR(EDATE(E83,12*INDEX('State Rules'!$E$5:$E$11,MATCH($B83,'State Rules'!$A$5:$A$11,0))),"")) -> 47026 | R83: =IF(P83="","",IFERROR(IF(P83<=INDEX('State Rules'!$I$5:$I$11,MATCH($B83,'State Rules'!$A$5:$A$11,0)),"Yes","No"),"")) -> Yes | S83: =IF(Q83="","",IFERROR(IF(Q83<=INDEX('State Rules'!$I$5:$I$11,MATCH($B83,'State Rules'!$A$5:$A$11,0)),"Yes","No"),"")) -> No | Z83: =IF(Q83="","",IF(Q83<=$B$4,N(W83)+N(X83),0)) -> 0 | AA83: =IF(OR(LEFT(N83,6)="Larger",LEFT(N83,4)="Memo"),H83,0) -> 0
A84: Houston | B84: =IFERROR(INDEX(Summary!$B$10:$B$17,MATCH($A84,Summary!$A$10:$A$17,0)),"") -> TX | C84: Houston | D84: 48 | E84: 46045 | F84: 1334 | H84: 850 | J84: No | K84: =IF(E84="","",($B$4-E84)/365.25) -> 0.7008898 | L84: =IF(K84="","no date",IF(K84<1,"0-1 yrs",IF(K84<2,"1-2 yrs",IF(K84<3,"2-3 yrs",IF(K84<5,"3-5 yrs","5+ yrs"))))) -> 0-1 yrs | M84: No | N84: =IF(M84="Yes","Memo flag - not ours / unknown / hold: resolve",IF(OR(COUNTIF(Summary!$C$4:$L$4,H84)>0,AND(A84="Philly",COUNTIF(Summary!$C$5:$L$5,H84)>0),AND(A84="TUR",COUNTIF(Summary!$C$6:$L$6,H84)>0)),"Fee amount - presumed company revenue",IF(H84<=Summary!$B$7,"Small amount - likely fee, review","Larger amount - likely includes agent commission"))) -> Larger amount - likely includes agent commission | O84: =IFERROR(INDEX('State Rules'!$C$5:$C$11,MATCH($B84,'State Rules'!$A$5:$A$11,0)),"") -> 1 | P84: =IF(OR(O84="",E84=""),"",EDATE(E84,12*O84)) -> 46410 | Q84: =IF(E84="","",IFERROR(EDATE(E84,12*INDEX('State Rules'!$E$5:$E$11,MATCH($B84,'State Rules'!$A$5:$A$11,0))),"")) -> 47141 | R84: =IF(P84="","",IFERROR(IF(P84<=INDEX('State Rules'!$I$5:$I$11,MATCH($B84,'State Rules'!$A$5:$A$11,0)),"Yes","No"),"")) -> Yes | S84: =IF(Q84="","",IFERROR(IF(Q84<=INDEX('State Rules'!$I$5:$I$11,MATCH($B84,'State Rules'!$A$5:$A$11,0)),"Yes","No"),"")) -> No | Z84: =IF(Q84="","",IF(Q84<=$B$4,N(W84)+N(X84),0)) -> 0 | AA84: =IF(OR(LEFT(N84,6)="Larger",LEFT(N84,4)="Memo"),H84,0) -> 850
A85: Houston | B85: =IFERROR(INDEX(Summary!$B$10:$B$17,MATCH($A85,Summary!$A$10:$A$17,0)),"") -> TX | C85: Houston | D85: 49 | E85: 46052 | F85: 101147 | H85: 644 | J85: No | K85: =IF(E85="","",($B$4-E85)/365.25) -> 0.68172485 | L85: =IF(K85="","no date",IF(K85<1,"0-1 yrs",IF(K85<2,"1-2 yrs",IF(K85<3,"2-3 yrs",IF(K85<5,"3-5 yrs","5+ yrs"))))) -> 0-1 yrs | M85: No | N85: =IF(M85="Yes","Memo flag - not ours / unknown / hold: resolve",IF(OR(COUNTIF(Summary!$C$4:$L$4,H85)>0,AND(A85="Philly",COUNTIF(Summary!$C$5:$L$5,H85)>0),AND(A85="TUR",COUNTIF(Summary!$C$6:$L$6,H85)>0)),"Fee amount - presumed company revenue",IF(H85<=Summary!$B$7,"Small amount - likely fee, review","Larger amount - likely includes agent commission"))) -> Fee amount - presumed company revenue | O85: =IFERROR(INDEX('State Rules'!$C$5:$C$11,MATCH($B85,'State Rules'!$A$5:$A$11,0)),"") -> 1 | P85: =IF(OR(O85="",E85=""),"",EDATE(E85,12*O85)) -> 46417 | Q85: =IF(E85="","",IFERROR(EDATE(E85,12*INDEX('State Rules'!$E$5:$E$11,MATCH($B85,'State Rules'!$A$5:$A$11,0))),"")) -> 47148 | R85: =IF(P85="","",IFERROR(IF(P85<=INDEX('State Rules'!$I$5:$I$11,MATCH($B85,'State Rules'!$A$5:$A$11,0)),"Yes","No"),"")) -> Yes | S85: =IF(Q85="","",IFERROR(IF(Q85<=INDEX('State Rules'!$I$5:$I$11,MATCH($B85,'State Rules'!$A$5:$A$11,0)),"Yes","No"),"")) -> No | Z85: =IF(Q85="","",IF(Q85<=$B$4,N(W85)+N(X85),0)) -> 0 | AA85: =IF(OR(LEFT(N85,6)="Larger",LEFT(N85,4)="Memo"),H85,0) -> 0
A86: Houston | B86: =IFERROR(INDEX(Summary!$B$10:$B$17,MATCH($A86,Summary!$A$10:$A$17,0)),"") -> TX | C86: Houston | D86: 50 | E86: 46098 | F86: 916573566 | G86: 5th Stream Realty LLC | H86: 1397.5 | J86: No | K86: =IF(E86="","",($B$4-E86)/365.25) -> 0.55578371 | L86: =IF(K86="","no date",IF(K86<1,"0-1 yrs",IF(K86<2,"1-2 yrs",IF(K86<3,"2-3 yrs",IF(K86<5,"3-5 yrs","5+ yrs"))))) -> 0-1 yrs | M86: No | N86: =IF(M86="Yes","Memo flag - not ours / unknown / hold: resolve",IF(OR(COUNTIF(Summary!$C$4:$L$4,H86)>0,AND(A86="Philly",COUNTIF(Summary!$C$5:$L$5,H86)>0),AND(A86="TUR",COUNTIF(Summary!$C$6:$L$6,H86)>0)),"Fee amount - presumed company revenue",IF(H86<=Summary!$B$7,"Small amount - likely fee, review","Larger amount - likely includes agent commission"))) -> Larger amount - likely includes agent commission | O86: =IFERROR(INDEX('State Rules'!$C$5:$C$11,MATCH($B86,'State Rules'!$A$5:$A$11,0)),"") -> 1 | P86: =IF(OR(O86="",E86=""),"",EDATE(E86,12*O86)) -> 46463 | Q86: =IF(E86="","",IFERROR(EDATE(E86,12*INDEX('State Rules'!$E$5:$E$11,MATCH($B86,'State Rules'!$A$5:$A$11,0))),"")) -> 47194 | R86: =IF(P86="","",IFERROR(IF(P86<=INDEX('State Rules'!$I$5:$I$11,MATCH($B86,'State Rules'!$A$5:$A$11,0)),"Yes","No"),"")) -> No | S86: =IF(Q86="","",IFERROR(IF(Q86<=INDEX('State Rules'!$I$5:$I$11,MATCH($B86,'State Rules'!$A$5:$A$11,0)),"Yes","No"),"")) -> No | Z86: =IF(Q86="","",IF(Q86<=$B$4,N(W86)+N(X86),0)) -> 0 | AA86: =IF(OR(LEFT(N86,6)="Larger",LEFT(N86,4)="Memo"),H86,0) -> 1397.5
A87: Houston | B87: =IFERROR(INDEX(Summary!$B$10:$B$17,MATCH($A87,Summary!$A$10:$A$17,0)),"") -> TX | C87: Houston | D87: 51 | E87: 46119 | F87: 8504541397 | G87: AvidXchange, Inc | H87: 999.5 | J87: No | K87: =IF(E87="","",($B$4-E87)/365.25) -> 0.49828884 | L87: =IF(K87="","no date",IF(K87<1,"0-1 yrs",IF(K87<2,"1-2 yrs",IF(K87<3,"2-3 yrs",IF(K87<5,"3-5 yrs","5+ yrs"))))) -> 0-1 yrs | M87: No | N87: =IF(M87="Yes","Memo flag - not ours / unknown / hold: resolve",IF(OR(COUNTIF(Summary!$C$4:$L$4,H87)>0,AND(A87="Philly",COUNTIF(Summary!$C$5:$L$5,H87)>0),AND(A87="TUR",COUNTIF(Summary!$C$6:$L$6,H87)>0)),"Fee amount - presumed company revenue",IF(H87<=Summary!$B$7,"Small amount - likely fee, review","Larger amount - likely includes agent commission"))) -> Larger amount - likely includes agent commission | O87: =IFERROR(INDEX('State Rules'!$C$5:$C$11,MATCH($B87,'State Rules'!$A$5:$A$11,0)),"") -> 1 | P87: =IF(OR(O87="",E87=""),"",EDATE(E87,12*O87)) -> 46484 | Q87: =IF(E87="","",IFERROR(EDATE(E87,12*INDEX('State Rules'!$E$5:$E$11,MATCH($B87,'State Rules'!$A$5:$A$11,0))),"")) -> 47215 | R87: =IF(P87="","",IFERROR(IF(P87<=INDEX('State Rules'!$I$5:$I$11,MATCH($B87,'State Rules'!$A$5:$A$11,0)),"Yes","No"),"")) -> No | S87: =IF(Q87="","",IFERROR(IF(Q87<=INDEX('State Rules'!$I$5:$I$11,MATCH($B87,'State Rules'!$A$5:$A$11,0)),"Yes","No"),"")) -> No | Z87: =IF(Q87="","",IF(Q87<=$B$4,N(W87)+N(X87),0)) -> 0 | AA87: =IF(OR(LEFT(N87,6)="Larger",LEFT(N87,4)="Memo"),H87,0) -> 999.5
A88: Houston | B88: =IFERROR(INDEX(Summary!$B$10:$B$17,MATCH($A88,Summary!$A$10:$A$17,0)),"") -> TX | C88: Houston | D88: 52 | E88: 46146 | F88: 593035158 | H88: 15450 | I88: Fidelity National Title | J88: No | K88: =IF(E88="","",($B$4-E88)/365.25) -> 0.42436687 | L88: =IF(K88="","no date",IF(K88<1,"0-1 yrs",IF(K88<2,"1-2 yrs",IF(K88<3,"2-3 yrs",IF(K88<5,"3-5 yrs","5+ yrs"))))) -> 0-1 yrs | M88: No | N88: =IF(M88="Yes","Memo flag - not ours / unknown / hold: resolve",IF(OR(COUNTIF(Summary!$C$4:$L$4,H88)>0,AND(A88="Philly",COUNTIF(Summary!$C$5:$L$5,H88)>0),AND(A88="TUR",COUNTIF(Summary!$C$6:$L$6,H88)>0)),"Fee amount - presumed company revenue",IF(H88<=Summary!$B$7,"Small amount - likely fee, review","Larger amount - likely includes agent commission"))) -> Larger amount - likely includes agent commission | O88: =IFERROR(INDEX('State Rules'!$C$5:$C$11,MATCH($B88,'State Rules'!$A$5:$A$11,0)),"") -> 1 | P88: =IF(OR(O88="",E88=""),"",EDATE(E88,12*O88)) -> 46511 | Q88: =IF(E88="","",IFERROR(EDATE(E88,12*INDEX('State Rules'!$E$5:$E$11,MATCH($B88,'State Rules'!$A$5:$A$11,0))),"")) -> 47242 | R88: =IF(P88="","",IFERROR(IF(P88<=INDEX('State Rules'!$I$5:$I$11,MATCH($B88,'State Rules'!$A$5:$A$11,0)),"Yes","No"),"")) -> No | S88: =IF(Q88="","",IFERROR(IF(Q88<=INDEX('State Rules'!$I$5:$I$11,MATCH($B88,'State Rules'!$A$5:$A$11,0)),"Yes","No"),"")) -> No | Z88: =IF(Q88="","",IF(Q88<=$B$4,N(W88)+N(X88),0)) -> 0 | AA88: =IF(OR(LEFT(N88,6)="Larger",LEFT(N88,4)="Memo"),H88,0) -> 15450
A89: Houston | B89: =IFERROR(INDEX(Summary!$B$10:$B$17,MATCH($A89,Summary!$A$10:$A$17,0)),"") -> TX | C89: Houston | D89: 53 | E89: 46162 | F89: 103360 | H89: 644 | I89: 6919 Calhoun Road | J89: No | K89: =IF(E89="","",($B$4-E89)/365.25) -> 0.38056126 | L89: =IF(K89="","no date",IF(K89<1,"0-1 yrs",IF(K89<2,"1-2 yrs",IF(K89<3,"2-3 yrs",IF(K89<5,"3-5 yrs","5+ yrs"))))) -> 0-1 yrs | M89: No | N89: =IF(M89="Yes","Memo flag - not ours / unknown / hold: resolve",IF(OR(COUNTIF(Summary!$C$4:$L$4,H89)>0,AND(A89="Philly",COUNTIF(Summary!$C$5:$L$5,H89)>0),AND(A89="TUR",COUNTIF(Summary!$C$6:$L$6,H89)>0)),"Fee amount - presumed company revenue",IF(H89<=Summary!$B$7,"Small amount - likely fee, review","Larger amount - likely includes agent commission"))) -> Fee amount - presumed company revenue | O89: =IFERROR(INDEX('State Rules'!$C$5:$C$11,MATCH($B89,'State Rules'!$A$5:$A$11,0)),"") -> 1 | P89: =IF(OR(O89="",E89=""),"",EDATE(E89,12*O89)) -> 46527 | Q89: =IF(E89="","",IFERROR(EDATE(E89,12*INDEX('State Rules'!$E$5:$E$11,MATCH($B89,'State Rules'!$A$5:$A$11,0))),"")) -> 47258 | R89: =IF(P89="","",IFERROR(IF(P89<=INDEX('State Rules'!$I$5:$I$11,MATCH($B89,'State Rules'!$A$5:$A$11,0)),"Yes","No"),"")) -> No | S89: =IF(Q89="","",IFERROR(IF(Q89<=INDEX('State Rules'!$I$5:$I$11,MATCH($B89,'State Rules'!$A$5:$A$11,0)),"Yes","No"),"")) -> No | Z89: =IF(Q89="","",IF(Q89<=$B$4,N(W89)+N(X89),0)) -> 0 | AA89: =IF(OR(LEFT(N89,6)="Larger",LEFT(N89,4)="Memo"),H89,0) -> 0
A90: Houston | B90: =IFERROR(INDEX(Summary!$B$10:$B$17,MATCH($A90,Summary!$A$10:$A$17,0)),"") -> TX | C90: Houston | D90: 54 | E90: 46188 | F90: 211594 | G90: LPT Realty | H90: 875 | I90: 329485 - 19410 Bold River Road | J90: No | K90: =IF(E90="","",($B$4-E90)/365.25) -> 0.30937714 | L90: =IF(K90="","no date",IF(K90<1,"0-1 yrs",IF(K90<2,"1-2 yrs",IF(K90<3,"2-3 yrs",IF(K90<5,"3-5 yrs","5+ yrs"))))) -> 0-1 yrs | M90: No | N90: =IF(M90="Yes","Memo flag - not ours / unknown / hold: resolve",IF(OR(COUNTIF(Summary!$C$4:$L$4,H90)>0,AND(A90="Philly",COUNTIF(Summary!$C$5:$L$5,H90)>0),AND(A90="TUR",COUNTIF(Summary!$C$6:$L$6,H90)>0)),"Fee amount - presumed company revenue",IF(H90<=Summary!$B$7,"Small amount - likely fee, review","Larger amount - likely includes agent commission"))) -> Larger amount - likely includes agent commission | O90: =IFERROR(INDEX('State Rules'!$C$5:$C$11,MATCH($B90,'State Rules'!$A$5:$A$11,0)),"") -> 1 | P90: =IF(OR(O90="",E90=""),"",EDATE(E90,12*O90)) -> 46553 | Q90: =IF(E90="","",IFERROR(EDATE(E90,12*INDEX('State Rules'!$E$5:$E$11,MATCH($B90,'State Rules'!$A$5:$A$11,0))),"")) -> 47284 | R90: =IF(P90="","",IFERROR(IF(P90<=INDEX('State Rules'!$I$5:$I$11,MATCH($B90,'State Rules'!$A$5:$A$11,0)),"Yes","No"),"")) -> No | S90: =IF(Q90="","",IFERROR(IF(Q90<=INDEX('State Rules'!$I$5:$I$11,MATCH($B90,'State Rules'!$A$5:$A$11,0)),"Yes","No"),"")) -> No | Z90: =IF(Q90="","",IF(Q90<=$B$4,N(W90)+N(X90),0)) -> 0 | AA90: =IF(OR(LEFT(N90,6)="Larger",LEFT(N90,4)="Memo"),H90,0) -> 875
A91: Houston | B91: =IFERROR(INDEX(Summary!$B$10:$B$17,MATCH($A91,Summary!$A$10:$A$17,0)),"") -> TX | C91: Houston | D91: 55 | E91: 46197 | F91: 514 | G91: Evergreen Residential Holdings, LLC | H91: 922.5 | I91: 5710 Quinn Landing Houston, TX 77091 | J91: No | K91: =IF(E91="","",($B$4-E91)/365.25) -> 0.28473648 | L91: =IF(K91="","no date",IF(K91<1,"0-1 yrs",IF(K91<2,"1-2 yrs",IF(K91<3,"2-3 yrs",IF(K91<5,"3-5 yrs","5+ yrs"))))) -> 0-1 yrs | M91: No | N91: =IF(M91="Yes","Memo flag - not ours / unknown / hold: resolve",IF(OR(COUNTIF(Summary!$C$4:$L$4,H91)>0,AND(A91="Philly",COUNTIF(Summary!$C$5:$L$5,H91)>0),AND(A91="TUR",COUNTIF(Summary!$C$6:$L$6,H91)>0)),"Fee amount - presumed company revenue",IF(H91<=Summary!$B$7,"Small amount - likely fee, review","Larger amount - likely includes agent commission"))) -> Larger amount - likely includes agent commission | O91: =IFERROR(INDEX('State Rules'!$C$5:$C$11,MATCH($B91,'State Rules'!$A$5:$A$11,0)),"") -> 1 | P91: =IF(OR(O91="",E91=""),"",EDATE(E91,12*O91)) -> 46562 | Q91: =IF(E91="","",IFERROR(EDATE(E91,12*INDEX('State Rules'!$E$5:$E$11,MATCH($B91,'State Rules'!$A$5:$A$11,0))),"")) -> 47293 | R91: =IF(P91="","",IFERROR(IF(P91<=INDEX('State Rules'!$I$5:$I$11,MATCH($B91,'State Rules'!$A$5:$A$11,0)),"Yes","No"),"")) -> No | S91: =IF(Q91="","",IFERROR(IF(Q91<=INDEX('State Rules'!$I$5:$I$11,MATCH($B91,'State Rules'!$A$5:$A$11,0)),"Yes","No"),"")) -> No | Z91: =IF(Q91="","",IF(Q91<=$B$4,N(W91)+N(X91),0)) -> 0 | AA91: =IF(OR(LEFT(N91,6)="Larger",LEFT(N91,4)="Memo"),H91,0) -> 922.5
A92: Houston | B92: =IFERROR(INDEX(Summary!$B$10:$B$17,MATCH($A92,Summary!$A$10:$A$17,0)),"") -> TX | C92: Houston | D92: 56 | E92: 46202 | F92: 2419 | G92: SG Management LLC | H92: 1000 | J92: No | K92: =IF(E92="","",($B$4-E92)/365.25) -> 0.27104723 | L92: =IF(K92="","no date",IF(K92<1,"0-1 yrs",IF(K92<2,"1-2 yrs",IF(K92<3,"2-3 yrs",IF(K92<5,"3-5 yrs","5+ yrs"))))) -> 0-1 yrs | M92: No | N92: =IF(M92="Yes","Memo flag - not ours / unknown / hold: resolve",IF(OR(COUNTIF(Summary!$C$4:$L$4,H92)>0,AND(A92="Philly",COUNTIF(Summary!$C$5:$L$5,H92)>0),AND(A92="TUR",COUNTIF(Summary!$C$6:$L$6,H92)>0)),"Fee amount - presumed company revenue",IF(H92<=Summary!$B$7,"Small amount - likely fee, review","Larger amount - likely includes agent commission"))) -> Larger amount - likely includes agent commission | O92: =IFERROR(INDEX('State Rules'!$C$5:$C$11,MATCH($B92,'State Rules'!$A$5:$A$11,0)),"") -> 1 | P92: =IF(OR(O92="",E92=""),"",EDATE(E92,12*O92)) -> 46567 | Q92: =IF(E92="","",IFERROR(EDATE(E92,12*INDEX('State Rules'!$E$5:$E$11,MATCH($B92,'State Rules'!$A$5:$A$11,0))),"")) -> 47298 | R92: =IF(P92="","",IFERROR(IF(P92<=INDEX('State Rules'!$I$5:$I$11,MATCH($B92,'State Rules'!$A$5:$A$11,0)),"Yes","No"),"")) -> No | S92: =IF(Q92="","",IFERROR(IF(Q92<=INDEX('State Rules'!$I$5:$I$11,MATCH($B92,'State Rules'!$A$5:$A$11,0)),"Yes","No"),"")) -> No | Z92: =IF(Q92="","",IF(Q92<=$B$4,N(W92)+N(X92),0)) -> 0 | AA92: =IF(OR(LEFT(N92,6)="Larger",LEFT(N92,4)="Memo"),H92,0) -> 1000
A93: Houston | B93: =IFERROR(INDEX(Summary!$B$10:$B$17,MATCH($A93,Summary!$A$10:$A$17,0)),"") -> TX | C93: Houston | D93: 57 | E93: 46203 | F93: 1299881 | G93: TDECU | H93: 1700 | I93: 3318 Schroeder | J93: No | K93: =IF(E93="","",($B$4-E93)/365.25) -> 0.26830938 | L93: =IF(K93="","no date",IF(K93<1,"0-1 yrs",IF(K93<2,"1-2 yrs",IF(K93<3,"2-3 yrs",IF(K93<5,"3-5 yrs","5+ yrs"))))) -> 0-1 yrs | M93: No | N93: =IF(M93="Yes","Memo flag - not ours / unknown / hold: resolve",IF(OR(COUNTIF(Summary!$C$4:$L$4,H93)>0,AND(A93="Philly",COUNTIF(Summary!$C$5:$L$5,H93)>0),AND(A93="TUR",COUNTIF(Summary!$C$6:$L$6,H93)>0)),"Fee amount - presumed company revenue",IF(H93<=Summary!$B$7,"Small amount - likely fee, review","Larger amount - likely includes agent commission"))) -> Larger amount - likely includes agent commission | O93: =IFERROR(INDEX('State Rules'!$C$5:$C$11,MATCH($B93,'State Rules'!$A$5:$A$11,0)),"") -> 1 | P93: =IF(OR(O93="",E93=""),"",EDATE(E93,12*O93)) -> 46568 | Q93: =IF(E93="","",IFERROR(EDATE(E93,12*INDEX('State Rules'!$E$5:$E$11,MATCH($B93,'State Rules'!$A$5:$A$11,0))),"")) -> 47299 | R93: =IF(P93="","",IFERROR(IF(P93<=INDEX('State Rules'!$I$5:$I$11,MATCH($B93,'State Rules'!$A$5:$A$11,0)),"Yes","No"),"")) -> No | S93: =IF(Q93="","",IFERROR(IF(Q93<=INDEX('State Rules'!$I$5:$I$11,MATCH($B93,'State Rules'!$A$5:$A$11,0)),"Yes","No"),"")) -> No | Z93: =IF(Q93="","",IF(Q93<=$B$4,N(W93)+N(X93),0)) -> 0 | AA93: =IF(OR(LEFT(N93,6)="Larger",LEFT(N93,4)="Memo"),H93,0) -> 1700
A94: Houston | B94: =IFERROR(INDEX(Summary!$B$10:$B$17,MATCH($A94,Summary!$A$10:$A$17,0)),"") -> TX | C94: Houston | D94: 58 | E94: 46204 | F94: 104665 | G94: InFocus Title LLC | H94: 644 | I94: Listing agent commission | J94: No | K94: =IF(E94="","",($B$4-E94)/365.25) -> 0.26557153 | L94: =IF(K94="","no date",IF(K94<1,"0-1 yrs",IF(K94<2,"1-2 yrs",IF(K94<3,"2-3 yrs",IF(K94<5,"3-5 yrs","5+ yrs"))))) -> 0-1 yrs | M94: No | N94: =IF(M94="Yes","Memo flag - not ours / unknown / hold: resolve",IF(OR(COUNTIF(Summary!$C$4:$L$4,H94)>0,AND(A94="Philly",COUNTIF(Summary!$C$5:$L$5,H94)>0),AND(A94="TUR",COUNTIF(Summary!$C$6:$L$6,H94)>0)),"Fee amount - presumed company revenue",IF(H94<=Summary!$B$7,"Small amount - likely fee, review","Larger amount - likely includes agent commission"))) -> Fee amount - presumed company revenue | O94: =IFERROR(INDEX('State Rules'!$C$5:$C$11,MATCH($B94,'State Rules'!$A$5:$A$11,0)),"") -> 1 | P94: =IF(OR(O94="",E94=""),"",EDATE(E94,12*O94)) -> 46569 | Q94: =IF(E94="","",IFERROR(EDATE(E94,12*INDEX('State Rules'!$E$5:$E$11,MATCH($B94,'State Rules'!$A$5:$A$11,0))),"")) -> 47300 | R94: =IF(P94="","",IFERROR(IF(P94<=INDEX('State Rules'!$I$5:$I$11,MATCH($B94,'State Rules'!$A$5:$A$11,0)),"Yes","No"),"")) -> No | S94: =IF(Q94="","",IFERROR(IF(Q94<=INDEX('State Rules'!$I$5:$I$11,MATCH($B94,'State Rules'!$A$5:$A$11,0)),"Yes","No"),"")) -> No | Z94: =IF(Q94="","",IF(Q94<=$B$4,N(W94)+N(X94),0)) -> 0 | AA94: =IF(OR(LEFT(N94,6)="Larger",LEFT(N94,4)="Memo"),H94,0) -> 0
A95: Houston | B95: =IFERROR(INDEX(Summary!$B$10:$B$17,MATCH($A95,Summary!$A$10:$A$17,0)),"") -> TX | C95: Houston | D95: 59 | E95: 46224 | F95: 232098 | G95: Patten title | H95: 495 | I95: 2703 Glenn Lakes | J95: No | K95: =IF(E95="","",($B$4-E95)/365.25) -> 0.21081451 | L95: =IF(K95="","no date",IF(K95<1,"0-1 yrs",IF(K95<2,"1-2 yrs",IF(K95<3,"2-3 yrs",IF(K95<5,"3-5 yrs","5+ yrs"))))) -> 0-1 yrs | M95: No | N95: =IF(M95="Yes","Memo flag - not ours / unknown / hold: resolve",IF(OR(COUNTIF(Summary!$C$4:$L$4,H95)>0,AND(A95="Philly",COUNTIF(Summary!$C$5:$L$5,H95)>0),AND(A95="TUR",COUNTIF(Summary!$C$6:$L$6,H95)>0)),"Fee amount - presumed company revenue",IF(H95<=Summary!$B$7,"Small amount - likely fee, review","Larger amount - likely includes agent commission"))) -> Larger amount - likely includes agent commission | O95: =IFERROR(INDEX('State Rules'!$C$5:$C$11,MATCH($B95,'State Rules'!$A$5:$A$11,0)),"") -> 1 | P95: =IF(OR(O95="",E95=""),"",EDATE(E95,12*O95)) -> 46589 | Q95: =IF(E95="","",IFERROR(EDATE(E95,12*INDEX('State Rules'!$E$5:$E$11,MATCH($B95,'State Rules'!$A$5:$A$11,0))),"")) -> 47320 | R95: =IF(P95="","",IFERROR(IF(P95<=INDEX('State Rules'!$I$5:$I$11,MATCH($B95,'State Rules'!$A$5:$A$11,0)),"Yes","No"),"")) -> No | S95: =IF(Q95="","",IFERROR(IF(Q95<=INDEX('State Rules'!$I$5:$I$11,MATCH($B95,'State Rules'!$A$5:$A$11,0)),"Yes","No"),"")) -> No | Z95: =IF(Q95="","",IF(Q95<=$B$4,N(W95)+N(X95),0)) -> 0 | AA95: =IF(OR(LEFT(N95,6)="Larger",LEFT(N95,4)="Memo"),H95,0) -> 495
A96: Houston | B96: =IFERROR(INDEX(Summary!$B$10:$B$17,MATCH($A96,Summary!$A$10:$A$17,0)),"") -> TX | C96: Houston | D96: 60 | E96: 46239 | H96: 795 | J96: No | K96: =IF(E96="","",($B$4-E96)/365.25) -> 0.16974675 | L96: =IF(K96="","no date",IF(K96<1,"0-1 yrs",IF(K96<2,"1-2 yrs",IF(K96<3,"2-3 yrs",IF(K96<5,"3-5 yrs","5+ yrs"))))) -> 0-1 yrs | M96: No | N96: =IF(M96="Yes","Memo flag - not ours / unknown / hold: resolve",IF(OR(COUNTIF(Summary!$C$4:$L$4,H96)>0,AND(A96="Philly",COUNTIF(Summary!$C$5:$L$5,H96)>0),AND(A96="TUR",COUNTIF(Summary!$C$6:$L$6,H96)>0)),"Fee amount - presumed company revenue",IF(H96<=Summary!$B$7,"Small amount - likely fee, review","Larger amount - likely includes agent commission"))) -> Larger amount - likely includes agent commission | O96: =IFERROR(INDEX('State Rules'!$C$5:$C$11,MATCH($B96,'State Rules'!$A$5:$A$11,0)),"") -> 1 | P96: =IF(OR(O96="",E96=""),"",EDATE(E96,12*O96)) -> 46604 | Q96: =IF(E96="","",IFERROR(EDATE(E96,12*INDEX('State Rules'!$E$5:$E$11,MATCH($B96,'State Rules'!$A$5:$A$11,0))),"")) -> 47335 | R96: =IF(P96="","",IFERROR(IF(P96<=INDEX('State Rules'!$I$5:$I$11,MATCH($B96,'State Rules'!$A$5:$A$11,0)),"Yes","No"),"")) -> No | S96: =IF(Q96="","",IFERROR(IF(Q96<=INDEX('State Rules'!$I$5:$I$11,MATCH($B96,'State Rules'!$A$5:$A$11,0)),"Yes","No"),"")) -> No | Z96: =IF(Q96="","",IF(Q96<=$B$4,N(W96)+N(X96),0)) -> 0 | AA96: =IF(OR(LEFT(N96,6)="Larger",LEFT(N96,4)="Memo"),H96,0) -> 795
A97: TUR | B97: =IFERROR(INDEX(Summary!$B$10:$B$17,MATCH($A97,Summary!$A$10:$A$17,0)),"") -> TX | C97: TUR | D97: 22 | E97: 44951 | F97: 64427 | G97: Stewart Title Company | H97: 120 | I97: 1791141 | J97: No | K97: =IF(E97="","",($B$4-E97)/365.25) -> 3.6960986 | L97: =IF(K97="","no date",IF(K97<1,"0-1 yrs",IF(K97<2,"1-2 yrs",IF(K97<3,"2-3 yrs",IF(K97<5,"3-5 yrs","5+ yrs"))))) -> 3-5 yrs | M97: No | N97: =IF(M97="Yes","Memo flag - not ours / unknown / hold: resolve",IF(OR(COUNTIF(Summary!$C$4:$L$4,H97)>0,AND(A97="Philly",COUNTIF(Summary!$C$5:$L$5,H97)>0),AND(A97="TUR",COUNTIF(Summary!$C$6:$L$6,H97)>0)),"Fee amount - presumed company revenue",IF(H97<=Summary!$B$7,"Small amount - likely fee, review","Larger amount - likely includes agent commission"))) -> Small amount - likely fee, review | O97: =IFERROR(INDEX('State Rules'!$C$5:$C$11,MATCH($B97,'State Rules'!$A$5:$A$11,0)),"") -> 1 | P97: =IF(OR(O97="",E97=""),"",EDATE(E97,12*O97)) -> 45316 | Q97: =IF(E97="","",IFERROR(EDATE(E97,12*INDEX('State Rules'!$E$5:$E$11,MATCH($B97,'State Rules'!$A$5:$A$11,0))),"")) -> 46047 | R97: =IF(P97="","",IFERROR(IF(P97<=INDEX('State Rules'!$I$5:$I$11,MATCH($B97,'State Rules'!$A$5:$A$11,0)),"Yes","No"),"")) -> Yes | S97: =IF(Q97="","",IFERROR(IF(Q97<=INDEX('State Rules'!$I$5:$I$11,MATCH($B97,'State Rules'!$A$5:$A$11,0)),"Yes","No"),"")) -> Yes | Z97: =IF(Q97="","",IF(Q97<=$B$4,N(W97)+N(X97),0)) -> 0 | AA97: =IF(OR(LEFT(N97,6)="Larger",LEFT(N97,4)="Memo"),H97,0) -> 0
A98: TUR | B98: =IFERROR(INDEX(Summary!$B$10:$B$17,MATCH($A98,Summary!$A$10:$A$17,0)),"") -> TX | C98: TUR | D98: 23 | E98: 45049 | F98: 43756 | G98: WPG National Title | H98: 544 | I98: 23-121431 | J98: No | K98: =IF(E98="","",($B$4-E98)/365.25) -> 3.4277892 | L98: =IF(K98="","no date",IF(K98<1,"0-1 yrs",IF(K98<2,"1-2 yrs",IF(K98<3,"2-3 yrs",IF(K98<5,"3-5 yrs","5+ yrs"))))) -> 3-5 yrs | M98: No | N98: =IF(M98="Yes","Memo flag - not ours / unknown / hold: resolve",IF(OR(COUNTIF(Summary!$C$4:$L$4,H98)>0,AND(A98="Philly",COUNTIF(Summary!$C$5:$L$5,H98)>0),AND(A98="TUR",COUNTIF(Summary!$C$6:$L$6,H98)>0)),"Fee amount - presumed company revenue",IF(H98<=Summary!$B$7,"Small amount - likely fee, review","Larger amount - likely includes agent commission"))) -> Larger amount - likely includes agent commission | O98: =IFERROR(INDEX('State Rules'!$C$5:$C$11,MATCH($B98,'State Rules'!$A$5:$A$11,0)),"") -> 1 | P98: =IF(OR(O98="",E98=""),"",EDATE(E98,12*O98)) -> 45415 | Q98: =IF(E98="","",IFERROR(EDATE(E98,12*INDEX('State Rules'!$E$5:$E$11,MATCH($B98,'State Rules'!$A$5:$A$11,0))),"")) -> 46145 | R98: =IF(P98="","",IFERROR(IF(P98<=INDEX('State Rules'!$I$5:$I$11,MATCH($B98,'State Rules'!$A$5:$A$11,0)),"Yes","No"),"")) -> Yes | S98: =IF(Q98="","",IFERROR(IF(Q98<=INDEX('State Rules'!$I$5:$I$11,MATCH($B98,'State Rules'!$A$5:$A$11,0)),"Yes","No"),"")) -> Yes | Z98: =IF(Q98="","",IF(Q98<=$B$4,N(W98)+N(X98),0)) -> 0 | AA98: =IF(OR(LEFT(N98,6)="Larger",LEFT(N98,4)="Memo"),H98,0) -> 544
A99: TUR | B99: =IFERROR(INDEX(Summary!$B$10:$B$17,MATCH($A99,Summary!$A$10:$A$17,0)),"") -> TX | C99: TUR | D99: 24 | E99: 45093 | F99: 10458 | G99: Partners Title Company | H99: 250 | I99: Order # WL-7199 | J99: No | K99: =IF(E99="","",($B$4-E99)/365.25) -> 3.3073238 | L99: =IF(K99="","no date",IF(K99<1,"0-1 yrs",IF(K99<2,"1-2 yrs",IF(K99<3,"2-3 yrs",IF(K99<5,"3-5 yrs","5+ yrs"))))) -> 3-5 yrs | M99: No | N99: =IF(M99="Yes","Memo flag - not ours / unknown / hold: resolve",IF(OR(COUNTIF(Summary!$C$4:$L$4,H99)>0,AND(A99="Philly",COUNTIF(Summary!$C$5:$L$5,H99)>0),AND(A99="TUR",COUNTIF(Summary!$C$6:$L$6,H99)>0)),"Fee amount - presumed company revenue",IF(H99<=Summary!$B$7,"Small amount - likely fee, review","Larger amount - likely includes agent commission"))) -> Fee amount - presumed company revenue | O99: =IFERROR(INDEX('State Rules'!$C$5:$C$11,MATCH($B99,'State Rules'!$A$5:$A$11,0)),"") -> 1 | P99: =IF(OR(O99="",E99=""),"",EDATE(E99,12*O99)) -> 45459 | Q99: =IF(E99="","",IFERROR(EDATE(E99,12*INDEX('State Rules'!$E$5:$E$11,MATCH($B99,'State Rules'!$A$5:$A$11,0))),"")) -> 46189 | R99: =IF(P99="","",IFERROR(IF(P99<=INDEX('State Rules'!$I$5:$I$11,MATCH($B99,'State Rules'!$A$5:$A$11,0)),"Yes","No"),"")) -> Yes | S99: =IF(Q99="","",IFERROR(IF(Q99<=INDEX('State Rules'!$I$5:$I$11,MATCH($B99,'State Rules'!$A$5:$A$11,0)),"Yes","No"),"")) -> Yes | Z99: =IF(Q99="","",IF(Q99<=$B$4,N(W99)+N(X99),0)) -> 0 | AA99: =IF(OR(LEFT(N99,6)="Larger",LEFT(N99,4)="Memo"),H99,0) -> 0
A100: TUR | B100: =IFERROR(INDEX(Summary!$B$10:$B$17,MATCH($A100,Summary!$A$10:$A$17,0)),"") -> TX | C100: TUR | D100: 25 | E100: 45093 | F100: 518005123 | H100: 644 | I100: ? Couldn't locate | J100: No | K100: =IF(E100="","",($B$4-E100)/365.25) -> 3.3073238 | L100: =IF(K100="","no date",IF(K100<1,"0-1 yrs",IF(K100<2,"1-2 yrs",IF(K100<3,"2-3 yrs",IF(K100<5,"3-5 yrs","5+ yrs"))))) -> 3-5 yrs | M100: Yes | N100: =IF(M100="Yes","Memo flag - not ours / unknown / hold: resolve",IF(OR(COUNTIF(Summary!$C$4:$L$4,H100)>0,AND(A100="Philly",COUNTIF(Summary!$C$5:$L$5,H100)>0),AND(A100="TUR",COUNTIF(Summary!$C$6:$L$6,H100)>0)),"Fee amount - presumed company revenue",IF(H100<=Summary!$B$7,"Small amount - likely fee, review","Larger amount - likely includes agent commission"))) -> Memo flag - not ours / unknown / hold: resolve | O100: =IFERROR(INDEX('State Rules'!$C$5:$C$11,MATCH($B100,'State Rules'!$A$5:$A$11,0)),"") -> 1 | P100: =IF(OR(O100="",E100=""),"",EDATE(E100,12*O100)) -> 45459 | Q100: =IF(E100="","",IFERROR(EDATE(E100,12*INDEX('State Rules'!$E$5:$E$11,MATCH($B100,'State Rules'!$A$5:$A$11,0))),"")) -> 46189 | R100: =IF(P100="","",IFERROR(IF(P100<=INDEX('State Rules'!$I$5:$I$11,MATCH($B100,'State Rules'!$A$5:$A$11,0)),"Yes","No"),"")) -> Yes | S100: =IF(Q100="","",IFERROR(IF(Q100<=INDEX('State Rules'!$I$5:$I$11,MATCH($B100,'State Rules'!$A$5:$A$11,0)),"Yes","No"),"")) -> Yes | Z100: =IF(Q100="","",IF(Q100<=$B$4,N(W100)+N(X100),0)) -> 0 | AA100: =IF(OR(LEFT(N100,6)="Larger",LEFT(N100,4)="Memo"),H100,0) -> 644
A101: TUR | B101: =IFERROR(INDEX(Summary!$B$10:$B$17,MATCH($A101,Summary!$A$10:$A$17,0)),"") -> TX | C101: TUR | D101: 26 | E101: 45133 | F101: 526070032 | G101: Alamo Title Company | H101: 150 | J101: No | K101: =IF(E101="","",($B$4-E101)/365.25) -> 3.1978097 | L101: =IF(K101="","no date",IF(K101<1,"0-1 yrs",IF(K101<2,"1-2 yrs",IF(K101<3,"2-3 yrs",IF(K101<5,"3-5 yrs","5+ yrs"))))) -> 3-5 yrs | M101: No | N101: =IF(M101="Yes","Memo flag - not ours / unknown / hold: resolve",IF(OR(COUNTIF(Summary!$C$4:$L$4,H101)>0,AND(A101="Philly",COUNTIF(Summary!$C$5:$L$5,H101)>0),AND(A101="TUR",COUNTIF(Summary!$C$6:$L$6,H101)>0)),"Fee amount - presumed company revenue",IF(H101<=Summary!$B$7,"Small amount - likely fee, review","Larger amount - likely includes agent commission"))) -> Fee amount - presumed company revenue | O101: =IFERROR(INDEX('State Rules'!$C$5:$C$11,MATCH($B101,'State Rules'!$A$5:$A$11,0)),"") -> 1 | P101: =IF(OR(O101="",E101=""),"",EDATE(E101,12*O101)) -> 45499 | Q101: =IF(E101="","",IFERROR(EDATE(E101,12*INDEX('State Rules'!$E$5:$E$11,MATCH($B101,'State Rules'!$A$5:$A$11,0))),"")) -> 46229 | R101: =IF(P101="","",IFERROR(IF(P101<=INDEX('State Rules'!$I$5:$I$11,MATCH($B101,'State Rules'!$A$5:$A$11,0)),"Yes","No"),"")) -> Yes | S101: =IF(Q101="","",IFERROR(IF(Q101<=INDEX('State Rules'!$I$5:$I$11,MATCH($B101,'State Rules'!$A$5:$A$11,0)),"Yes","No"),"")) -> Yes | Z101: =IF(Q101="","",IF(Q101<=$B$4,N(W101)+N(X101),0)) -> 0 | AA101: =IF(OR(LEFT(N101,6)="Larger",LEFT(N101,4)="Memo"),H101,0) -> 0
...

Sheet Current Month
A1: Current-month unbooked deposits ('Deposited checks' block, no 'x' in Sage column) - all September/October 2026
A2: Listed only so the Summary ties to the cash-requirements workbook. These are in the normal matching cycle and are not an unclaimed-property concern today.
A4: Entity | B4: Bank / block | C4: Source row | D4: Deposit date | E4: Check # | F4: Amount
A5: Dallas | B5: Dallas | C5: 111 | D5: 46281 | E5: 6423804118 | F5: 124
A6: Dallas | B6: Dallas | C6: 137 | D6: 46286 | E6: 934707304 | F6: 625
A7: Dallas | B7: Dallas | C7: 143 | D7: 46286 | E7: 934659478 | F7: 748.5
A8: Dallas | B8: Dallas | C8: 155 | D8: 46286 | E8: 8510735044 | F8: 2599
A9: Dallas | B9: Dallas | C9: 165 | D9: 46288 | E9: 2263 | F9: 500
A10: Dallas | B10: Dallas | C10: 172 | D10: 46289 | E10: 7255 | F10: 2300
A11: Dallas | B11: Dallas | C11: 220 | D11: 46297 | E11: 1321 | F11: 644
A12: Dallas | B12: Dallas | C12: 229 | D12: 46300 | E12: 8737 | F12: 644
A13: Dallas | B13: Dallas | C13: 230 | D13: 46300 | E13: 35245 | F13: 644
A14: Dallas | B14: Dallas | C14: 231 | D14: 46300 | E14: 37957 | F14: 644
A15: Dallas | B15: Dallas | C15: 232 | D15: 46300 | E15: 1007121877 | F15: 644
A16: Dallas | B16: Dallas | C16: 233 | D16: 46300 | E16: 1067 | F16: 780
... A21: Chicago | B21: CapOne | C21: 57 | D21: 46300 | E21: 1573 | F21: 700
A22: Chicago | B22: Chase | C22: 38 | D22: 46296 | F22: 250
A23: Chicago | B23: Chase | C23: 39 | D23: 46300 | F23: 12995
A24: Houston | B24: Houston | C24: 85 | D24: 46286 | E24: 2562 | F24: 1175
A25: Houston | B25: Houston | C25: 100 | D25: 46293 | E25: 237769268 | F25: 178.6
A26: Houston | B26: Houston | C26: 102 | D26: 46293 | E26: 6043577 | F26: 295
A27: Houston | B27: Houston | C27: 109 | D27: 46294 | E27: 4227 | F27: 250
A28: Houston | B28: Houston | C28: 119 | D28: 46297 | E28: 1048 | F28: 1950
A29: Houston | B29: Houston | C29: 121 | D29: 46300 | E29: 5041036114 | F29: 40
A30: Houston | B30: Houston | C30: 122 | D30: 46300 | E30: 48438 | F30: 644
A31: Houston | B31: Houston | C31: 123 | D31: 46300 | E31: 550058834 | F31: 644
A32: Houston | B32: Houston | C32: 124 | D32: 46300 | E32: 664 | F32: 1194.5
A33: Houston | B33: Houston | C33: 125 | D33: 46300 | E33: 860570 | F33: 1750
A34: Houston | B34: Houston | C34: 126 | D34: 46300 | E34: 7227004805 | F34: 1950.83
A35: Philly | B35: CapOne | C35: 40 | D35: 46281 | E35: 52556 | F35: 35
... A54: TUR | B54: TUR | C54: 116 | D54: 46300 | E54: 179 | F54: 1835
A55: Leading Edge | B55: Regions | C55: 25 | D55: 46269 | F55: 2370
A56: Leading Edge | B56: Regions | C56: 55 | D56: 46281 | F56: 900
A57: Leading Edge | B57: Regions | C57: 92 | D57: 46297 | F57: 3000
A58: Leading Edge | B58: Regions | C58: 93 | D58: 46300 | F58: 6372.5
A59: Leading Edge | B59: Regions | C59: 94 | D59: 46300 | F59: 7650
A60: Leading Edge | B60: Regions | C60: 95 | D60: 46300 | F60: 8100
A61: Leading Edge | B61: Cadence 0264 | C61: 34 | D61: 46283 | F61: 3000
A62: TOTAL | F62: =SUM(F5:F61) -> 144542

Sheet Gaps & Next Steps
A1: What is missing, and what to do next
A3: # | B3: Item | C3: Why it matters | D3: Who / where
A4: 1 | B4: DATA GAP: the fee vs. agent split of every check is unknown | C4: The source workbook has E&O / FEE / Commission columns but they are empty for all 181 items. Per the user, fee checks are typically $644, $1,044, $69 or other small amounts, so items at those amounts are presumed company revenue and items at or under the small-amount threshold are treated as likely fees. Larger checks likely include an agent's commission split, but how much of each is the agent's is still unknown; only that share (plus anything owed back to a payer) can ever be unclaimed property. Until the split is known, every dollar figure on the Summary is an upper bound, not an amount to remit. | D4: Match each check to its Paperless Pipeline transaction; fill Detail cols U-W.
A5: 2 | B5: DATA GAP: owner identity and last-known address | C5: The first priority rule sends property to the state of the owner's last-known address. User confirmed that for many older checks the agent is not known. Where the agent can be identified, record the name and state in Detail cols T-U. Where it cannot, the item falls to the second priority rule (state of formation of the LLC). | D5: Agent master file / Paperless Pipeline; fill Detail cols T-U.
A6: 3 | B6: DATA GAP: state of formation for each LLC | C6: User confirmed each office is an LLC but not where each was formed. This decides where every unknown-agent item is reported and which state's voluntary disclosure program to approach. 'Corporate HQ in Kansas City' is not the test. | D6: Legal / entity org chart.
A7: 4 | B7: RESOLVED: entity-to-state mapping | C7: User confirmed 10/6/2026: Dallas, Houston, TUR = Texas; Chicago = Illinois; Philly = Pennsylvania; Leading Edge = Alabama; Gallery = Florida. | D7: Done.
A8: 5 | B8: CONFIRM: payable date vs. deposit date | C8: Dormancy runs from when the amount became payable to the owner, not from when the check was deposited. Deposit date is used as a proxy throughout. If agents are paid on closing, the closing date is the better trigger and could be earlier. | D8: Paperless Pipeline closing dates.
A9: 6 | B9: RESOLVED: agents are independent contractors | C9: User confirmed 10/6/2026. Texas' 1-year rule applies to 'wages' as defined in Labor Code 61.001, which excludes independent contractors, so the 3-year general rule is the likely Texas test. Illinois and Alabama reach 'other compensation for personal services' and Pennsylvania lists commissions, so their shorter periods likely apply. Florida's wage rule is not shown to reach contractors, so 5 years is likely. Counsel should confirm each. | D9: Confirm with counsel.
A10: 7 | B10: RESOLVED: no prior write-offs | C10: User confirmed nothing has been done with the unapplied deposits so far, so the population in this workbook is the full population and there is no prior 'private escheat' to unwind. | D10: Done.
A11: 8 | B11: ICA CLAUSES THAT REDUCE WHAT IS OWED TO AGENTS - legal question | C11: Every ICA lets the Broker hold or apply commissions against amounts the agent owes (dues, fees, E&O deductibles, indemnity) and conditions post-termination payouts on dues being paid in full. The Philly ICA goes further: an incomplete file 30 days past closing is paid 50/50 and 60 days past closing is 'forfeited'; a license not reactivated within 30 days means 'brokerage will keep 100% of commission'. TUR's agreement forfeits accrued commissions if the agent collects in their own name or breaches Section 5. A documented offset reduces the agent's share dollar for dollar. A contractual forfeiture is less certain: Alabama's act (and, per secondary sources, most states' acts) says a contractual limitation on the owner's right does not prevent property from being presumed abandoned. Whether Texas, Pennsylvania, Illinois or Florida would honor these clauses against an escheat claim is for counsel. Do not treat a forfeiture as the company's money until counsel says so AND the triggering facts (closing date, file status at day 60, termination date) are documented per item. See the ICA Terms tab. | D11: Counsel; Accounting to document per item.
A12: 9 | B12: WHEN THE AGENT'S SHARE BECOMES PAYABLE (dormancy trigger) | C12: Houston's TXR-2301 form is explicit: the associate's fee is payable when Broker receives Broker's fees (para. 16.C), so the deposit date is the trigger for Houston. Dallas, Chicago and Philly ICAs pay 'promptly after receipt and processing' but 'provided that Broker has received a complete File'. A condition that depends on the agent or the broker completing paperwork probably does not defer dormancy under anti-limitation provisions, but it is an argument counsel may want to assess. TUR agents are normally paid by the title company at closing; TUR's deposited checks are usually the broker's portion, lease or new-home commissions, so TUR's larger items need the Disbursement Authorization form to find the agent share. | D12: Counsel; Accounting.
A13: 10 | B13: DATA: the split exists on the file | C13: TUR's Disbursement Authorization form records TUR / Agent / Mentor amounts per transaction. Dallas, Chicago and Philly fees are on the Closing Disclosure. Pull these for each larger item to fill Detail cols V-X; that converts the upper-bound figures into the real reportable amount. | D13: Accounting / Paperless Pipeline.
A14: 11 | B14: NOT PROVIDED: Houston fee schedule | C14: The Houston agreement incorporates an attached fee schedule that was not in the copy provided; the $49 E&O and $65 monthly are stated in the body. Houston's $644 items imply the same $595+$49 structure, but confirm. | D14: User.
A15: 12 | B15: ACTION: work the oldest items first | C15: Houston has four items from 2022 and Dallas/TUR/Philly have 2023 items. Under the Texas 3-year test, every Texas item deposited before 3/1/2023 would already have been due on the July 1, 2026 report if it was owed to someone else; the Detail tab's 'Dormant date - LONG' column identifies them. | D15: Accounting.
... A20: 17 | B20: NOT VERIFIED in this session | C20: Statute and state-treasury web pages were blocked by this session's network policy, so every rule on the State Rules tab rests on search-engine summaries of those pages and on secondary sources (Sovos, UPPO, law-firm alerts). Specific items I could not confirm: Illinois business-holder report deadline; PA December 31 cutoff and VDA terms; FL and AL due-diligence thresholds; MO VDA. Treat the State Rules tab as a starting point for counsel, not a filing position. | D20: Counsel / unclaimed-property advisor.

Sheet ICA Terms
A1: Independent Contractor Agreement terms relevant to accrued commissions and unclaimed property
A2: Five agreements provided 10/6/2026. Quotations are from the documents; 'relevance' is analysis, not legal advice. Dallas and Chicago PDFs are scans and were read visually; the other three were text-extracted.
A4: Entity | B4: Legal entity named in the document | C4: Document | D4: Clause / location | E4: What it says | F4: Relevance to accrued commissions / unclaimed property
A5: Dallas | B5: URE Dallas LLC dba United Real Estate (Nick Bristow, General Manager, Broker) | C5: Independent Contractor Agreement for Dallas/Frisco, DocuSign CBD8CDF3..., revised 4/18/2023 | D5: Commissions and Fees (p.2) | E5: Commissions, compensation, bonuses and fees are paid to Broker. Contractor Commissions 'will be promptly paid to by Broker after receipt & processing of such Commissions, less any amounts owed to Broker, & provided that Broker has received a complete File.' | F5: Agent's share arises on receipt, net of amounts the agent owes, conditioned on a complete file. Supports using deposit date as the dormancy trigger; the complete-file condition is a counsel question (see Gaps).
A6: Dallas | C6: same | D6: Broker Fees (p.3) | E6: $595 transaction fee per side for residential sales up to $649,999; $995 at $650,000 and above; commercial 10%; other events 12% (min $75, max $995 per side); Broker-generated lead fee 40%; E&O Fee $49 per transaction; 'All sales related fees due Broker must be included on the transaction's Closing Disclosure or HUD-1 Statement & paid through the close of escrow.' Monthly $65 + $4 convenience fee by credit card. Annual cap: after 24 transactions, $50 fee + E&O per transaction. | F6: Confirms $644 = $595 + $49 and $1,044 = $995 + $49 arrive from title as company fee revenue, and $69 = monthly dues. These checks are the company's money, not unclaimed property.
A7: Dallas | C7: same | D7: Errors & Omissions Insurance (p.4) | E7: Broker may withhold from Contractor's commissions payable an amount adequate to satisfy uncovered claims, placed in a Claims and Disputes Retention Account pending settlement. | F7: A documented withholding for a claim is a legitimate reduction of the agent's share; keep the claim file.
A8: Dallas | C8: same | D8: Protection of Contractor's Listings and Contracts; Transaction Defined; Termination (p.10) | E8: Commissions earned and paid on sales contracts completed before termination 'will be disbursed to Contractor in compliance with the commission plan in effect... conditioned on Contractor having any and all dues, fees and expenses owing to Broker paid in full.' 'Broker has the right to hold and/or apply any commissions owing to Contractor, as may be necessary to pay for or secure any obligations of Contractor.' Transactions not closed before termination are paid at a 70/30 split. | F8: Offset rights: amounts an agent owes the company reduce the agent's reportable share dollar for dollar if documented. No clause forfeits earned commissions outright.
A9: Dallas | C9: same | D9: Contractor Information (p.10); Agent Information sheet (p.1); Controlling Law (p.11) | E9: Contractor must immediately update mailing address, phone and email. The Agent Information sheet collects home address, state and zip. Controlling law: Texas. | F9: The company should hold a last-known address for every identified agent, which puts those items under the first priority rule (agent's address state, usually Texas).
A10: Chicago | B10: URE Chicago LLC dba United Real Estate - Chicago (Richard Williams, Designated Managing Broker) | C10: Independent Contractor Agreement, DocuSign A769C223... | D10: Commissions and Fees; Broker Fees (pp.2-3) | E10: Same commission language as Dallas (promptly paid after receipt and processing, less amounts owed, provided Broker has a complete File). Fees: $595 per side up to $650,000; $995 at $650,001+; commercial greater of 12% or $595; other events 12% (min $75, max $995); lead fee 40%; E&O $49 per side; monthly $69; annual cap after 24 transactions. | F10: Same fee structure as Dallas: $644 / $1,044 / $69 are company revenue.
A11: Chicago | C11: same | D11: E&O; Protection of Listings; Transaction Defined; Termination; Controlling Law (pp.4, 9-11) | E11: Same E&O withholding, dues-paid-in-full condition and hold/apply rights as Dallas. No 70/30 post-termination line. Contractor must update mailing address. Controlling law: Texas. | F11: Offset rights as Dallas. The Texas choice-of-law clause does not change which state takes custody of unclaimed property; the priority rules do.
A12: Houston | B12: URE Houston LLC d/b/a United Real Estate (Carol Drake, Managing Broker) | C12: Texas REALTORS form TXR-2301 (07-08-22), DocuSign 3DE311AB... | D12: Para. 12.B Receipt of Brokerage Fees | E12: Associate must deliver any compensation for brokerage services received from any client, escrow agent, title company or other person to Broker for disbursement in accordance with the agreement. | F12: All commission checks flow through the Broker, which is why they land in the deposited-checks block.
A13: Houston | C13: same | D13: Para. 16.A and 16.C Associate's Fees | E13: 'All fees and compensation that Broker or Associate earn for providing brokerage services... are payable to and belong to Broker.' 'Associate's fees under this agreement are earned at the time Broker's fees are earned... Associate's fees under this agreement are payable when Broker receives Broker's fees under the applicable agreements for brokerage services, unless the fees are subject to arbitration, litigation, or a court order.' | F13: Clearest trigger in the five documents: the agent's share is PAYABLE WHEN THE BROKER RECEIVES THE CHECK. For Houston the deposit date is the dormancy start date with little room for argument.
A14: Houston | C14: same | D14: Para. 16.D Disputes; Para. 17.B Special Expenses | E14: Disputed fees between associates are held in trust pending resolution. Special expenses: $65 monthly fee by auto-debit; each transaction carries a $49 E&O charge plus a transaction fee per the attached fee schedule, deducted from gross fees before calculating Associate's fees. | F14: Fee schedule itself was not in the copy provided. The $49 E&O and the $644 items imply the same $595 + $49 pattern as Dallas; confirm.
A15: Houston | C15: same | D15: Para. 21 Termination; Para. 24.E Controlling Law; signature block | E15: Either party may terminate on written notice. Any fee unpaid at termination is paid per the fee schedule. No forfeiture clause. Controlling law: Texas. Signature block collects the associate's home address. | F15: Termination does not extinguish the agent's right to unpaid fees. Last-known address should be on file.
A16: TUR | B16: Quick-Close Properties, LLC dba Texas United Realty (TREC license 599460) | C16: TUR Legacy Sign Up Docs v1 (TREC sponsorship form, Agent Agreement, Commission Policy, Policies, DA Checklist, Disbursement Authorization form) | D16: Policies item 11 Commission Payment | E16: 'Licensee acknowledges he/she will be paid at closing and funding from the title company for all commissions earned except... 1) Lease commissions are paid through the broker directly to the licensee three business days after broker has received and deposited the commission check. 2) New Home commissions... three business days after received and deposited, broker will cut agent's check.' | F16: TUR agents are normally paid by title at closing, so checks TUR deposits are usually the broker's portion, a lease commission or a new-home commission. For lease and new-home items the agent's share is payable three business days after deposit, which fixes the dormancy trigger.
A17: TUR | C17: same | D17: Commission Policy of Texas United Realty | E17: Plan 1 New Agent Mentorship: 70% split. Plan 2 Agent Coaching: 85% split less transaction fee. Plan 3 Transaction Fee Plan: $150 (sale up to $10K commission), $250 (up to $20K), $350 (up to $30K), $450 (up to $40K), $60 residential lease. All plans $179 annual fee. Commercial 70/30 or 95/5. | F17: Explains TUR's recurring $150 / $250 / $60 deposits as fee checks and gives the split to apply to larger items once the plan on the DA form is known.
A18: TUR | C18: same | D18: Disbursement Authorization form | E18: Per-transaction form showing total commission and the amounts to Texas United Realty, Agent and Mentor, approved by Broker/Owner, with a request that title mail the HUD and broker's portion to TUR. | F18: The agent/company split for every TUR transaction is on this form. Pull it for each larger item to replace the upper-bound figures.
A19: TUR | C19: same | D19: Agent Agreement paras. 1.K, 3.B, 5.F, 8.C | E19: 1.K: an agent who collects a fee in their own name 'will forfeit any accrued but uncollected commissions'. 3.B: agent assigns commissions to TUR to secure indemnification. 5.F: breach of Section 5 (confidentiality / non-solicitation) means the agent 'shall lose all rights to any further commissions'. 8.C: amounts owed at or after termination may be deducted from commissions due. | F19: Offset (8.C, 3.B) is a documented reduction. Forfeiture (1.K, 5.F) is a legal question: anti-limitation provisions in unclaimed property acts may override a contractual forfeiture. Do not rely on it without counsel and a documented breach.
A20: TUR | C20: same | D20: Policies item 6 Record Keeping | E20: All transaction documentation kept for four years from closing or termination of contract. | F20: Four years is shorter than unclaimed property record-retention expectations (commonly 10 years after a report) and audit look-backs. Preserve DA forms and HUDs for the aged items regardless.
A21: Philly | B21: 'United Real Estate' (no LLC name in the document); Pennsylvania Real Estate Commission licensee | C21: Independent Contractor Agreement, Updated 08.2023, 11 pages | D21: Para. 3 Commissions and Fees | E21: '100% of any and all such commissions will be promptly paid to Contractor by Broker after receipt and processing, less any amounts owing to Broker. Payment of any and all commissions is subject to Broker receiving a complete sales file no less than five (5) business days prior to closing.' | F21: Agent's share arises on receipt net of amounts owed; complete-file condition as Dallas.
A22: Philly | C22: same | D22: Para. 3 fee schedule | E22: $595 transaction fee per side for sales up to $799,999.99; $995 at $800,000+; 'charged to the Buyer or Seller and paid to Broker'; agent responsible if the buyer/seller does not pay. E&O $49 per transaction; enhanced E&O $110 on personal transactions. Leases 12% (min $125, or $595/$995 whichever is less) + $49. Referrals 10% (min $100) + $49. Commercial 10% + $49. Monthly $65 + $4 card fee, $25 late fee. Lead fee 25-50%; mentor fee 30% on first four transactions. 'All fees due Broker must be included on the transaction's HUD-1/ALTA/Closing Disclosure statement and paid through the close of escrow.' | F22: Confirms fee checks arrive from settlement. User adds $495 and $295 as Philly fee amounts (not in this 08.2023 schedule; presumably an earlier schedule).
A23: Philly | C23: same | D23: Para. 21 Protection of Listings; Para. 22 Transaction Defined; Para. 23 Termination | E23: Post-termination commissions disbursed per the plan in effect, 'conditioned on Contractor having any and all dues, fees and expenses owing to Broker paid in full.' Broker may 'hold and/or apply any commissions owing to Contractor' to secure obligations. On termination, executed contracts split 70/30. 'If the Contractor's license expires or goes inactive, anything that is currently under contract brokerage split will be fifty/fifty. Contractor will have 30 days to bring their license back to active status. If Contractor fails to bring license back to active status within the 30 days, brokerage will keep 100% of commission.' | F23: Offset rights as elsewhere, plus an express 100% retention clause for lapsed licenses. Whether Pennsylvania unclaimed property law honors a contractual retention against an escheat claim is for counsel.
A24: Philly | C24: same | D24: Para. 31 Fines and Penalties | E24: '3. Any incomplete file(s) 30 days past closing will be paid at a 50/50 split. 4. Any incomplete file(s) 60 days past closing will be forfeited and grounds for termination.' | F24: The most consequential clause for Philly's aged items: if a file was never completed, the ICA says the agent's share was forfeited at day 60 after closing. If counsel concludes Pennsylvania (or the agent's address state) honors this, those amounts are company revenue, not unclaimed property. Document the closing date and file status for each item before relying on it; anti-limitation provisions may override.
A25: Philly | C25: same | D25: Para. 26 Contractor Information; Para. 28 Controlling Law; Para. 30 Paperless Pipeline | E25: Contractor must update mailing address. Controlling law: Pennsylvania. All documents must be uploaded to Paperless Pipeline within 72 hours. | F25: Last-known address should be on file. Paperless Pipeline should show whether each aged file was ever completed.

Sheet Method
A1: Method
A3: 1. Source file: United_Cash_Requirements.xlsx as provided on 10/6/2026 (file name f519c0da-United_Cash_Requirements.xlsx).
A4: 2. For each entity tab, the 'Previous Month's Accrued Commissions' block was read (Dallas M20:R143, Chicago R20:V190, Houston M20:R286, Philly S21:W133, DC R22:V194, TUR M21:R299, Leading Edge AA22:AE195 and AG22:AK195, Gallery M21:R299). Rows without an 'x' in the 'accounted for in Sage' column are the unbooked items that make up the accrued balance.
A5: 3. Each entity's extracted unbooked total was tied to the tab's 'outstanding amount' cell (Dallas M18 = 59,991.62; Houston M18 = 76,889.50; Philly S19 = 29,708.78; TUR M19 = 55,528.45; Leading Edge AA20 = 250.00 and AG20 = 395.00; Gallery M19 = 4,001.11; Chicago R18 = 0; DC R20 = 0). All tie exactly.
A6: 4. The current-month 'Deposited checks' blocks were read the same way and tie to each tab's A18/A19 (and the second-bank cells) and to the source Summary row 5.
A7: 5. URE Corp carries no accrued commissions (A4 = -O58 where O58 is empty).
A8: 6. Ages are computed from the deposit date to the as-of date. Dormant dates = deposit date + the state period in months (EDATE).
A9: 7. Classification hints are heuristics on amount and memo text only; they are not conclusions.
A10: 8. State rules were researched by web search on 10/6/2026. Primary statute pages could not be opened from this session; see the State Rules tab 'Verification status' column for what is and is not confirmed.
A11: 9. Five independent contractor agreements were provided 10/6/2026 (Dallas/Frisco, Chicago, Houston TXR-2301, TUR legacy sign-up docs, Pennsylvania ICA). Fee amounts in Summary rows 4-6 come from the user and from those fee schedules; the ICA Terms tab cites each clause used.

Sheet State Rules
A1: Unclaimed property rules by state - dormancy periods applied in this analysis
A2: Short period = the period for wages / compensation for personal services. Long period = the general catch-all period. Which one applies to independent-contractor agent commissions is a legal question that differs by state (see basis columns). Verification column says what could and could not be confirmed from primary sources in this session.
A4: State | B4: Name | C4: Short period (yrs) | D4: Short period basis | E4: Long period (yrs) | F4: Long period basis | G4: Report due | H4: Report cutoff ('as of') | I4: Next cutoff date | J4: Due diligence to owner | K4: Voluntary disclosure / penalties | L4: Verification status | M4: Likely test for independent-contractor commissions (SHORT/LONG) | N4: Why | O4: Sources
A5: TX | B5: Texas | C5: 1 | D5: Unclaimed 'wages' - Tex. Prop. Code 72.1015 (1 year). 'Wages' takes its meaning from Labor Code 61.001, which covers compensation owed by an EMPLOYER to an EMPLOYEE and excludes independent contractors. Independent-contractor agent commissions therefore likely fall under the general rule, not the 1-year rule - confirm with counsel / Comptroller. | E5: 3 | F5: General personal property - Tex. Prop. Code 72.101(a): presumed abandoned after more than 3 years with owner location unknown and no claim/act of ownership. | G5: July 1 (Tex. Prop. Code 74.101) | H5: March 1 (property held on March 1 is reported the following July 1) | I5: 46447 | J5: Notice to owner by mail/e-mail at least 60 days before delivery for property over $250 (Tex. Prop. Code 74.1011). | K5: Comptroller offers a Voluntary Disclosure Agreement with waiver of penalty and interest; not available once an investigation has started or (per secondary sources) to holders who have filed Texas reports before. | L5: Dormancy periods, report date, and due-diligence rule confirmed from search summaries of the statute text; statute pages themselves were blocked by this session's network policy. No business-to-business exemption was found for Texas. | M5: LONG | N5: Agents are independent contractors (confirmed by user). Texas' 1-year rule covers 'wages' as defined in Labor Code 61.001, which is limited to employer-to-employee compensation and expressly excludes independent contractors. The 3-year general rule is therefore the likely test. Confirm with counsel; some advisors report commissions under NAUPA code MS02 conservatively on the shorter period. | O5: https://statutes.capitol.texas.gov/docs/PR/htm/PR.72.htm ; https://statutes.capitol.texas.gov/Docs/PR/htm/PR.74.htm ; https://texas.public.law/statutes/tex._prop._code_section_72.1015 ; https://texas.public.law/statutes/tex._labor_code_section_61.001 ; https://www.comptroller.texas.gov/taxes/publications/96-576.php
A6: IL | B6: Illinois | C6: 1 | D6: 765 ILCS 1026/15-201: 'wages, commissions, bonuses, or reimbursements to which an employee is entitled, or other compensation for personal services' - 1 year after payable. The 'other compensation for personal services' language is broader than Texas and plausibly reaches independent-contractor commissions. | E6: 3 | F6: 765 ILCS 1026/15-201 catch-all: all other property 3 years after the obligation to pay arises (per secondary sources). | G6: November 1 for financial, insurance and government holders (confirmed). Deadline for ordinary business holders NOT confirmed from the statute in this session - the prior Illinois act used May 1 with a December 31 cutoff. CONFIRM. | H6: June 30 for the November 1 filers; business-holder cutoff NOT confirmed. | I6: 46568 | J6: Due-diligence letter by first-class mail for property over $50, sent 60 to 365 days before the report (per Illinois Treasurer guidance summary). | K6: Not researched in this session. | L6: Illinois eliminated its business-to-business exemption when it adopted RUUPA (effective 1/1/2018). Chicago's prior-month accrued balance is $0, so Illinois exposure today is only the current-month unbooked deposits. | M6: SHORT | N6: Illinois' 1-year rule reaches 'other compensation for personal services', not only employee wages, so independent-contractor commissions plausibly fall under it. 3-year general rule is the fallback. | O6: https://www.ilga.gov/legislation/ilcs/documents/076510260K15-201.htm ; https://icash.illinoistreasurer.gov/app/faq ; https://www.duanemorris.com/articles/illinois_slides_backward_unclaimed_property_law_0917.html
A7: PA | B7: Pennsylvania | C7: 2 | D7: Wages / commissions - 2 years per the PA Treasury Dormancy Matrix as summarized in search results (cited there as 72 P.S. 1301.5). NOT verified from the statute text in this session. | E7: 3 | F7: General dormancy period 3 years for most property types (72 P.S. 1301.1 et seq.) per secondary sources. | G7: April 15 | H7: December 31 (per secondary sources; NOT verified from statute in this session) | I7: 46387 | J7: Written notice by first-class mail 60 to 120 days before the April 15 deadline for property of $50 or more with a usable address. | K7: PA's formal amnesty program ended 10/31/2010. Interest of 12% per year from the date the property was due is cited by secondary sources. Ask PA Treasury about current voluntary compliance terms. | L7: All PA facts come from secondary summaries (PA Treasury Dormancy Matrix as quoted, Sovos, UPPO). Statute and Treasury pages were blocked in this session. | M7: SHORT | N7: PA Treasury's dormancy matrix lists wages/commissions at 2 years without an employee limitation in the sources found. 3-year general rule is the fallback. Not verified from statute text. | O7: https://www.patreasury.gov/pdf/unclaimed-property/Dormancy-Matrix.pdf ; https://www.patreasury.gov/unclaimed-property/holders/ ; https://sovos.com/tax-reporting/unclaimed-property-laws-by-state/pennsylvania/
A8: FL | B8: Florida | C8: 1 | D8: Fla. Stat. 717.115: unpaid WAGES owing in the ordinary course of business unclaimed for more than 1 year after becoming payable. Whether independent-contractor commissions are 'wages' here is not settled in the sources found - if not, the 5-year general rule applies. | E8: 5 | F8: Fla. Stat. 717.102(1): general 5-year dormancy period for other intangible property. | G8: Before May 1, covering the preceding calendar year (Fla. Stat. 717.117) | H8: December 31 | I8: 46387 | J8: Report must list owners with property of $50 or more; due-diligence notice requirement in 717.117 (threshold and timing not verified from statute text in this session). | K8: Florida has a Voluntary Disclosure program: no penalties, 5-year look-back instead of 10, 2-year audit window after acceptance (per secondary summary of Florida DFS program). | L8: Dormancy periods and report date confirmed from search summaries of the statute; statute pages blocked. Gallery = Florida is an ASSUMPTION. | M8: LONG | N8: Fla. Stat. 717.115 covers 'unpaid wages'. Nothing found extends it to independent-contractor commissions, so the 5-year general rule is the likely test. Confirm with counsel. | O8: https://www.flsenate.gov/Laws/Statutes/2024/717.115 ; https://www.flsenate.gov/Laws/Statutes/2024/717.102 ; https://flsenate.gov/Laws/Statutes/2024/717.117 ; https://www.fltreasurehunt.gov/Holder.jsp
A9: AL | B9: Alabama | C9: 1 | D9: Ala. Code 35-12-72: 'wages or other compensation for personal services' presumed abandoned 1 year after the compensation becomes payable. 'Other compensation for personal services' plausibly reaches independent-contractor commissions. | E9: 3 | F9: Ala. Code 35-12-72: all other property 3 years after the owner's right to demand it or the obligation to pay arises, whichever is first. | G9: November 1, covering the 12 months preceding July 1 | H9: June 30 | I9: 46568 | J9: Aggregate/reporting threshold $50 per secondary sources; due-diligence notice rule (35-12-77) not verified in this session. | K9: Not researched in this session. | L9: Dormancy periods confirmed from search summaries of the Code; Code pages blocked. Leading Edge = Alabama is an ASSUMPTION. | M9: SHORT | N9: Ala. Code 35-12-72 covers 'wages or other compensation for personal services', so independent-contractor commissions plausibly fall under the 1-year rule. 3-year general rule is the fallback. | O9: https://law.justia.com/codes/alabama/2023/title-35/chapter-12/article-2/article-2a/section-35-12-72 ; https://treasury.alabama.gov/alabama-treasury-law/unclaimed-property-law/ ; https://unclaimed.org/reporting/alabama/
A10: MO | B10: Missouri (HQ / possible state of formation) | C10: 3 | D10: RSMo 447.536 as amended by HB 1075 (2014): payroll/wages dormancy reduced from 5 to 3 years effective 1/1/2015. | E10: 5 | F10: RSMo 447.536: general 5-year dormancy period for most property types. | G10: November 1 | H10: June 30 | I10: 46568 | J10: Due diligence letter required when the owner is due $50 or more (Missouri Treasurer guidance). | K10: Not researched in this session. | L10: Missouri matters only under the SECOND priority rule (Texas v. New Jersey, 379 U.S. 674 (1965)): property whose owner address is unknown goes to the holder's state of incorporation/formation - which is the entity's formation state, NOT its headquarters city. Missouri also has a business-to-business exclusion (HB 1075, 2014) for checks/credits owed to a business entity in the ordinary course of business. | M10: LONG | N10: Missouri's 3-year rule is for payroll checks; commissions to non-employees would fall under the 5-year general rule. Applies only if an LLC is formed in Missouri and the owner's address is unknown. | O10: https://revisor.mo.gov/main/OneSection.aspx?section=447.536 ; https://treasurer.mo.gov/UCP/ReportingUnclaimedProperty.aspx ; https://ryan.com/about-ryan/news-and-insights/2014/missouri-legislation-adds-unclaimed-property-business-to-business-exclusions-and-other-changes/
A11: DC | B11: District of Columbia | D11: Not researched - DC accrued balance is $0. | F11: Not researched. | L11: Not researched. | N11: Not researched.
A13: Priority rules (Texas v. New Jersey, 379 U.S. 674 (1965)): (1) the state of the owner's last-known address on the holder's books; (2) if no address, the holder's state of incorporation/formation. The user confirmed that for many older checks the agent is unknown: those items fall under rule (2) and go to the STATE WHERE EACH LLC WAS FORMED (still to be provided), not to the office's state and not to Kansas City. Private retention of amounts owed to others ('private escheat') is not permitted by any state; an unknown owner does not make the money the company's.
A14: Blue = hardcoded inputs you can change. All dormancy periods are expressed in years and are applied from the DEPOSIT DATE in the cash-requirements workbook as a proxy for the date the amount became payable - the true trigger is when the agent's share became payable, which may be earlier (closing date) or later.
